Workbook
Name IQ_DAILY: 500000

Sheet Disclaimer
B2: Project Demeter - Financial Model
B4: DISCLAIMER This document and any other materials accompanying this document (collectively, the “Materials”) are provided on a non-binding and non-reliance basis and are for general informational and marketing purposes only. By accepting any Materials, the recipient acknowledges and agrees to the matters set out below. The Materials have been prepared by Eastdil Secured Limited (the “Advisor”) to obtain indications of interest only. The Materials do not constitute an offer or invitation to make an investment, in any form, in the opportunity discussed herein. Provision of the Materials is not intended to create any kind of contractual or fiduciary relationship between the recipient and the Sponsor or Advisor. Any offer or related transaction will only be made on the basis of the completion of the recipient’s due diligence exercise, and the negotiation and execution of full documentation. The Materials have been prepared on the basis of information obtained from Advisor’s client (the “Sponsor”) and other sources considered to be reliable. Neither the Advisor nor the Sponsor have verified information contained in the Materials or the underlying sources. This is because the Advisor and Sponsor anticipate that the intended recipient will complete their own due diligence exercise and obtain appropriate professional advice on these matters. The Advisor and the Sponsor do not undertake any duty or obligation to update the information. Neither the Advisor nor the Sponsor makes or gives any representation, warranty or guarantee, whether express or implied, that the information contained in the Materials or otherwise supplied to the recipient, at any time by or on behalf of the Advisor or the Sponsor whether in writing or not is complete or accurate or up to date, or that reasonable care has been taken in compiling, preparing or furnishing the information. The Materials provide a guide only and are not intended to be exhaustive. They should not be used as the basis of any credit analysis or other evaluation, they do not contain disclosure of any of the risks associated with the opportunity, and they are not to be construed as investment, tax or legal advice in relation to the relevant subject matter. Any opinions or estimates contained in the Materials represent the judgement of the Advisor at the time the Materials are produced and these are subject to change without notice. The Materials may contain statements, opinions, estimates, targets or projections that are forward looking and which include projections of future financial performance, anticipated growth strategies and anticipated trends and are subject to numerous risks, uncertainties and assumptions. Such statements or projections are based on current expectations and projections about future events and actual results could differ materially in light of actual events, levels of activity, performance or achievements. Estimates or forecasts in the Materials should not be interpreted as a promise or representation by the Advisor or the Sponsor as to future matters and nothing contained in the Materials should be relied upon as a representation as to future matters. Each recipient is responsible for making its own credit analysis and its own independent assessment of the relevant subject matter and such independent investigation as it considers necessary or appropriate for determining whether to participate in the relevant investment. The Materials have been prepared to obtain indications of interest only. The Materials do not constitute an offer or invitation or recommendation to buy or subscribe any securities or make an investment, in any form and in any jurisdiction, in the opportunity discussed herein. Provision of the Materials is not intended to create any kind of contractual or fiduciary relationship between the Advisor and the recipient or the Sponsor and the recipient of the Materials. Neither the Advisor nor the Sponsor accepts or assumes responsibility or liability of any kind (whether for negligence or otherwise) to any of the recipients of the Materials or to any other person for any action taken or omitted to be taken by any party in connection with or arising in any way from or in relation to the information contained in the Materials. None of the Advisor, the Sponsor or any of their or their affiliates’ respective directors, officers, employees, agents, partners or professional advisors shall be liable for any direct, indirect or consequential loss or damage suffered by any person as a result of relying on any statement contained in the Materials or any such other information. The Materials are confidential and are not to be used for any other purpose or made available to any other person without the express written consent of the Advisor. Each recipient should also be aware that some of the information may constitute material non-public information concerning Stonegate or its securities and that the use of that information may be regulated or prohibited by applicable legislation relating to insider dealing. By receipt of the Materials, each recipient undertakes not to use any of the Materials for any unlawful purpose. Each recipient should therefore take appropriate advice as to the use to which such information may lawfully be put. The Materials and any use thereof are subject to the respective non-disclosure agreement that each recipient entered into in respect of the opportunity discussed herein prior to receiving the Materials. Eastdil Secured Limited is a company incorporated under English law with its registered office at One Berkeley Street, London, W1J 8DJ. Eastdil Secured Limited is registered with the UK’s Companies House under number 12751924. Eastdil Secured © 2026. All Rights Reserved. PUB25.

Sheet Assumptions>>>

Sheet Dashboard
C3: Project Demeter
C4: Dashboard
C6: Key Inputs
C8: Valuation Assumptions | H8: Business Plan Levers
C9: Entry
C10: Entry Multiple (FY26 Outlet EBITDA) | D10: 12 | H10: Growth Capex (IM p.84)
C11: Purchasers' Costs | D11: 0.01 | H11: On / Off Toggle | I11: 1 | J11: (1 = On; 0 = Off)
H12: Target ROI | I12: 0.45
C13: Exit | H13: Growth Capex Spend per Project | I13: 40000
C14: Exit Multiple | D14: 12 | H14: # of Pubs Invested per Portfolio p.a. | I14: 42
C15: Sales Costs | D15: 0.01 | H15: Average Growth Capex Spend p.a. | I15: =-AVERAGE(Portfolio!O74:S74) -> 1482901.7
C17: Operational Assumptions | H17: Disposals (IM p.85)
H18: On / Off Toggle | I18: 1 | J18: (1 = On; 0 = Off)
C19: BCF (Growth Rate per Barrel) | H19: Disposal Multiple | I19: 13
C20: Pricing vs CPI | D20: 0.02 | H20: # of Pubs Disposed per Portfolio p.a. | I20: 16
C21: COGS Baseline | D21: 0.02 | E21: (Flat, CPI, RPI or Fixed Growth) | H21: Average Disposal Proceeds p.a. | I21: =AVERAGE(Portfolio!O75:S75) -> 23668419
C22: COGS vs Baseline | D22: 0
C23: Dist & Disp Baseline | D23: 0.02 | E23: (Flat, CPI, RPI or Fixed Growth) | H23: Surplus land (IM p.86)
H24: On / Off Toggle | I24: 1 | J24: (1 = On; 0 = Off)
C25: WSM (Absolute Growth Rate) | H25: Total Surplus land Proceeds | I25: 17500000
C26: Sales | D26: 0 | H26: Average Sale Proceeds p.a. | I26: =AVERAGE(Portfolio!O76:S76) -> 3500000
C27: Discounts | D27: 0
C28: COGS | D28: 0 | H28: Financing Assumptions
C29: Dist & Disp | D29: 0 | H29: EBITDA Multiple | I29: 7
H30: Margin | I30: 0.0475
C31: Other Assumptions | H31: Interest Method | I31: Current
C32: Maintenance Capex per Pub | D32: 8000 | H32: Type | I32: Fixed
C33: Corporate Overheads per Pub | D33: 8700 | H33: 5Y Swap | I33: 0.04026
C34: Bad Debt as % of EBITDA | D34: -0.015 | H34: Commitment Fee % | I34: 0
C35: # of Closed Pubs per Portfolio p.a. | D35: 10 | E35: ='Detailed Assumptions'!E108 -> 0.032467532 | H35: Commitment Fee Method | I35: Current
H36: UFF | I36: 0.01
H37: Amortisation | I37: 0
H38: Exit Fee | I38: 0.01
H39: Release Pricing Premium | I39: 0.15
H40: Implied LTV (%) | I40: =I29/D10 -> 0.58333333
C42: Key Outputs
C44: Valuation | H44: Returns
I45: Unlevered | J45: Levered
C46: Entry Purchase Price | D46: =-'Returns Analysis'!Q43 -> 3.460193e+08 | H46: IRR | I46: ='Returns Analysis'!I55 -> 0.14414125 | J46: ='Returns Analysis'!J55 -> 0.1913599
C47: Entry FY26 Outlet EBITDA Multiple | D47: =D$46/E47 -> 12 | E47: ='Returns Analysis'!I28 -> 28834942 | H47: Equity Multiple | I47: ='Returns Analysis'!I58 -> 1.6857874 | J47: ='Returns Analysis'!J58 -> 2.0653518
C48: Entry FY26 Corporate EBITDA Multiple | D48: =D$46/E48 -> 13.229393 | E48: ='Returns Analysis'!I28+'Returns Analysis'!I30 -> 26155342 | H48: Year 1 Cash-on-Cash | I48: ='Returns Analysis'!I59 -> 0.12662551 | J48: ='Returns Analysis'!J59 -> 0.085900223
C49: Entry Price per Pub | D49: =D$46/E49 -> 1123439.3 | E49: =Portfolio!N9 -> 308 | H49: Year 5 Cash-on-Cash | I49: ='Returns Analysis'!I60 -> 0.15528693 | J49: ='Returns Analysis'!J60 -> 0.10451077
C51: Sources & Uses
C53: Sources | D53: Amount | E53: % of Total | H53: Uses | I53: Amount | J53: % of Total
C54: Day-1 Equity | D54: =-'Returns Analysis'!Q50 -> 1.4965335e+08 | E54: =D54/D$56 -> 0.42821782 | H54: Day-1 Purchase Price | I54: =D46 -> 3.460193e+08 | J54: =I54/I$56 -> 0.99009901
C55: Day-1 Debt Drawdown | D55: ='Returns Analysis'!Q49 -> 1.9982615e+08 | E55: =D55/D$56 -> 0.57178218 | H55: Transaction Costs | I55: =-'Returns Analysis'!Q45 -> 3460193 | J55: =I55/I$56 -> 0.0099009901
C56: Total Day-1 Sources | D56: =SUM(D54:D55) -> 3.494795e+08 | E56: =D56/D$56 -> 1 | H56: Total Day-1 Sources | I56: =SUM(I54:I55) -> 3.494795e+08 | J56: =I56/I$56 -> 1
C58: Summary Cashflow
D60: ='Detailed Assumptions'!$E$17 -> FY26E | E60: ='Detailed Assumptions'!$F$17 -> FY27E | F60: ='Detailed Assumptions'!$G$17 -> FY28E | G60: ='Detailed Assumptions'!$H$17 -> FY29E | H60: ='Detailed Assumptions'!$I$17 -> FY30E | I60: ='Detailed Assumptions'!$J$17 -> FY31E | J60: FY26E-FY31E CAGR
C61: # of Pubs | D61: =Portfolio!N9 -> 308 | E61: =Portfolio!O9 -> 292 | F61: =Portfolio!P9 -> 276 | G61: =Portfolio!Q9 -> 260 | H61: =Portfolio!R9 -> 244 | I61: =Portfolio!S9 -> 228
C63: BCF Volumes (Barrels) | D63: =Portfolio!N19 -> 46171.62 | E63: =Portfolio!O19 -> 45875.273 | F63: =Portfolio!P19 -> 44232.509 | G63: =Portfolio!Q19 -> 42482.492 | H63: =Portfolio!R19 -> 40663.946 | I63: =Portfolio!S19 -> 38757.829 | J63: =IFERROR(((I63/D63)^(1/5))-1,0) -> -0.034400868
C65: Drinks gross profit (BCF + WSM) | D65: ='Returns Analysis'!I22 -> 16220326 | E65: ='Returns Analysis'!J22 -> 16977330 | F65: ='Returns Analysis'!K22 -> 17206443 | G65: ='Returns Analysis'!L22 -> 17328213 | H65: ='Returns Analysis'!M22 -> 17347419 | I65: ='Returns Analysis'!N22 -> 17286720 | J65: =IFERROR(((I65/D65)^(1/5))-1,0) -> 0.012816115
C66: Total rental income | D66: ='Returns Analysis'!I23 -> 11314203 | E66: ='Returns Analysis'!J23 -> 11610486 | F66: ='Returns Analysis'!K23 -> 11569977 | G66: ='Returns Analysis'!L23 -> 11476062 | H66: ='Returns Analysis'!M23 -> 11310608 | I66: ='Returns Analysis'!N23 -> 11087204 | J66: =IFERROR(((I66/D66)^(1/5))-1,0) -> -0.0040452348
C67: Total other income | D67: ='Returns Analysis'!I24 -> 1964702 | E67: ='Returns Analysis'!J24 -> 1929539.6 | F67: ='Returns Analysis'!K24 -> 1824052.2 | G67: ='Returns Analysis'!L24 -> 1718564.9 | H67: ='Returns Analysis'!M24 -> 1613077.5 | I67: ='Returns Analysis'!N24 -> 1507590.1 | J67: =IFERROR(((I67/D67)^(1/5))-1,0) -> -0.051587391
C68: Net income (drinks GP + rent + other income) | D68: ='Returns Analysis'!I25 -> 29499231 | E68: ='Returns Analysis'!J25 -> 30517356 | F68: ='Returns Analysis'!K25 -> 30600472 | G68: ='Returns Analysis'!L25 -> 30522840 | H68: ='Returns Analysis'!M25 -> 30271105 | I68: ='Returns Analysis'!N25 -> 29881514 | J68: =IFERROR(((I68/D68)^(1/5))-1,0) -> 0.0025784846
C70: Total pub costs | D70: ='Returns Analysis'!I27 -> -664289.16 | E70: ='Returns Analysis'!J27 -> -665448.32 | F70: ='Returns Analysis'!K27 -> -641649.83 | G70: ='Returns Analysis'!L27 -> -616633.22 | H70: ='Returns Analysis'!M27 -> -590359.28 | I70: ='Returns Analysis'!N27 -> -562787.73 | J70: =IFERROR(((I70/D70)^(1/5))-1,0) -> -0.032619138
C71: Outlet EBITDA | D71: ='Returns Analysis'!I28 -> 28834942 | E71: ='Returns Analysis'!J28 -> 29851908 | F71: ='Returns Analysis'!K28 -> 29958822 | G71: ='Returns Analysis'!L28 -> 29906207 | H71: ='Returns Analysis'!M28 -> 29680745 | I71: ='Returns Analysis'!N28 -> 29318726 | J71: =IFERROR(((I71/D71)^(1/5))-1,0) -> 0.003333247
C73: Overheads | D73: ='Returns Analysis'!I30 -> -2679600 | E73: ='Returns Analysis'!J30 -> -2698178 | F73: ='Returns Analysis'!K30 -> -2614763 | G73: ='Returns Analysis'!L30 -> -2521776.6 | H73: ='Returns Analysis'!M30 -> -2419207.9 | I73: ='Returns Analysis'!N30 -> -2311200.4 | J73: =IFERROR(((I73/D73)^(1/5))-1,0) -> -0.02914689
C74: Corporate EBITDA | D74: ='Returns Analysis'!I31 -> 26155342 | E74: ='Returns Analysis'!J31 -> 27153730 | F74: ='Returns Analysis'!K31 -> 27344059 | G74: ='Returns Analysis'!L31 -> 27384430 | H74: ='Returns Analysis'!M31 -> 27261537 | I74: ='Returns Analysis'!N31 -> 27007526 | J74: =IFERROR(((I74/D74)^(1/5))-1,0) -> 0.0064330263
C76: Maintenance capex | D76: ='Returns Analysis'!I33 -> -3065576.1 | E76: ='Returns Analysis'!J33 -> -2388160 | F76: ='Returns Analysis'!K33 -> -2302752 | G76: ='Returns Analysis'!L33 -> -2212972.4 | H76: ='Returns Analysis'!M33 -> -2118680.5 | I76: ='Returns Analysis'!N33 -> -2019731.8 | J76: =IFERROR(((I76/D76)^(1/5))-1,0) -> -0.080066742
C77: Bad debts | D77: ='Returns Analysis'!I34 -> -432524.13 | E77: ='Returns Analysis'!J34 -> -447778.62 | F77: ='Returns Analysis'!K34 -> -449382.33 | G77: ='Returns Analysis'!L34 -> -448593.1 | H77: ='Returns Analysis'!M34 -> -445211.18 | I77: ='Returns Analysis'!N34 -> -439780.9 | J77: =IFERROR(((I77/D77)^(1/5))-1,0) -> 0.003333247
C78: Security costs re closed sites | D78: ='Returns Analysis'!I35 -> -300000 | E78: ='Returns Analysis'!J35 -> -307402.93 | F78: ='Returns Analysis'!K35 -> -314526.43 | G78: ='Returns Analysis'!L35 -> -321272.72 | H78: ='Returns Analysis'!M35 -> -327569.22 | I78: ='Returns Analysis'!N35 -> -333924.15 | J78: =IFERROR(((I78/D78)^(1/5))-1,0) -> 0.021657473
C79: Normalised operating CF | D79: ='Returns Analysis'!I36 -> 22357242 | E79: ='Returns Analysis'!J36 -> 24010388 | F79: ='Returns Analysis'!K36 -> 24277398 | G79: ='Returns Analysis'!L36 -> 24401592 | H79: ='Returns Analysis'!M36 -> 24370076 | I79: ='Returns Analysis'!N36 -> 24214089 | J79: =IFERROR(((I79/D79)^(1/5))-1,0) -> 0.016084866
C81: Growth capex | D81: ='Returns Analysis'!I38 -> -1391870.9 | E81: ='Returns Analysis'!J38 -> -1597966.6 | F81: ='Returns Analysis'!K38 -> -1546113.4 | G81: ='Returns Analysis'!L38 -> -1488519.2 | H81: ='Returns Analysis'!M38 -> -1425078.2 | I81: ='Returns Analysis'!N38 -> -1356831.2 | J81: =IFERROR(((I81/D81)^(1/5))-1,0) -> -0.0050863927
C82: Asset disposal proceeds | D82: ='Returns Analysis'!I39 -> 0 | E82: ='Returns Analysis'!J39 -> 21007265 | F82: ='Returns Analysis'!K39 -> 22302773 | G82: ='Returns Analysis'!L39 -> 23631372 | H82: ='Returns Analysis'!M39 -> 24988348 | I82: ='Returns Analysis'!N39 -> 26412339 | J82: 0
C83: Surplus land disposal proceeds | D83: ='Returns Analysis'!I40 -> 0 | E83: ='Returns Analysis'!J40 -> 833333.33 | F83: ='Returns Analysis'!K40 -> 2500000 | G83: ='Returns Analysis'!L40 -> 4166666.7 | H83: ='Returns Analysis'!M40 -> 5000000 | I83: ='Returns Analysis'!N40 -> 5000000 | J83: 0
C84: Portfolio net cash flow | D84: ='Returns Analysis'!I41 -> 20965371 | E84: ='Returns Analysis'!J41 -> 44253020 | F84: ='Returns Analysis'!K41 -> 47534058 | G84: ='Returns Analysis'!L41 -> 50711112 | H84: ='Returns Analysis'!M41 -> 52933346 | I84: ='Returns Analysis'!N41 -> 54269597 | J84: =IFERROR(((I84/D84)^(1/5))-1,0) -> 0.20951375
C86: Purchase Price | D86: ='Returns Analysis'!I43 -> -3.460193e+08 | E86: ='Returns Analysis'!J43 -> 0 | F86: ='Returns Analysis'!K43 -> 0 | G86: ='Returns Analysis'!L43 -> 0 | H86: ='Returns Analysis'!M43 -> 0 | I86: ='Returns Analysis'!N43 -> 0 | J86: 0
C87: Exit Proceeds | D87: ='Returns Analysis'!I44 -> 0 | E87: ='Returns Analysis'!J44 -> 0 | F87: ='Returns Analysis'!K44 -> 0 | G87: ='Returns Analysis'!L44 -> 0 | H87: ='Returns Analysis'!M44 -> 0 | I87: ='Returns Analysis'!N44 -> 3.4287577e+08 | J87: 0
C88: Transaction Costs | D88: ='Returns Analysis'!I45 -> -3460193 | E88: ='Returns Analysis'!J45 -> 0 | F88: ='Returns Analysis'!K45 -> 0 | G88: ='Returns Analysis'!L45 -> 0 | H88: ='Returns Analysis'!M45 -> 0 | I88: ='Returns Analysis'!N45 -> -3428757.7 | J88: 0
C89: Unlevered portfolio net cash flow | D89: ='Returns Analysis'!I46 -> -3.2851413e+08 | E89: ='Returns Analysis'!J46 -> 44253020 | F89: ='Returns Analysis'!K46 -> 47534058 | G89: ='Returns Analysis'!L46 -> 50711112 | H89: ='Returns Analysis'!M46 -> 52933346 | I89: ='Returns Analysis'!N46 -> 3.9371661e+08 | J89: 0
C91: Financing Cashflows | D91: ='Returns Analysis'!I49 -> 1.9982615e+08 | E91: ='Returns Analysis'!J49 -> -31397764 | F91: ='Returns Analysis'!K49 -> -31005739 | G91: ='Returns Analysis'!L49 -> -30559065 | H91: ='Returns Analysis'!M49 -> -30052726 | I91: ='Returns Analysis'!N49 -> -1.5319156e+08 | J91: 0
C92: Levered portfolio net cash flow | D92: ='Returns Analysis'!I50 -> -1.2868798e+08 | E92: ='Returns Analysis'!J50 -> 12855256 | F92: ='Returns Analysis'!K50 -> 16528319 | G92: ='Returns Analysis'!L50 -> 20152047 | H92: ='Returns Analysis'!M50 -> 22880619 | I92: ='Returns Analysis'!N50 -> 2.4052505e+08 | J92: 0

Sheet Detailed Assumptions
D2: Note: all figures throughout the model are in £ unless otherwise noted.
B3: X | D3: Drivers Toggles
E4: =Dashboard!I11 -> 1 | F4: =Dashboard!I18 -> 1
E5: Growth Capex | F5: Disposals | G5: Surplus Land
D6: Portfolio | E6: =IF(E$4=1,1,0) -> 1 | F6: =IF(F$4=1,1,0) -> 1 | G6: =Dashboard!$I$24 -> 1
B10: X | D10: Transaction Timing
D12: Start date | E12: 46296 | F12: Note: Should always be inputted at the beginning of the month: 01/xx/xx
D13: Exit date | E13: =EOMONTH(E12,12*5-1) -> 48121
B15: X | D15: Growth assumptions
E17: FY26E | F17: FY27E | G17: FY28E | H17: FY29E | I17: FY30E | J17: FY31E
D19: BCF Volumes
D20: Value | F20: 0 | G20: 0 | H20: 0 | I20: 0 | J20: 0
D21: Mainstream | F21: 0 | G21: 0 | H21: 0 | I21: 0 | J21: 0
D22: Premium Mainstream | F22: 0 | G22: 0 | H22: 0 | I22: 0 | J22: 0
D23: Premium | F23: 0 | G23: 0 | H23: 0 | I23: 0 | J23: 0
D25: BCF assumptions
D26: Pricing vs CPI | E26: =Dashboard!D20 -> 0.02
D27: COGS vs Baseline | E27: =Dashboard!D22 -> 0
D28: Discounts vs CPI | E28: =E26 -> 0.02
D29: Duty per Barrel | E29: 125 | F29: Note: Price per barrel is calculated on the price per barrel excl. £125 of duty. Therefore the growth rate is applied to a smaller base figure than is shown in the cashflows and growth in pricing is therefore below CPI + X% assumed here. Duty is a cost of sale which is recouped directly from the publican on a 1:1 basis.
D31: WSM assumptions
D32: Sales growth | E32: =Dashboard!D26 -> 0
D33: Discounts | E33: =Dashboard!D27 -> 0
D34: Cost of sales | E34: =Dashboard!D28 -> 0
D35: Dist & disp | E35: =Dashboard!D29 -> 0
D37: Inflation assumptions
D38: Flat Forecast | E38: Flat | F38: 0 | G38: 0 | H38: 0 | I38: 0 | J38: 0
D39: CPI forecast | E39: CPI | F39: 0.024676438 | G39: 0.023173151 | H39: 0.021449041 | I39: 0.01959863 | J39: 0.019400274
D40: RPI forecast | E40: RPI | F40: 0.035127123 | G40: 0.033197534 | H40: 0.031849589 | I40: 0.025769589 | J40: 0.021623014
D42: Inflation-driven assumptions
D43: Cost of sales / barrel | E43: =Dashboard!D21 -> 0.02 | F43: =IF(ISNUMBER($E43),$E43,INDEX(F$38:F$40,MATCH($E43,$E$38:$E$40,0))) -> 0.02 | G43: =IF(ISNUMBER($E43),$E43,INDEX(G$38:G$40,MATCH($E43,$E$38:$E$40,0))) -> 0.02 | H43: =IF(ISNUMBER($E43),$E43,INDEX(H$38:H$40,MATCH($E43,$E$38:$E$40,0))) -> 0.02 | I43: =IF(ISNUMBER($E43),$E43,INDEX(I$38:I$40,MATCH($E43,$E$38:$E$40,0))) -> 0.02 | J43: =IF(ISNUMBER($E43),$E43,INDEX(J$38:J$40,MATCH($E43,$E$38:$E$40,0))) -> 0.02
D44: Dist & disp / barrel (BCF) | E44: =Dashboard!D23 -> 0.02 | F44: =IF(ISNUMBER($E44),$E44,INDEX(F$38:F$40,MATCH($E44,$E$38:$E$40,0))) -> 0.02 | G44: =IF(ISNUMBER($E44),$E44,INDEX(G$38:G$40,MATCH($E44,$E$38:$E$40,0))) -> 0.02 | H44: =IF(ISNUMBER($E44),$E44,INDEX(H$38:H$40,MATCH($E44,$E$38:$E$40,0))) -> 0.02 | I44: =IF(ISNUMBER($E44),$E44,INDEX(I$38:I$40,MATCH($E44,$E$38:$E$40,0))) -> 0.02 | J44: =IF(ISNUMBER($E44),$E44,INDEX(J$38:J$40,MATCH($E44,$E$38:$E$40,0))) -> 0.02
D45: Tie Release Fees | E45: RPI | F45: =IF(ISNUMBER($E45),$E45,INDEX(F$38:F$40,MATCH($E45,$E$38:$E$40,0))) -> 0.035127123 | G45: =IF(ISNUMBER($E45),$E45,INDEX(G$38:G$40,MATCH($E45,$E$38:$E$40,0))) -> 0.033197534 | H45: =IF(ISNUMBER($E45),$E45,INDEX(H$38:H$40,MATCH($E45,$E$38:$E$40,0))) -> 0.031849589 | I45: =IF(ISNUMBER($E45),$E45,INDEX(I$38:I$40,MATCH($E45,$E$38:$E$40,0))) -> 0.025769589 | J45: =IF(ISNUMBER($E45),$E45,INDEX(J$38:J$40,MATCH($E45,$E$38:$E$40,0))) -> 0.021623014
D46: Other income | E46: Flat | F46: =IF(ISNUMBER($E46),$E46,INDEX(F$38:F$40,MATCH($E46,$E$38:$E$40,0))) -> 0 | G46: =IF(ISNUMBER($E46),$E46,INDEX(G$38:G$40,MATCH($E46,$E$38:$E$40,0))) -> 0 | H46: =IF(ISNUMBER($E46),$E46,INDEX(H$38:H$40,MATCH($E46,$E$38:$E$40,0))) -> 0 | I46: =IF(ISNUMBER($E46),$E46,INDEX(I$38:I$40,MATCH($E46,$E$38:$E$40,0))) -> 0 | J46: =IF(ISNUMBER($E46),$E46,INDEX(J$38:J$40,MATCH($E46,$E$38:$E$40,0))) -> 0
D47: Pub costs | E47: 0.02 | F47: =IF(ISNUMBER($E47),$E47,INDEX(F$38:F$40,MATCH($E47,$E$38:$E$40,0))) -> 0.02 | G47: =IF(ISNUMBER($E47),$E47,INDEX(G$38:G$40,MATCH($E47,$E$38:$E$40,0))) -> 0.02 | H47: =IF(ISNUMBER($E47),$E47,INDEX(H$38:H$40,MATCH($E47,$E$38:$E$40,0))) -> 0.02 | I47: =IF(ISNUMBER($E47),$E47,INDEX(I$38:I$40,MATCH($E47,$E$38:$E$40,0))) -> 0.02 | J47: =IF(ISNUMBER($E47),$E47,INDEX(J$38:J$40,MATCH($E47,$E$38:$E$40,0))) -> 0.02
D48: Maintenance capex | E48: 0.02 | F48: =IF(ISNUMBER($E48),$E48,INDEX(F$38:F$40,MATCH($E48,$E$38:$E$40,0))) -> 0.02 | G48: =IF(ISNUMBER($E48),$E48,INDEX(G$38:G$40,MATCH($E48,$E$38:$E$40,0))) -> 0.02 | H48: =IF(ISNUMBER($E48),$E48,INDEX(H$38:H$40,MATCH($E48,$E$38:$E$40,0))) -> 0.02 | I48: =IF(ISNUMBER($E48),$E48,INDEX(I$38:I$40,MATCH($E48,$E$38:$E$40,0))) -> 0.02 | J48: =IF(ISNUMBER($E48),$E48,INDEX(J$38:J$40,MATCH($E48,$E$38:$E$40,0))) -> 0.02
D49: Overheads | E49: CPI | F49: =IF(ISNUMBER($E49),$E49,INDEX(F$38:F$40,MATCH($E49,$E$38:$E$40,0))) -> 0.024676438 | G49: =IF(ISNUMBER($E49),$E49,INDEX(G$38:G$40,MATCH($E49,$E$38:$E$40,0))) -> 0.023173151 | H49: =IF(ISNUMBER($E49),$E49,INDEX(H$38:H$40,MATCH($E49,$E$38:$E$40,0))) -> 0.021449041 | I49: =IF(ISNUMBER($E49),$E49,INDEX(I$38:I$40,MATCH($E49,$E$38:$E$40,0))) -> 0.01959863 | J49: =IF(ISNUMBER($E49),$E49,INDEX(J$38:J$40,MATCH($E49,$E$38:$E$40,0))) -> 0.019400274
D50: Security costs re. closures | E50: CPI | F50: =IF(ISNUMBER($E50),$E50,INDEX(F$38:F$40,MATCH($E50,$E$38:$E$40,0))) -> 0.024676438 | G50: =IF(ISNUMBER($E50),$E50,INDEX(G$38:G$40,MATCH($E50,$E$38:$E$40,0))) -> 0.023173151 | H50: =IF(ISNUMBER($E50),$E50,INDEX(H$38:H$40,MATCH($E50,$E$38:$E$40,0))) -> 0.021449041 | I50: =IF(ISNUMBER($E50),$E50,INDEX(I$38:I$40,MATCH($E50,$E$38:$E$40,0))) -> 0.01959863 | J50: =IF(ISNUMBER($E50),$E50,INDEX(J$38:J$40,MATCH($E50,$E$38:$E$40,0))) -> 0.019400274
D52: Maintenance capex FY26F / pub / year | E52: =Dashboard!D32 -> 8000
D53: Bad debts / EBITDA | E53: =Dashboard!D34 -> -0.015
E55: =$E$17 -> FY26E | F55: =$F$17 -> FY27E | G55: =$G$17 -> FY28E | H55: =$H$17 -> FY29E | I55: =$I$17 -> FY30E | J55: =$J$17 -> FY31E | M55: =$E$17 -> FY26E | N55: =$F$17 -> FY27E | O55: =$G$17 -> FY28E | P55: =$H$17 -> FY29E | Q55: =$I$17 -> FY30E | R55: =$J$17 -> FY31E | U55: =$E$17 -> FY26E | V55: =$F$17 -> FY27E | W55: =$G$17 -> FY28E | X55: =$H$17 -> FY29E | Y55: =$I$17 -> FY30E | Z55: =$J$17 -> FY31E | AC55: =$E$17 -> FY26E | AD55: =$F$17 -> FY27E | AE55: =$G$17 -> FY28E | AF55: =$H$17 -> FY29E | AG55: =$I$17 -> FY30E | AH55: =$J$17 -> FY31E
D57: Value | L57: Mid-Market | T57: Upper Mid-Market | AB57: Premium
D58: Portfolio - Value | L58: Portfolio - Mid-Market | T58: Portfolio - Upper Mid-Market | AB58: Portfolio - Premium
B59: X | C59: Portfolio | D59: Portfolio
D60: BCF | L60: BCF | T60: BCF | AB60: BCF
D61: Volumes | F61: ='Detailed Assumptions'!$F$20 -> 0 | G61: ='Detailed Assumptions'!$G$20 -> 0 | H61: ='Detailed Assumptions'!$H$20 -> 0 | I61: ='Detailed Assumptions'!$I$20 -> 0 | J61: ='Detailed Assumptions'!$J$20 -> 0 | L61: Volumes | N61: ='Detailed Assumptions'!$F$21 -> 0 | O61: ='Detailed Assumptions'!$G$21 -> 0 | P61: ='Detailed Assumptions'!$H$21 -> 0 | Q61: ='Detailed Assumptions'!$I$21 -> 0 | R61: ='Detailed Assumptions'!$J$21 -> 0 | T61: Volumes | V61: ='Detailed Assumptions'!$F$22 -> 0 | W61: ='Detailed Assumptions'!$G$22 -> 0 | X61: ='Detailed Assumptions'!$H$22 -> 0 | Y61: ='Detailed Assumptions'!$I$22 -> 0 | Z61: ='Detailed Assumptions'!$J$22 -> 0 | AB61: Volumes | AD61: ='Detailed Assumptions'!$F$23 -> 0 | AE61: ='Detailed Assumptions'!$G$23 -> 0 | AF61: ='Detailed Assumptions'!$H$23 -> 0 | AG61: ='Detailed Assumptions'!$I$23 -> 0 | AH61: ='Detailed Assumptions'!$J$23 -> 0
D62: Pricing vs CPI | F62: =$E$26 -> 0.02 | G62: =$F62 -> 0.02 | H62: =$F62 -> 0.02 | I62: =$F62 -> 0.02 | J62: =$F62 -> 0.02 | L62: Pricing vs CPI | N62: =$E$26 -> 0.02 | O62: =$N62 -> 0.02 | P62: =$N62 -> 0.02 | Q62: =$N62 -> 0.02 | R62: =$N62 -> 0.02 | T62: Pricing vs CPI | V62: =$E$26 -> 0.02 | W62: =$V62 -> 0.02 | X62: =$V62 -> 0.02 | Y62: =$V62 -> 0.02 | Z62: =$V62 -> 0.02 | AB62: Pricing vs CPI | AD62: =$E$26 -> 0.02 | AE62: =$AD62 -> 0.02 | AF62: =$AD62 -> 0.02 | AG62: =$AD62 -> 0.02 | AH62: =$AD62 -> 0.02
D63: Pricing | F63: =$F$39+F62 -> 0.044676438 | G63: =$G$39+G62 -> 0.043173151 | H63: =$H$39+H62 -> 0.041449041 | I63: =$I$39+I62 -> 0.03959863 | J63: =$J$39+J62 -> 0.039400274 | L63: Pricing | N63: =$F$39+N62 -> 0.044676438 | O63: =$G$39+O62 -> 0.043173151 | P63: =$H$39+P62 -> 0.041449041 | Q63: =$I$39+Q62 -> 0.03959863 | R63: =$J$39+R62 -> 0.039400274 | T63: Pricing | V63: =$F$39+V62 -> 0.044676438 | W63: =$G$39+W62 -> 0.043173151 | X63: =$H$39+X62 -> 0.041449041 | Y63: =$I$39+Y62 -> 0.03959863 | Z63: =$J$39+Z62 -> 0.039400274 | AB63: Pricing | AD63: =$F$39+AD62 -> 0.044676438 | AE63: =$G$39+AE62 -> 0.043173151 | AF63: =$H$39+AF62 -> 0.041449041 | AG63: =$I$39+AG62 -> 0.03959863 | AH63: =$J$39+AH62 -> 0.039400274
D64: COGS vs Baseline | F64: =E27 -> 0 | G64: =$F64 -> 0 | H64: =$F64 -> 0 | I64: 0 | J64: =$F64 -> 0 | L64: COGS vs Baseline | N64: =$E$27 -> 0 | O64: =$N64 -> 0 | P64: =$N64 -> 0 | Q64: =$N64 -> 0 | R64: =$N64 -> 0 | T64: COGS vs Baseline | V64: =$E$27 -> 0 | W64: =$V64 -> 0 | X64: =$V64 -> 0 | Y64: =$V64 -> 0 | Z64: =$V64 -> 0 | AB64: COGS vs Baseline | AD64: =$E$27 -> 0 | AE64: =$AD64 -> 0 | AF64: =$AD64 -> 0 | AG64: =$AD64 -> 0 | AH64: =$AD64 -> 0
D65: Cost of sales per barrel | F65: =$F$43+F64 -> 0.02 | G65: =$G$43+G64 -> 0.02 | H65: =$H$43+H64 -> 0.02 | I65: =$I$43+I64 -> 0.02 | J65: =$J$43+J64 -> 0.02 | L65: Cost of sales per barrel | N65: =$F$43+N64 -> 0.02 | O65: =$G$43+O64 -> 0.02 | P65: =$H$43+P64 -> 0.02 | Q65: =$I$43+Q64 -> 0.02 | R65: =$J$43+R64 -> 0.02 | T65: Cost of sales per barrel | V65: =$F$43+V64 -> 0.02 | W65: =$G$43+W64 -> 0.02 | X65: =$H$43+X64 -> 0.02 | Y65: =$I$43+Y64 -> 0.02 | Z65: =$J$43+Z64 -> 0.02 | AB65: Cost of sales per barrel | AD65: =$F$43+AD64 -> 0.02 | AE65: =$G$43+AE64 -> 0.02 | AF65: =$H$43+AF64 -> 0.02 | AG65: =$I$43+AG64 -> 0.02 | AH65: =$J$43+AH64 -> 0.02
D66: Discounts | F66: =$E$28+INDEX($F$39:$J$39,MATCH(F55,$F$17:$J$17,0)) -> 0.044676438 | G66: =$E$28+INDEX($F$39:$J$39,MATCH(G55,$F$17:$J$17,0)) -> 0.043173151 | H66: =$E$28+INDEX($F$39:$J$39,MATCH(H55,$F$17:$J$17,0)) -> 0.041449041 | I66: =$E$28+INDEX($F$39:$J$39,MATCH(I55,$F$17:$J$17,0)) -> 0.03959863 | J66: =$E$28+INDEX($F$39:$J$39,MATCH(J55,$F$17:$J$17,0)) -> 0.039400274 | L66: Discounts | N66: =$E$28+INDEX($F$39:$J$39,MATCH(N55,$F$17:$J$17,0)) -> 0.044676438 | O66: =$E$28+INDEX($F$39:$J$39,MATCH(O55,$F$17:$J$17,0)) -> 0.043173151 | P66: =$E$28+INDEX($F$39:$J$39,MATCH(P55,$F$17:$J$17,0)) -> 0.041449041 | Q66: =$E$28+INDEX($F$39:$J$39,MATCH(Q55,$F$17:$J$17,0)) -> 0.03959863 | R66: =$E$28+INDEX($F$39:$J$39,MATCH(R55,$F$17:$J$17,0)) -> 0.039400274 | T66: Discounts | V66: =$E$28+INDEX($F$39:$J$39,MATCH(V55,$F$17:$J$17,0)) -> 0.044676438 | W66: =$E$28+INDEX($F$39:$J$39,MATCH(W55,$F$17:$J$17,0)) -> 0.043173151 | X66: =$E$28+INDEX($F$39:$J$39,MATCH(X55,$F$17:$J$17,0)) -> 0.041449041 | Y66: =$E$28+INDEX($F$39:$J$39,MATCH(Y55,$F$17:$J$17,0)) -> 0.03959863 | Z66: =$E$28+INDEX($F$39:$J$39,MATCH(Z55,$F$17:$J$17,0)) -> 0.039400274 | AB66: Discounts | AD66: =$E$28+INDEX($F$39:$J$39,MATCH(AD55,$F$17:$J$17,0)) -> 0.044676438 | AE66: =$E$28+INDEX($F$39:$J$39,MATCH(AE55,$F$17:$J$17,0)) -> 0.043173151 | AF66: =$E$28+INDEX($F$39:$J$39,MATCH(AF55,$F$17:$J$17,0)) -> 0.041449041 | AG66: =$E$28+INDEX($F$39:$J$39,MATCH(AG55,$F$17:$J$17,0)) -> 0.03959863 | AH66: =$E$28+INDEX($F$39:$J$39,MATCH(AH55,$F$17:$J$17,0)) -> 0.039400274
D68: WSM | L68: WSM | T68: WSM | AB68: WSM
D69: Sales | F69: =$E$32 -> 0 | G69: =F69 -> 0 | H69: =G69 -> 0 | I69: =H69 -> 0 | J69: =I69 -> 0 | L69: Sales | N69: =$E$32 -> 0 | O69: =N69 -> 0 | P69: =O69 -> 0 | Q69: =P69 -> 0 | R69: =Q69 -> 0 | T69: Sales | V69: =$E$32 -> 0 | W69: =V69 -> 0 | X69: =W69 -> 0 | Y69: =X69 -> 0 | Z69: =Y69 -> 0 | AB69: Sales | AD69: =$E$32 -> 0 | AE69: =AD69 -> 0 | AF69: =AE69 -> 0 | AG69: =AF69 -> 0 | AH69: =AG69 -> 0
D70: Cost of sales | F70: =$E$34 -> 0 | G70: =$E$34 -> 0 | H70: =$E$34 -> 0 | I70: =$E$34 -> 0 | J70: =$E$34 -> 0 | L70: Cost of sales | N70: =$E$34 -> 0 | O70: =$E$34 -> 0 | P70: =$E$34 -> 0 | Q70: =$E$34 -> 0 | R70: =$E$34 -> 0 | T70: Cost of sales | V70: =$E$34 -> 0 | W70: =$E$34 -> 0 | X70: =$E$34 -> 0 | Y70: =$E$34 -> 0 | Z70: =$E$34 -> 0 | AB70: Cost of sales | AD70: =$E$34 -> 0 | AE70: =$E$34 -> 0 | AF70: =$E$34 -> 0 | AG70: =$E$34 -> 0 | AH70: =$E$34 -> 0
D71: Discounts | F71: =$E$33 -> 0 | G71: =$E$33 -> 0 | H71: =$E$33 -> 0 | I71: =$E$33 -> 0 | J71: =$E$33 -> 0 | L71: Discounts | N71: =$E$33 -> 0 | O71: =$E$33 -> 0 | P71: =$E$33 -> 0 | Q71: =$E$33 -> 0 | R71: =$E$33 -> 0 | T71: Discounts | V71: =$E$33 -> 0 | W71: =$E$33 -> 0 | X71: =$E$33 -> 0 | Y71: =$E$33 -> 0 | Z71: =$E$33 -> 0 | AB71: Discounts | AD71: =$E$33 -> 0 | AE71: =$E$33 -> 0 | AF71: =$E$33 -> 0 | AG71: =$E$33 -> 0 | AH71: =$E$33 -> 0
D73: Rental Income | L73: Rental Income | T73: Rental Income | AB73: Rental Income
D74: Rental Income | F74: {=INDEX($F$40:$J$40,0,MATCH(F$55,$F$17:$J$17,0))*INDEX(Portfolio_Categorisation!$H$24:$H$27,MATCH(D58,Portfolio_Categorisation!$C$24:$C$27,0),0)+ INDEX($F$39:$J$39,0,MATCH(F$55,$F$17:$J$17,0))*INDEX(Portfolio_Categorisation!$I$24:$I$27,MATCH(D58,Portfolio_Categorisation!$C$24:$C$27,0),0)} -> 0.028427966 | G74: {=INDEX($F$40:$J$40,0,MATCH(G$55,$F$17:$J$17,0))*INDEX(Portfolio_Categorisation!$H$24:$H$27,MATCH(D58,Portfolio_Categorisation!$C$24:$C$27,0),0)+ INDEX($F$39:$J$39,0,MATCH(G$55,$F$17:$J$17,0))*INDEX(Portfolio_Categorisation!$I$24:$I$27,MATCH(D58,Portfolio_Categorisation!$C$24:$C$27,0),0)} -> 0.026771647 | H74: {=INDEX($F$40:$J$40,0,MATCH(H$55,$F$17:$J$17,0))*INDEX(Portfolio_Categorisation!$H$24:$H$27,MATCH(D58,Portfolio_Categorisation!$C$24:$C$27,0),0)+ INDEX($F$39:$J$39,0,MATCH(H$55,$F$17:$J$17,0))*INDEX(Portfolio_Categorisation!$I$24:$I$27,MATCH(D58,Portfolio_Categorisation!$C$24:$C$27,0),0)} -> 0.025182571 | I74: {=INDEX($F$40:$J$40,0,MATCH(I$55,$F$17:$J$17,0))*INDEX(Portfolio_Categorisation!$H$24:$H$27,MATCH(D58,Portfolio_Categorisation!$C$24:$C$27,0),0)+ INDEX($F$39:$J$39,0,MATCH(I$55,$F$17:$J$17,0))*INDEX(Portfolio_Categorisation!$I$24:$I$27,MATCH(D58,Portfolio_Categorisation!$C$24:$C$27,0),0)} -> 0.021813846 | J74: {=INDEX($F$40:$J$40,0,MATCH(J$55,$F$17:$J$17,0))*INDEX(Portfolio_Categorisation!$H$24:$H$27,MATCH(D58,Portfolio_Categorisation!$C$24:$C$27,0),0)+ INDEX($F$39:$J$39,0,MATCH(J$55,$F$17:$J$17,0))*INDEX(Portfolio_Categorisation!$I$24:$I$27,MATCH(D58,Portfolio_Categorisation!$C$24:$C$27,0),0)} -> 0.020198181 | L74: Rental Income | N74: {=INDEX($F$40:$J$40,0,MATCH(N$55,$F$17:$J$17,0))*INDEX(Portfolio_Categorisation!$H$24:$H$27,MATCH(L58,Portfolio_Categorisation!$C$24:$C$27,0),0)+ INDEX($F$39:$J$39,0,MATCH(N$55,$F$17:$J$17,0))*INDEX(Portfolio_Categorisation!$I$24:$I$27,MATCH(L58,Portfolio_Categorisation!$C$24:$C$27,0),0)} -> 0.029519439 | O74: {=INDEX($F$40:$J$40,0,MATCH(O$55,$F$17:$J$17,0))*INDEX(Portfolio_Categorisation!$H$24:$H$27,MATCH(L58,Portfolio_Categorisation!$C$24:$C$27,0),0)+ INDEX($F$39:$J$39,0,MATCH(O$55,$F$17:$J$17,0))*INDEX(Portfolio_Categorisation!$I$24:$I$27,MATCH(L58,Portfolio_Categorisation!$C$24:$C$27,0),0)} -> 0.027818597 | P74: {=INDEX($F$40:$J$40,0,MATCH(P$55,$F$17:$J$17,0))*INDEX(Portfolio_Categorisation!$H$24:$H$27,MATCH(L58,Portfolio_Categorisation!$C$24:$C$27,0),0)+ INDEX($F$39:$J$39,0,MATCH(P$55,$F$17:$J$17,0))*INDEX(Portfolio_Categorisation!$I$24:$I$27,MATCH(L58,Portfolio_Categorisation!$C$24:$C$27,0),0)} -> 0.026268807 | Q74: {=INDEX($F$40:$J$40,0,MATCH(Q$55,$F$17:$J$17,0))*INDEX(Portfolio_Categorisation!$H$24:$H$27,MATCH(L58,Portfolio_Categorisation!$C$24:$C$27,0),0)+ INDEX($F$39:$J$39,0,MATCH(Q$55,$F$17:$J$17,0))*INDEX(Portfolio_Categorisation!$I$24:$I$27,MATCH(L58,Portfolio_Categorisation!$C$24:$C$27,0),0)} -> 0.022458343 | R74: {=INDEX($F$40:$J$40,0,MATCH(R$55,$F$17:$J$17,0))*INDEX(Portfolio_Categorisation!$H$24:$H$27,MATCH(L58,Portfolio_Categorisation!$C$24:$C$27,0),0)+ INDEX($F$39:$J$39,0,MATCH(R$55,$F$17:$J$17,0))*INDEX(Portfolio_Categorisation!$I$24:$I$27,MATCH(L58,Portfolio_Categorisation!$C$24:$C$27,0),0)} -> 0.020430324 | T74: Rental Income | V74: {=INDEX($F$40:$J$40,0,MATCH(V$55,$F$17:$J$17,0))*INDEX(Portfolio_Categorisation!$H$24:$H$27,MATCH(T58,Portfolio_Categorisation!$C$24:$C$27,0),0)+ INDEX($F$39:$J$39,0,MATCH(V$55,$F$17:$J$17,0))*INDEX(Portfolio_Categorisation!$I$24:$I$27,MATCH(T58,Portfolio_Categorisation!$C$24:$C$27,0),0)} -> 0.029947219 | W74: {=INDEX($F$40:$J$40,0,MATCH(W$55,$F$17:$J$17,0))*INDEX(Portfolio_Categorisation!$H$24:$H$27,MATCH(T58,Portfolio_Categorisation!$C$24:$C$27,0),0)+ INDEX($F$39:$J$39,0,MATCH(W$55,$F$17:$J$17,0))*INDEX(Portfolio_Categorisation!$I$24:$I$27,MATCH(T58,Portfolio_Categorisation!$C$24:$C$27,0),0)} -> 0.028228927 | X74: {=INDEX($F$40:$J$40,0,MATCH(X$55,$F$17:$J$17,0))*INDEX(Portfolio_Categorisation!$H$24:$H$27,MATCH(T58,Portfolio_Categorisation!$C$24:$C$27,0),0)+ INDEX($F$39:$J$39,0,MATCH(X$55,$F$17:$J$17,0))*INDEX(Portfolio_Categorisation!$I$24:$I$27,MATCH(T58,Portfolio_Categorisation!$C$24:$C$27,0),0)} -> 0.026694535 | Y74: {=INDEX($F$40:$J$40,0,MATCH(Y$55,$F$17:$J$17,0))*INDEX(Portfolio_Categorisation!$H$24:$H$27,MATCH(T58,Portfolio_Categorisation!$C$24:$C$27,0),0)+ INDEX($F$39:$J$39,0,MATCH(Y$55,$F$17:$J$17,0))*INDEX(Portfolio_Categorisation!$I$24:$I$27,MATCH(T58,Portfolio_Categorisation!$C$24:$C$27,0),0)} -> 0.02271094 | Z74: {=INDEX($F$40:$J$40,0,MATCH(Z$55,$F$17:$J$17,0))*INDEX(Portfolio_Categorisation!$H$24:$H$27,MATCH(T58,Portfolio_Categorisation!$C$24:$C$27,0),0)+ INDEX($F$39:$J$39,0,MATCH(Z$55,$F$17:$J$17,0))*INDEX(Portfolio_Categorisation!$I$24:$I$27,MATCH(T58,Portfolio_Categorisation!$C$24:$C$27,0),0)} -> 0.020521308 | AB74: Rental Income | AD74: {=INDEX($F$40:$J$40,0,MATCH(AD$55,$F$17:$J$17,0))*INDEX(Portfolio_Categorisation!$H$24:$H$27,MATCH(AB58,Portfolio_Categorisation!$C$24:$C$27,0),0)+ INDEX($F$39:$J$39,0,MATCH(AD$55,$F$17:$J$17,0))*INDEX(Portfolio_Categorisation!$I$24:$I$27,MATCH(AB58,Portfolio_Categorisation!$C$24:$C$27,0),0)} -> 0.030744578 | AE74: {=INDEX($F$40:$J$40,0,MATCH(AE$55,$F$17:$J$17,0))*INDEX(Portfolio_Categorisation!$H$24:$H$27,MATCH(AB58,Portfolio_Categorisation!$C$24:$C$27,0),0)+ INDEX($F$39:$J$39,0,MATCH(AE$55,$F$17:$J$17,0))*INDEX(Portfolio_Categorisation!$I$24:$I$27,MATCH(AB58,Portfolio_Categorisation!$C$24:$C$27,0),0)} -> 0.02899376 | AF74: {=INDEX($F$40:$J$40,0,MATCH(AF$55,$F$17:$J$17,0))*INDEX(Portfolio_Categorisation!$H$24:$H$27,MATCH(AB58,Portfolio_Categorisation!$C$24:$C$27,0),0)+ INDEX($F$39:$J$39,0,MATCH(AF$55,$F$17:$J$17,0))*INDEX(Portfolio_Categorisation!$I$24:$I$27,MATCH(AB58,Portfolio_Categorisation!$C$24:$C$27,0),0)} -> 0.027488069 | AG74: {=INDEX($F$40:$J$40,0,MATCH(AG$55,$F$17:$J$17,0))*INDEX(Portfolio_Categorisation!$H$24:$H$27,MATCH(AB58,Portfolio_Categorisation!$C$24:$C$27,0),0)+ INDEX($F$39:$J$39,0,MATCH(AG$55,$F$17:$J$17,0))*INDEX(Portfolio_Categorisation!$I$24:$I$27,MATCH(AB58,Portfolio_Categorisation!$C$24:$C$27,0),0)} -> 0.023181768 | AH74: {=INDEX($F$40:$J$40,0,MATCH(AH$55,$F$17:$J$17,0))*INDEX(Portfolio_Categorisation!$H$24:$H$27,MATCH(AB58,Portfolio_Categorisation!$C$24:$C$27,0),0)+ INDEX($F$39:$J$39,0,MATCH(AH$55,$F$17:$J$17,0))*INDEX(Portfolio_Categorisation!$I$24:$I$27,MATCH(AB58,Portfolio_Categorisation!$C$24:$C$27,0),0)} -> 0.020690897
D76: Other | L76: Other | T76: Other | AB76: Other
D77: Maintenance capex / pub / year | E77: =$E$52 -> 8000 | L77: Maintenance capex / pub / year | M77: =$E$52 -> 8000 | T77: Maintenance capex / pub / year | U77: =$E$52 -> 8000 | AB77: Maintenance capex / pub / year | AC77: =$E$52 -> 8000
D78: Bad debts / EBITDA | E78: =$E$53 -> -0.015 | L78: Bad debts / EBITDA | M78: =$E$53 -> -0.015 | T78: Bad debts / EBITDA | U78: =$E$53 -> -0.015 | AB78: Bad debts / EBITDA | AC78: =$E$53 -> -0.015
B80: X | D80: Corporate overheads / pub
D81: Corporate overheads / pub | E81: =Dashboard!$D$33 -> 8700
B83: X | D83: Growth capex assumptions
D85: Target ROI | E85: =Dashboard!I12 -> 0.45
D86: Capex period | E86: 1
D87: Capex start date | E87: =EOMONTH($E$12,4) -> 46446
D88: Growth capex / pub | E88: =Dashboard!I13 -> 40000
E90: 1 | F90: 2 | G90: 3 | H90: 4 | I90: 5 | J90: 6
D91: EBITDA growth post-capex | E91: 0 | F91: 0.04 | G91: 0.04 | H91: 0.04 | I91: 0.04 | J91: 0.04
D93: Assumed # of Pubs invested each year | F93: =F17 -> FY27E | G93: =G17 -> FY28E | H93: =H17 -> FY29E | I93: =I17 -> FY30E | J93: =J17 -> FY31E
D94: Portfolio | F94: =Dashboard!$I$14 -> 42 | G94: =F94 -> 42 | H94: =G94 -> 42 | I94: =H94 -> 42 | J94: =I94 -> 42
D95: Total | F95: =F94 -> 42 | G95: =G94 -> 42 | H95: =H94 -> 42 | I95: =I94 -> 42 | J95: =J94 -> 42
D96: % of total estate invested | F96: =IFERROR(F95/Portfolio!O9,0) -> 0.14383562 | G96: =IFERROR(G95/Portfolio!P9,0) -> 0.15217391 | H96: =IFERROR(H95/Portfolio!Q9,0) -> 0.16153846 | I96: =IFERROR(I95/Portfolio!R9,0) -> 0.17213115 | J96: =IFERROR(J95/Portfolio!S9,0) -> 0.18421053
D97: Capex spent per year | F97: =-Portfolio!O74 -> 1597966.6 | G97: =-Portfolio!P74 -> 1546113.4 | H97: =-Portfolio!Q74 -> 1488519.2 | I97: =-Portfolio!R74 -> 1425078.2 | J97: =-Portfolio!S74 -> 1356831.2
D98: Actual # of pubs invested each year | F98: =SUM('Portfolio>>>:<<<Portfolio'!R155) -> 42 | G98: =SUM('Portfolio>>>:<<<Portfolio'!R156) -> 42 | H98: =SUM('Portfolio>>>:<<<Portfolio'!R157) -> 42 | I98: =SUM('Portfolio>>>:<<<Portfolio'!R158) -> 42 | J98: =SUM('Portfolio>>>:<<<Portfolio'!R159) -> 42
E100: Drinks | F100: Rent
D101: EBITDA growth split | E101: 0.55 | F101: =1-E101 -> 0.45
B103: X | D103: Closures
D105: # of Pubs Closed Annually | E105: =E$17 -> FY26E | F105: =F$17 -> FY27E | G105: =G$17 -> FY28E | H105: =H$17 -> FY29E | I105: =I$17 -> FY30E | J105: =J$17 -> FY31E
D106: Portfolio | E106: =Dashboard!$D$35 -> 10 | F106: =E106 -> 10 | G106: =F106 -> 10 | H106: =G106 -> 10 | I106: =H106 -> 10 | J106: =I106 -> 10
D107: Total | E107: =E106 -> 10 | F107: =F106 -> 10 | G107: =G106 -> 10 | H107: =H106 -> 10 | I107: =I106 -> 10 | J107: =J106 -> 10
D108: % of total estate closed | E108: =IFERROR(E107/Portfolio!N9,0) -> 0.032467532 | F108: =IFERROR(F107/Portfolio!O9,0) -> 0.034246575 | G108: =IFERROR(G107/Portfolio!P9,0) -> 0.036231884 | H108: =IFERROR(H107/Portfolio!Q9,0) -> 0.038461538 | I108: =IFERROR(I107/Portfolio!R9,0) -> 0.040983607 | J108: =IFERROR(J107/Portfolio!S9,0) -> 0.043859649
D110: Annual security costs per closed pub | E110: 30000
B113: X | D113: Disposals
D115: Disposal Frequency | E115: 6
D117: No. of pubs disposed | F117: Portfolio | H117: =F117 -> Portfolio
D118: 1 | E118: =EOMONTH(E12,4) -> 46446 | F118: =Dashboard!$I$20/2 -> 8 | H118: =F118*$F$6 -> 8
D119: =D118+1 -> 2 | E119: =EOMONTH(E118,$E$115) -> 46630 | F119: =Dashboard!$I$20/2 -> 8 | H119: =F119*$F$6 -> 8
D120: =D119+1 -> 3 | E120: =EOMONTH(E119,$E$115) -> 46812 | F120: =Dashboard!$I$20/2 -> 8 | H120: =F120*$F$6 -> 8
D121: =D120+1 -> 4 | E121: =EOMONTH(E120,$E$115) -> 46996 | F121: =Dashboard!$I$20/2 -> 8 | H121: =F121*$F$6 -> 8
D122: =D121+1 -> 5 | E122: =EOMONTH(E121,$E$115) -> 47177 | F122: =Dashboard!$I$20/2 -> 8 | H122: =F122*$F$6 -> 8
D123: =D122+1 -> 6 | E123: =EOMONTH(E122,$E$115) -> 47361 | F123: =Dashboard!$I$20/2 -> 8 | H123: =F123*$F$6 -> 8
D124: =D123+1 -> 7 | E124: =EOMONTH(E123,$E$115) -> 47542 | F124: =Dashboard!$I$20/2 -> 8 | H124: =F124*$F$6 -> 8
D125: =D124+1 -> 8 | E125: =EOMONTH(E124,$E$115) -> 47726 | F125: =Dashboard!$I$20/2 -> 8 | H125: =F125*$F$6 -> 8
D126: =D125+1 -> 9 | E126: =EOMONTH(E125,$E$115) -> 47907 | F126: =Dashboard!$I$20/2 -> 8 | H126: =F126*$F$6 -> 8
D127: =D126+1 -> 10 | E127: =EOMONTH(E126,$E$115) -> 48091 | F127: =Dashboard!$I$20/2 -> 8 | H127: =F127*$F$6 -> 8
D128: Total disposals | F128: =SUM(F118:F127) -> 80 | H128: =SUM(H118:H127) -> 80
D129: % of total estate disposed | F129: =F128/Portfolio!N9 -> 0.25974026
D131: Disposal multiples | E131: EBITDA Multiple | F131: Yield
D132: Portfolio | E132: =Dashboard!$I$19 -> 13 | F132: =IFERROR(1/E132,0) -> 0.076923077
...

Sheet Outputs>>>

Sheet Returns Analysis
C2: X | E2: Assumptions
E4: Portfolio entry | P4: Sources | R4: Amount | S4: % of Total | U4: Uses | W4: Amount | X4: % of Total
E5: Entry Date | I5: =EOMONTH('Detailed Assumptions'!E12,-1) -> 46295 | P5: Day-1 Equity | R5: =-Q50 -> 1.4965335e+08 | S5: =R5/R$7 -> 0.42821782 | U5: Day-1 Purchase Price | W5: =I15 -> 3.460193e+08 | X5: =W5/W$7 -> 0.99009901
E6: Entry multiple (outlet level) | I6: =Dashboard!D10 -> 12 | P6: Day-1 Debt Drawdown | R6: =Q49 -> 1.9982615e+08 | S6: =R6/R$7 -> 0.57178218 | U6: Transaction Costs | W6: =-Q45 -> 3460193 | X6: =W6/W$7 -> 0.0099009901
E7: Purchasers' Costs | I7: =Dashboard!D11 -> 0.01 | P7: Total Day-1 Sources | R7: =SUM(R5:R6) -> 3.494795e+08 | S7: =R7/R$7 -> 1 | U7: Total Day-1 Sources | W7: =SUM(W5:W6) -> 3.494795e+08 | X7: =W7/W$7 -> 1
E9: Portfolio exit
E10: Exit multiple (outlet level) | I10: =Dashboard!D14 -> 12
E11: Exit Date | I11: ='Detailed Assumptions'!$E$13 -> 48121
E12: Sales Costs | I12: =Dashboard!D15 -> 0.01
E14: Valuation Summary
E15: Acq value | I15: =-I43 -> 3.460193e+08
E16: Outlet EBITDA multiple | I16: =I15/I28 -> 12
E17: Corporate EBITDA multiple | I17: =I15/(SUM(I28,I30)) -> 13.229393
Q18: {=INDEX(Index_Tab!$F$4:$K$4,MATCH(1,(Q$20>=Index_Tab!$F$5:$K$5)*(Q$20<=Index_Tab!$F$17:$K$17),0))} -> FY26E | R18: {=INDEX(Index_Tab!$G$4:$K$4,MATCH(1,(R$20>=Index_Tab!$G$5:$K$5)*(R$20<=Index_Tab!$G$17:$K$17),0))} -> FY27E | S18: {=INDEX(Index_Tab!$G$4:$K$4,MATCH(1,(S$20>=Index_Tab!$G$5:$K$5)*(S$20<=Index_Tab!$G$17:$K$17),0))} -> FY27E | T18: {=INDEX(Index_Tab!$G$4:$K$4,MATCH(1,(T$20>=Index_Tab!$G$5:$K$5)*(T$20<=Index_Tab!$G$17:$K$17),0))} -> FY27E | U18: {=INDEX(Index_Tab!$G$4:$K$4,MATCH(1,(U$20>=Index_Tab!$G$5:$K$5)*(U$20<=Index_Tab!$G$17:$K$17),0))} -> FY27E | V18: {=INDEX(Index_Tab!$G$4:$K$4,MATCH(1,(V$20>=Index_Tab!$G$5:$K$5)*(V$20<=Index_Tab!$G$17:$K$17),0))} -> FY27E | W18: {=INDEX(Index_Tab!$G$4:$K$4,MATCH(1,(W$20>=Index_Tab!$G$5:$K$5)*(W$20<=Index_Tab!$G$17:$K$17),0))} -> FY27E | X18: {=INDEX(Index_Tab!$G$4:$K$4,MATCH(1,(X$20>=Index_Tab!$G$5:$K$5)*(X$20<=Index_Tab!$G$17:$K$17),0))} -> FY27E | Y18: {=INDEX(Index_Tab!$G$4:$K$4,MATCH(1,(Y$20>=Index_Tab!$G$5:$K$5)*(Y$20<=Index_Tab!$G$17:$K$17),0))} -> FY27E | ... BY18: {=INDEX(Index_Tab!$G$4:$K$4,MATCH(1,(BY$20>=Index_Tab!$G$5:$K$5)*(BY$20<=Index_Tab!$G$17:$K$17),0))} -> FY31E
I19: ='Detailed Assumptions'!$E$17 -> FY26E | J19: ='Detailed Assumptions'!$F$17 -> FY27E | K19: ='Detailed Assumptions'!$G$17 -> FY28E | L19: ='Detailed Assumptions'!$H$17 -> FY29E | M19: ='Detailed Assumptions'!$I$17 -> FY30E | N19: ='Detailed Assumptions'!$J$17 -> FY31E | Q19: =EDATE(R19,-1) -> 46266 | R19: ='Detailed Assumptions'!$E$12 -> 46296 | S19: =R20+1 -> 46327 | T19: =S20+1 -> 46357 | U19: =T20+1 -> 46388 | V19: =U20+1 -> 46419 | W19: =V20+1 -> 46447 | X19: =W20+1 -> 46478 | Y19: =X20+1 -> 46508 | Z19: =Y20+1 -> 46539 | ... BY19: =BX20+1 -> 48092
I20: ='Detailed Assumptions'!$E$12-1 -> 46295 | J20: =EOMONTH(I20,12) -> 46660 | K20: =EOMONTH(J20,12) -> 47026 | L20: =EOMONTH(K20,12) -> 47391 | M20: =EOMONTH(L20,12) -> 47756 | N20: =EOMONTH(M20,12) -> 48121 | Q20: =EOMONTH(Q19,0) -> 46295 | R20: =EOMONTH(R19,0) -> 46326 | S20: =EOMONTH(S19,0) -> 46356 | T20: =EOMONTH(T19,0) -> 46387 | U20: =EOMONTH(U19,0) -> 46418 | V20: =EOMONTH(V19,0) -> 46446 | W20: =EOMONTH(W19,0) -> 46477 | X20: =EOMONTH(X19,0) -> 46507 | ... BY20: =EOMONTH(BY19,0) -> 48121
E22: Drinks gross profit (BCF + WSM) | I22: =Portfolio!N39 -> 16220326 | J22: =Portfolio!O39 -> 16977330 | K22: =Portfolio!P39 -> 17206443 | L22: =Portfolio!Q39 -> 17328213 | M22: =Portfolio!R39 -> 17347419 | N22: =Portfolio!S39 -> 17286720 | Q22: =Portfolio!V39 -> 0 | R22: =Portfolio!W39 -> 1423857.2 | S22: =Portfolio!X39 -> 1423857.2 | T22: =Portfolio!Y39 -> 1423857.2 | U22: =Portfolio!Z39 -> 1423857.2 | V22: =Portfolio!AA39 -> 1423857.2 | W22: =Portfolio!AB39 -> 1385632.8 | X22: =Portfolio!AC39 -> 1418590.9 | ... BY22: =Portfolio!CD39 -> 1401865.3
E23: Total rental income | I23: =Portfolio!N45 -> 11314203 | J23: =Portfolio!O45 -> 11610486 | K23: =Portfolio!P45 -> 11569977 | L23: =Portfolio!Q45 -> 11476062 | M23: =Portfolio!R45 -> 11310608 | N23: =Portfolio!S45 -> 11087204 | Q23: =Portfolio!V45 -> 0 | R23: =Portfolio!W45 -> 971506.83 | S23: =Portfolio!X45 -> 971506.83 | T23: =Portfolio!Y45 -> 971506.83 | U23: =Portfolio!Z45 -> 971506.83 | V23: =Portfolio!AA45 -> 971506.83 | W23: =Portfolio!AB45 -> 945426.11 | X23: =Portfolio!AC45 -> 972391.8 | ... BY23: =Portfolio!CD45 -> 904155.64
E24: Total other income | I24: =Portfolio!N52 -> 1964702 | J24: =Portfolio!O52 -> 1929539.6 | K24: =Portfolio!P52 -> 1824052.2 | L24: =Portfolio!Q52 -> 1718564.9 | M24: =Portfolio!R52 -> 1613077.5 | N24: =Portfolio!S52 -> 1507590.1 | Q24: =Portfolio!V52 -> 0 | R24: =Portfolio!W52 -> 163725.17 | S24: =Portfolio!X52 -> 163725.17 | T24: =Portfolio!Y52 -> 163725.17 | U24: =Portfolio!Z52 -> 163725.17 | V24: =Portfolio!AA52 -> 163725.17 | W24: =Portfolio!AB52 -> 159329.86 | X24: =Portfolio!AC52 -> 159329.86 | ... BY24: =Portfolio!CD52 -> 119772.1
E25: Net income (drinks GP + rent + other income) | I25: =SUM(I22:I24) -> 29499231 | J25: =SUM(J22:J24) -> 30517356 | K25: =SUM(K22:K24) -> 30600472 | L25: =SUM(L22:L24) -> 30522840 | M25: =SUM(M22:M24) -> 30271105 | N25: =SUM(N22:N24) -> 29881514 | Q25: =SUM(Q22:Q24) -> 0 | R25: =SUM(R22:R24) -> 2559089.2 | S25: =SUM(S22:S24) -> 2559089.2 | T25: =SUM(T22:T24) -> 2559089.2 | U25: =SUM(U22:U24) -> 2559089.2 | V25: =SUM(V22:V24) -> 2559089.2 | W25: =SUM(W22:W24) -> 2490388.8 | X25: =SUM(X22:X24) -> 2550312.5 | ... BY25: =SUM(BY22:BY24) -> 2425793
E27: Total pub costs | I27: =Portfolio!N59 -> -664289.16 | J27: =Portfolio!O59 -> -665448.32 | K27: =Portfolio!P59 -> -641649.83 | L27: =Portfolio!Q59 -> -616633.22 | M27: =Portfolio!R59 -> -590359.28 | N27: =Portfolio!S59 -> -562787.73 | Q27: =Portfolio!V59 -> 0 | R27: =Portfolio!W59 -> -56464.579 | S27: =Portfolio!X59 -> -56464.579 | T27: =Portfolio!Y59 -> -56464.579 | U27: =Portfolio!Z59 -> -56464.579 | V27: =Portfolio!AA59 -> -56464.579 | W27: =Portfolio!AB59 -> -54948.751 | X27: =Portfolio!AC59 -> -54948.751 | ... BY27: =Portfolio!CD59 -> -44711.27
E28: Outlet EBITDA | I28: =I25+I27 -> 28834942 | J28: =J25+J27 -> 29851908 | K28: =K25+K27 -> 29958822 | L28: =L25+L27 -> 29906207 | M28: =M25+M27 -> 29680745 | N28: =N25+N27 -> 29318726 | Q28: =Q25+Q27 -> 0 | R28: =R25+R27 -> 2502624.6 | S28: =S25+S27 -> 2502624.6 | T28: =T25+T27 -> 2502624.6 | U28: =U25+U27 -> 2502624.6 | V28: =V25+V27 -> 2502624.6 | W28: =W25+W27 -> 2435440 | X28: =X25+X27 -> 2495363.8 | ... BY28: =BY25+BY27 -> 2381081.7
E30: Overheads | I30: =Portfolio!N64 -> -2679600 | J30: =Portfolio!O64 -> -2698178 | K30: =Portfolio!P64 -> -2614763 | L30: =Portfolio!Q64 -> -2521776.6 | M30: =Portfolio!R64 -> -2419207.9 | N30: =Portfolio!S64 -> -2311200.4 | Q30: =Portfolio!V64 -> 0 | R30: =Portfolio!W64 -> -228810.25 | S30: =Portfolio!X64 -> -228810.25 | T30: =Portfolio!Y64 -> -228810.25 | U30: =Portfolio!Z64 -> -228810.25 | V30: =Portfolio!AA64 -> -228810.25 | W30: =Portfolio!AB64 -> -222867.13 | X30: =Portfolio!AC64 -> -222867.13 | ... BY30: =Portfolio!CD64 -> -183992.21
E31: Corporate EBITDA | I31: =I28+SUM(I30) -> 26155342 | J31: =J28+SUM(J30) -> 27153730 | K31: =K28+SUM(K30) -> 27344059 | L31: =L28+SUM(L30) -> 27384430 | M31: =M28+SUM(M30) -> 27261537 | N31: =N28+SUM(N30) -> 27007526 | Q31: =Q28+SUM(Q30) -> 0 | R31: =R28+SUM(R30) -> 2273814.3 | S31: =S28+SUM(S30) -> 2273814.3 | T31: =T28+SUM(T30) -> 2273814.3 | U31: =U28+SUM(U30) -> 2273814.3 | V31: =V28+SUM(V30) -> 2273814.3 | W31: =W28+SUM(W30) -> 2212572.9 | X31: =X28+SUM(X30) -> 2272496.7 | ... BY31: =BY28+SUM(BY30) -> 2197089.5
E33: Maintenance capex | I33: =Portfolio!N68 -> -3065576.1 | J33: =Portfolio!O68 -> -2388160 | K33: =Portfolio!P68 -> -2302752 | L33: =Portfolio!Q68 -> -2212972.4 | M33: =Portfolio!R68 -> -2118680.5 | N33: =Portfolio!S68 -> -2019731.8 | Q33: =Portfolio!V68 -> 0 | R33: =Portfolio!W68 -> -202640 | S33: =Portfolio!X68 -> -202640 | T33: =Portfolio!Y68 -> -202640 | U33: =Portfolio!Z68 -> -202640 | V33: =Portfolio!AA68 -> -202640 | W33: =Portfolio!AB68 -> -197200 | X33: =Portfolio!AC68 -> -197200 | ... BY33: =Portfolio!CD68 -> -160459.74
E34: Bad debts | I34: =Portfolio!N69 -> -432524.13 | J34: =Portfolio!O69 -> -447778.62 | K34: =Portfolio!P69 -> -449382.33 | L34: =Portfolio!Q69 -> -448593.1 | M34: =Portfolio!R69 -> -445211.18 | N34: =Portfolio!S69 -> -439780.9 | Q34: =Portfolio!V69 -> 0 | R34: =Portfolio!W69 -> -37539.369 | S34: =Portfolio!X69 -> -37539.369 | T34: =Portfolio!Y69 -> -37539.369 | U34: =Portfolio!Z69 -> -37539.369 | V34: =Portfolio!AA69 -> -37539.369 | W34: =Portfolio!AB69 -> -36531.6 | X34: =Portfolio!AC69 -> -37430.457 | ... BY34: =Portfolio!CD69 -> -35716.226
E35: Security costs re closed sites | I35: =Portfolio!N70 -> -300000 | J35: =Portfolio!O70 -> -307402.93 | K35: =Portfolio!P70 -> -314526.43 | L35: =Portfolio!Q70 -> -321272.72 | M35: =Portfolio!R70 -> -327569.22 | N35: =Portfolio!S70 -> -333924.15 | Q35: =Portfolio!V70 -> 0 | R35: =Portfolio!W70 -> -25616.911 | S35: =Portfolio!X70 -> -25616.911 | T35: =Portfolio!Y70 -> -25616.911 | U35: =Portfolio!Z70 -> -25616.911 | V35: =Portfolio!AA70 -> -25616.911 | W35: =Portfolio!AB70 -> -25616.911 | X35: =Portfolio!AC70 -> -25616.911 | ... BY35: =Portfolio!CD70 -> -27827.013
E36: Normalised operating CF | I36: =I31+SUM(I33:I35) -> 22357242 | J36: =J31+SUM(J33:J35) -> 24010388 | K36: =K31+SUM(K33:K35) -> 24277398 | L36: =L31+SUM(L33:L35) -> 24401592 | M36: =M31+SUM(M33:M35) -> 24370076 | N36: =N31+SUM(N33:N35) -> 24214089 | Q36: =Q31+SUM(Q33:Q35) -> 0 | R36: =R31+SUM(R33:R35) -> 2008018.1 | S36: =S31+SUM(S33:S35) -> 2008018.1 | T36: =T31+SUM(T33:T35) -> 2008018.1 | U36: =U31+SUM(U33:U35) -> 2008018.1 | V36: =V31+SUM(V33:V35) -> 2008018.1 | W36: =W31+SUM(W33:W35) -> 1953224.4 | X36: =X31+SUM(X33:X35) -> 2012249.3 | ... BY36: =BY31+SUM(BY33:BY35) -> 1973086.6
E38: Growth Capex | I38: =Portfolio!N74 -> -1391870.9 | J38: =Portfolio!O74 -> -1597966.6 | K38: =Portfolio!P74 -> -1546113.4 | L38: =Portfolio!Q74 -> -1488519.2 | M38: =Portfolio!R74 -> -1425078.2 | N38: =Portfolio!S74 -> -1356831.2 | Q38: =Portfolio!V74 -> 0 | R38: =Portfolio!W74 -> 0 | S38: =Portfolio!X74 -> 0 | T38: =Portfolio!Y74 -> 0 | U38: =Portfolio!Z74 -> 0 | V38: =Portfolio!AA74 -> 0 | W38: =Portfolio!AB74 -> -1597966.6 | X38: =Portfolio!AC74 -> 0 | ... BY38: =Portfolio!CD74 -> 0
E39: Asset disposal proceeds | I39: =Portfolio!N75 -> 0 | J39: =Portfolio!O75 -> 21007265 | K39: =Portfolio!P75 -> 22302773 | L39: =Portfolio!Q75 -> 23631372 | M39: =Portfolio!R75 -> 24988348 | N39: =Portfolio!S75 -> 26412339 | Q39: =Portfolio!V75 -> 0 | R39: =Portfolio!W75 -> 0 | S39: =Portfolio!X75 -> 0 | T39: =Portfolio!Y75 -> 0 | U39: =Portfolio!Z75 -> 0 | V39: =Portfolio!AA75 -> 10375982 | W39: =Portfolio!AB75 -> 0 | X39: =Portfolio!AC75 -> 0 | ... BY39: =Portfolio!CD75 -> 0
E40: Surplus land disposal proceeds | I40: =Portfolio!N76 -> 0 | J40: =Portfolio!O76 -> 833333.33 | K40: =Portfolio!P76 -> 2500000 | L40: =Portfolio!Q76 -> 4166666.7 | M40: =Portfolio!R76 -> 5000000 | N40: =Portfolio!S76 -> 5000000 | Q40: =Portfolio!V76 -> 0 | R40: =Portfolio!W76 -> 0 | S40: =Portfolio!X76 -> 0 | T40: =Portfolio!Y76 -> 0 | U40: =Portfolio!Z76 -> 0 | V40: =Portfolio!AA76 -> 0 | W40: =Portfolio!AB76 -> 0 | X40: =Portfolio!AC76 -> 0 | ... BY40: =Portfolio!CD76 -> 0
E41: Portfolio net cash flow | I41: =I36+SUM(I38:I40) -> 20965371 | J41: =J36+SUM(J38:J40) -> 44253020 | K41: =K36+SUM(K38:K40) -> 47534058 | L41: =L36+SUM(L38:L40) -> 50711112 | M41: =M36+SUM(M38:M40) -> 52933346 | N41: =N36+SUM(N38:N40) -> 54269597 | Q41: =Q36+SUM(Q38:Q40) -> 0 | R41: =R36+SUM(R38:R40) -> 2008018.1 | S41: =S36+SUM(S38:S40) -> 2008018.1 | T41: =T36+SUM(T38:T40) -> 2008018.1 | U41: =U36+SUM(U38:U40) -> 2008018.1 | V41: =V36+SUM(V38:V40) -> 12384000 | W41: =W36+SUM(W38:W40) -> 355257.75 | X41: =X36+SUM(X38:X40) -> 2012249.3 | ... BY41: =BY36+SUM(BY38:BY40) -> 1973086.6
E43: Purchase Price | I43: =SUMIFS($Q43:$BY43,$Q$18:$BY$18,I$19) -> -3.460193e+08 | J43: =SUMIFS($Q43:$BY43,$Q$18:$BY$18,J$19) -> 0 | K43: =SUMIFS($Q43:$BY43,$Q$18:$BY$18,K$19) -> 0 | L43: =SUMIFS($Q43:$BY43,$Q$18:$BY$18,L$19) -> 0 | M43: =SUMIFS($Q43:$BY43,$Q$18:$BY$18,M$19) -> 0 | N43: =SUMIFS($Q43:$BY43,$Q$18:$BY$18,N$19) -> 0 | Q43: =IF(Q$20=$I$5,-$I$28*$I$6,0) -> -3.460193e+08 | R43: =IF(R$20=$I$5,-$I$28*$I$6,0) -> 0 | S43: =IF(S$20=$I$5,-$I$28*$I$6,0) -> 0 | T43: =IF(T$20=$I$5,-$I$28*$I$6,0) -> 0 | U43: =IF(U$20=$I$5,-$I$28*$I$6,0) -> 0 | V43: =IF(V$20=$I$5,-$I$28*$I$6,0) -> 0 | W43: =IF(W$20=$I$5,-$I$28*$I$6,0) -> 0 | X43: =IF(X$20=$I$5,-$I$28*$I$6,0) -> 0 | ... BY43: =IF(BY$20=$I$5,-$I$28*$I$6,0) -> 0
E44: Exit Proceeds | I44: =SUMIFS($Q44:$BY44,$Q$18:$BY$18,I$19) -> 0 | J44: =SUMIFS($Q44:$BY44,$Q$18:$BY$18,J$19) -> 0 | K44: =SUMIFS($Q44:$BY44,$Q$18:$BY$18,K$19) -> 0 | L44: =SUMIFS($Q44:$BY44,$Q$18:$BY$18,L$19) -> 0 | M44: =SUMIFS($Q44:$BY44,$Q$18:$BY$18,M$19) -> 0 | N44: =SUMIFS($Q44:$BY44,$Q$18:$BY$18,N$19) -> 3.4287577e+08 | Q44: =IF(Q$20=$I$11,Q28*12*$I$10,0) -> 0 | R44: =IF(R$20=$I$11,R28*12*$I$10,0) -> 0 | S44: =IF(S$20=$I$11,S28*12*$I$10,0) -> 0 | T44: =IF(T$20=$I$11,T28*12*$I$10,0) -> 0 | U44: =IF(U$20=$I$11,U28*12*$I$10,0) -> 0 | V44: =IF(V$20=$I$11,V28*12*$I$10,0) -> 0 | W44: =IF(W$20=$I$11,W28*12*$I$10,0) -> 0 | X44: =IF(X$20=$I$11,X28*12*$I$10,0) -> 0 | ... BY44: =IF(BY$20=$I$11,BY28*12*$I$10,0) -> 3.4287577e+08
E45: Transaction Costs | I45: =SUMIFS($Q45:$BY45,$Q$18:$BY$18,I$19) -> -3460193 | J45: =SUMIFS($Q45:$BY45,$Q$18:$BY$18,J$19) -> 0 | K45: =SUMIFS($Q45:$BY45,$Q$18:$BY$18,K$19) -> 0 | L45: =SUMIFS($Q45:$BY45,$Q$18:$BY$18,L$19) -> 0 | M45: =SUMIFS($Q45:$BY45,$Q$18:$BY$18,M$19) -> 0 | N45: =SUMIFS($Q45:$BY45,$Q$18:$BY$18,N$19) -> -3428757.7 | Q45: =Q43*$I$7+-Q44*$I$12 -> -3460193 | R45: =R43*$I$7+-R44*$I$12 -> 0 | S45: =S43*$I$7+-S44*$I$12 -> 0 | T45: =T43*$I$7+-T44*$I$12 -> 0 | U45: =U43*$I$7+-U44*$I$12 -> 0 | V45: =V43*$I$7+-V44*$I$12 -> 0 | W45: =W43*$I$7+-W44*$I$12 -> 0 | X45: =X43*$I$7+-X44*$I$12 -> 0 | ... BY45: =BY43*$I$7+-BY44*$I$12 -> -3428757.7
E46: Unlevered portfolio net cash flow | I46: =SUM(I41:I45) -> -3.2851413e+08 | J46: =SUM(J41:J45) -> 44253020 | K46: =SUM(K41:K45) -> 47534058 | L46: =SUM(L41:L45) -> 50711112 | M46: =SUM(M41:M45) -> 52933346 | N46: =SUM(N41:N45) -> 3.9371661e+08 | Q46: =SUM(Q41:Q45) -> -3.494795e+08 | R46: =SUM(R41:R45) -> 2008018.1 | S46: =SUM(S41:S45) -> 2008018.1 | T46: =SUM(T41:T45) -> 2008018.1 | U46: =SUM(U41:U45) -> 2008018.1 | V46: =SUM(V41:V45) -> 12384000 | W46: =SUM(W41:W45) -> 355257.75 | X46: =SUM(X41:X45) -> 2012249.3 | ... BY46: =SUM(BY41:BY45) -> 3.414201e+08
E47: Unlevered running cash yield (incl. disposal proceeds) | J47: =AVERAGEIF($Q$18:$BY$18,J$19,$Q$47:$BY$47) -> 0.12662551 | K47: =AVERAGEIF($Q$18:$BY$18,K$19,$Q$47:$BY$47) -> 0.13601387 | L47: =AVERAGEIF($Q$18:$BY$18,L$19,$Q$47:$BY$47) -> 0.14510468 | M47: =AVERAGEIF($Q$18:$BY$18,M$19,$Q$47:$BY$47) -> 0.15146338 | N47: =AVERAGEIF($Q$18:$BY$18,N$19,$Q$47:$BY$47) -> 0.15528693 | R47: =(R41*12)/-$Q$46 -> 0.06894887 | S47: =(S41*12)/-$Q$46 -> 0.06894887 | T47: =(T41*12)/-$Q$46 -> 0.06894887 | U47: =(U41*12)/-$Q$46 -> 0.06894887 | V47: =(V41*12)/-$Q$46 -> 0.42522667 | W47: =(W41*12)/-$Q$46 -> 0.012198407 | X47: =(X41*12)/-$Q$46 -> 0.069094157 | Y47: =(Y41*12)/-$Q$46 -> 0.069094157 | ... BY47: =(BY41*12)/-$Q$46 -> 0.067749435
E49: Financing Cashflows | I49: =SUMIFS($Q49:$BY49,$Q$18:$BY$18,I$19) -> 1.9982615e+08 | J49: =SUMIFS($Q49:$BY49,$Q$18:$BY$18,J$19) -> -31397764 | K49: =SUMIFS($Q49:$BY49,$Q$18:$BY$18,K$19) -> -31005739 | L49: =SUMIFS($Q49:$BY49,$Q$18:$BY$18,L$19) -> -30559065 | M49: =SUMIFS($Q49:$BY49,$Q$18:$BY$18,M$19) -> -30052726 | N49: =SUMIFS($Q49:$BY49,$Q$18:$BY$18,N$19) -> -1.5319156e+08 | Q49: ='Debt Schedule'!R51 -> 1.9982615e+08 | R49: ='Debt Schedule'!S51 -> -1476156.8 | S49: ='Debt Schedule'!T51 -> -1476156.8 | T49: ='Debt Schedule'!U51 -> -1476156.8 | U49: ='Debt Schedule'!V51 -> -1476156.8 | V49: ='Debt Schedule'!W51 -> -8436711.6 | W49: ='Debt Schedule'!X51 -> -1425251.9 | X49: ='Debt Schedule'!Y51 -> -1425251.9 | ... BY49: ='Debt Schedule'!BZ51 -> -1.2457691e+08
E50: Levered portfolio net cash flow | I50: =I49+I46 -> -1.2868798e+08 | J50: =J49+J46 -> 12855256 | K50: =K49+K46 -> 16528319 | L50: =L49+L46 -> 20152047 | M50: =M49+M46 -> 22880619 | N50: =N49+N46 -> 2.4052505e+08 | Q50: =Q49+Q46 -> -1.4965335e+08 | R50: =R49+R46 -> 531861.25 | S50: =S49+S46 -> 531861.25 | T50: =T49+T46 -> 531861.25 | U50: =U49+U46 -> 531861.25 | V50: =V49+V46 -> 3947288.8 | W50: =W49+W46 -> -1069994.2 | X50: =X49+X46 -> 586997.34 | ... BY50: =BY49+BY46 -> 2.1684319e+08
E51: Levered running cash yield (incl. disposal proceeds) | J51: =AVERAGEIF($Q$18:$BY$18,J$19,$Q$51:$BY$51) -> 0.085900223 | K51: =AVERAGEIF($Q$18:$BY$18,K$19,$Q$51:$BY$51) -> 0.11044403 | L51: =AVERAGEIF($Q$18:$BY$18,L$19,$Q$51:$BY$51) -> 0.13465817 | M51: =AVERAGEIF($Q$18:$BY$18,M$19,$Q$51:$BY$51) -> 0.15289079 | N51: =AVERAGEIF($Q$18:$BY$18,N$19,$Q$51:$BY$51) -> 0.10451077 | R51: =(SUM(R41,R49)*12)/-$Q$50 -> 0.042647459 | S51: =(SUM(S41,S49)*12)/-$Q$50 -> 0.042647459 | T51: =(SUM(T41,T49)*12)/-$Q$50 -> 0.042647459 | U51: =(SUM(U41,U49)*12)/-$Q$50 -> 0.042647459 | V51: =(SUM(V41,V49)*12)/-$Q$50 -> 0.31651457 | W51: =(SUM(W41,W49)*12)/-$Q$50 -> -0.085797815 | X51: =(SUM(X41,X49)*12)/-$Q$50 -> 0.047068563 | Y51: =(SUM(Y41,Y49)*12)/-$Q$50 -> 0.047068563 | ... BX51: =(SUM(BX41,BX49)*12)/-$Q$50 -> 0.64365449 | BY51: =(SUM(BY41,BX49)*12)/-$Q$50 -> -0.64480792
E53: Return Summary
I54: Unlevered | J54: Levered
E55: IRR | I55: =XIRR($Q$46:$BY$46,$Q$20:$BY$20) -> 0.14414125 | J55: =XIRR($Q$50:$BY$50,$Q$20:$BY$20) -> 0.1913599
E56: Profit | I56: =SUM(Q46:BY46) -> 2.3966865e+08 | J56: =SUM(Q50:BY50) -> 1.6328794e+08
E57: Equity Requirement | I57: =-SUMIFS($Q46:$BY46,$Q46:$BY46,"<"&0) -> 3.494795e+08 | J57: =-SUMIFS($Q50:$BY50,$Q50:$BY50,"<"&0) -> 1.5327138e+08
E58: Equity Multiple | I58: =(I56+I57)/I57 -> 1.6857874 | J58: =(J56+J57)/J57 -> 2.0653518
E59: Year 1 Cash-on-Cash | I59: =J47 -> 0.12662551 | J59: =J51 -> 0.085900223
E60: Year 5 Cash-on-Cash | I60: =N47 -> 0.15528693 | J60: =N51 -> 0.10451077
E61: Avg. cash yield | I61: =AVERAGE(R47:BY47) -> 0.14289887 | J61: =AVERAGE(R51:BY51) -> 0.1176808

Sheet Debt Schedule
B2: X | D2: Debt schedule - initial portfolio
J4: ='Detailed Assumptions'!F$17 -> FY27E | K4: ='Detailed Assumptions'!G$17 -> FY28E | L4: ='Detailed Assumptions'!H$17 -> FY29E | M4: ='Detailed Assumptions'!I$17 -> FY30E | N4: ='Detailed Assumptions'!J$17 -> FY31E | R4: {=INDEX(Index_Tab!$F$4:$K$4,MATCH(1,(R6>=Index_Tab!$F$5:$K$5)*(R6<=Index_Tab!$F$17:$K$17),0))} -> FY26E | S4: {=INDEX(Index_Tab!$F$4:$K$4,MATCH(1,(S6>=Index_Tab!$F$5:$K$5)*(S6<=Index_Tab!$F$17:$K$17),0))} -> FY27E | T4: {=INDEX(Index_Tab!$F$4:$K$4,MATCH(1,(T6>=Index_Tab!$F$5:$K$5)*(T6<=Index_Tab!$F$17:$K$17),0))} -> FY27E | U4: {=INDEX(Index_Tab!$F$4:$K$4,MATCH(1,(U6>=Index_Tab!$F$5:$K$5)*(U6<=Index_Tab!$F$17:$K$17),0))} -> FY27E | V4: {=INDEX(Index_Tab!$F$4:$K$4,MATCH(1,(V6>=Index_Tab!$F$5:$K$5)*(V6<=Index_Tab!$F$17:$K$17),0))} -> FY27E | W4: {=INDEX(Index_Tab!$F$4:$K$4,MATCH(1,(W6>=Index_Tab!$F$5:$K$5)*(W6<=Index_Tab!$F$17:$K$17),0))} -> FY27E | X4: {=INDEX(Index_Tab!$F$4:$K$4,MATCH(1,(X6>=Index_Tab!$F$5:$K$5)*(X6<=Index_Tab!$F$17:$K$17),0))} -> FY27E | Y4: {=INDEX(Index_Tab!$F$4:$K$4,MATCH(1,(Y6>=Index_Tab!$F$5:$K$5)*(Y6<=Index_Tab!$F$17:$K$17),0))} -> FY27E | ... BZ4: {=INDEX(Index_Tab!$F$4:$K$4,MATCH(1,(BZ6>=Index_Tab!$F$5:$K$5)*(BZ6<=Index_Tab!$F$17:$K$17),0))} -> FY31E
D5: BoP | J5: =Index_Tab!G5 -> 46296 | K5: =J6+1 -> 46661 | L5: =K6+1 -> 47027 | M5: =L6+1 -> 47392 | N5: =M6+1 -> 47757 | R5: =EDATE(S5,-1) -> 46266 | S5: =J5 -> 46296 | T5: =S6+1 -> 46327 | U5: =T6+1 -> 46357 | V5: =U6+1 -> 46388 | W5: =V6+1 -> 46419 | X5: =W6+1 -> 46447 | Y5: =X6+1 -> 46478 | Z5: =Y6+1 -> 46508 | AA5: =Z6+1 -> 46539 | ... BZ5: =BY6+1 -> 48092
D6: EoP | J6: =EOMONTH(J5,11) -> 46660 | K6: =EOMONTH(K5,11) -> 47026 | L6: =EOMONTH(L5,11) -> 47391 | M6: =EOMONTH(M5,11) -> 47756 | N6: =EOMONTH(N5,11) -> 48121 | R6: =EOMONTH(R5,0) -> 46295 | S6: =EOMONTH(S5,0) -> 46326 | T6: =EOMONTH(T5,0) -> 46356 | U6: =EOMONTH(U5,0) -> 46387 | V6: =EOMONTH(V5,0) -> 46418 | W6: =EOMONTH(W5,0) -> 46446 | X6: =EOMONTH(X5,0) -> 46477 | Y6: =EOMONTH(Y5,0) -> 46507 | ... BZ6: =EOMONTH(BZ5,0) -> 48121
D8: Loan Start Date | E8: ='Returns Analysis'!I5 -> 46295
D9: Repayment Date | E9: ='Detailed Assumptions'!$E$141 -> 48121
D10: Loan Amount | E10: =E15 -> 2.0184459e+08
D12: Outlet EBITDA (pre-OHs)" | E12: =Portfolio!N61 -> 28834942
D13: EBITDA used for debt sizing (pre overheads) | E13: =E12 -> 28834942
D14: EBITDA Multiple | E14: ='Detailed Assumptions'!$E$140 -> 7
D15: Implied quantum | E15: =E13*E14 -> 2.0184459e+08
D18: All-In Cost | E18: =E22+E19 -> 0.08776
D19: Margin | E19: ='Detailed Assumptions'!$E$143 -> 0.0475
D20: Interest Method | E20: ='Detailed Assumptions'!$E$144 -> Current
D21: Type | E21: ='Detailed Assumptions'!$E$145 -> Fixed
D22: 5Y Swap | E22: ='Detailed Assumptions'!$E$146 -> 0.04026
D24: Commitment Fee % | E24: ='Detailed Assumptions'!$E$147 -> 0
D25: Commitment Fee Method | E25: ='Detailed Assumptions'!$E$148 -> Current
D26: UFF | E26: ='Detailed Assumptions'!$E$149 -> 0.01
D27: Amortisation | E27: ='Detailed Assumptions'!$E$150 -> 0
D28: Exit Fee | E28: ='Detailed Assumptions'!$E$151 -> 0.01
D29: Release Pricing Premium | E29: ='Detailed Assumptions'!$E$152 -> 0.15
D30: Allocated loan amount (% LTV) | E30: ='Detailed Assumptions'!$E$153 -> 0.58333333
D33: Disposal Proceeds | J33: =SUMIFS($S33:$BZ33,$S$4:$BZ$4,J$4) -> 21007265 | K33: =SUMIFS($S33:$BZ33,$S$4:$BZ$4,K$4) -> 22302773 | L33: =SUMIFS($S33:$BZ33,$S$4:$BZ$4,L$4) -> 23631372 | M33: =SUMIFS($S33:$BZ33,$S$4:$BZ$4,M$4) -> 24988348 | N33: =SUMIFS($S33:$BZ33,$S$4:$BZ$4,N$4) -> 26412339 | R33: =IFERROR(INDEX(Portfolio!$W$75:$CD$75,MATCH('Debt Schedule'!R$6,Portfolio!$W$4:$CD$4,0)),0) -> 0 | S33: =IFERROR(INDEX(Portfolio!$W$75:$CD$75,MATCH('Debt Schedule'!S$6,Portfolio!$W$4:$CD$4,0)),0) -> 0 | T33: =IFERROR(INDEX(Portfolio!$W$75:$CD$75,MATCH('Debt Schedule'!T$6,Portfolio!$W$4:$CD$4,0)),0) -> 0 | U33: =IFERROR(INDEX(Portfolio!$W$75:$CD$75,MATCH('Debt Schedule'!U$6,Portfolio!$W$4:$CD$4,0)),0) -> 0 | V33: =IFERROR(INDEX(Portfolio!$W$75:$CD$75,MATCH('Debt Schedule'!V$6,Portfolio!$W$4:$CD$4,0)),0) -> 0 | W33: =IFERROR(INDEX(Portfolio!$W$75:$CD$75,MATCH('Debt Schedule'!W$6,Portfolio!$W$4:$CD$4,0)),0) -> 10375982 | X33: =IFERROR(INDEX(Portfolio!$W$75:$CD$75,MATCH('Debt Schedule'!X$6,Portfolio!$W$4:$CD$4,0)),0) -> 0 | Y33: =IFERROR(INDEX(Portfolio!$W$75:$CD$75,MATCH('Debt Schedule'!Y$6,Portfolio!$W$4:$CD$4,0)),0) -> 0 | ... BZ33: =IFERROR(INDEX(Portfolio!$W$75:$CD$75,MATCH('Debt Schedule'!BZ$6,Portfolio!$W$4:$CD$4,0)),0) -> 0
D35: Opening Balance | J35: {=INDEX($S35:$BZ35,0,MATCH(EOMONTH(J$6,-11),$S$6:$BZ$6,0))} -> 2.0184459e+08 | K35: {=INDEX($S35:$BZ35,0,MATCH(EOMONTH(K$6,-11),$S$6:$BZ$6,0))} -> 1.8775222e+08 | L35: {=INDEX($S35:$BZ35,0,MATCH(EOMONTH(L$6,-11),$S$6:$BZ$6,0))} -> 1.7279078e+08 | M35: {=INDEX($S35:$BZ35,0,MATCH(EOMONTH(M$6,-11),$S$6:$BZ$6,0))} -> 1.5693807e+08 | N35: {=INDEX($S35:$BZ35,0,MATCH(EOMONTH(N$6,-11),$S$6:$BZ$6,0))} -> 1.4017505e+08 | R35: 0 | S35: =R49 -> 2.0184459e+08 | T35: =S49 -> 2.0184459e+08 | U35: =T49 -> 2.0184459e+08 | V35: =U49 -> 2.0184459e+08 | W35: =V49 -> 2.0184459e+08 | X35: =W49 -> 1.9488404e+08 | Y35: =X49 -> 1.9488404e+08 | Z35: =Y49 -> 1.9488404e+08 | ... BZ35: =BY49 -> 1.2245677e+08
D36: Drawdown | J36: =SUMIFS($S36:$BZ36,$S$4:$BZ$4,J$4) -> 0 | K36: =SUMIFS($S36:$BZ36,$S$4:$BZ$4,K$4) -> 0 | L36: =SUMIFS($S36:$BZ36,$S$4:$BZ$4,L$4) -> 0 | M36: =SUMIFS($S36:$BZ36,$S$4:$BZ$4,M$4) -> 0 | N36: =SUMIFS($S36:$BZ36,$S$4:$BZ$4,N$4) -> 0 | R36: =IF(R$6=$E$8,$E$10,0) -> 2.0184459e+08 | S36: =IF(S$6=$E$8,$E$10,0) -> 0 | T36: =IF(T$6=$E$8,$E$10,0) -> 0 | U36: =IF(U$6=$E$8,$E$10,0) -> 0 | V36: =IF(V$6=$E$8,$E$10,0) -> 0 | W36: =IF(W$6=$E$8,$E$10,0) -> 0 | X36: =IF(X$6=$E$8,$E$10,0) -> 0 | Y36: =IF(Y$6=$E$8,$E$10,0) -> 0 | ... BZ36: =IF(BZ$6=$E$8,$E$10,0) -> 0
D37: Upfront Fee | J37: =SUMIFS($S37:$BZ37,$S$4:$BZ$4,J$4) -> 0 | K37: =SUMIFS($S37:$BZ37,$S$4:$BZ$4,K$4) -> 0 | L37: =SUMIFS($S37:$BZ37,$S$4:$BZ$4,L$4) -> 0 | M37: =SUMIFS($S37:$BZ37,$S$4:$BZ$4,M$4) -> 0 | N37: =SUMIFS($S37:$BZ37,$S$4:$BZ$4,N$4) -> 0 | R37: =-IF(R$6=$E8,$E10*$E26,0) -> -2018445.9 | S37: =-IF(S$6=$E8,$E10*$E26,0) -> 0 | T37: =-IF(T$6=$E8,$E10*$E26,0) -> 0 | U37: =-IF(U$6=$E8,$E10*$E26,0) -> 0 | V37: =-IF(V$6=$E8,$E10*$E26,0) -> 0 | W37: =-IF(W$6=$E8,$E10*$E26,0) -> 0 | X37: =-IF(X$6=$E8,$E10*$E26,0) -> 0 | Y37: =-IF(Y$6=$E8,$E10*$E26,0) -> 0 | ... BZ37: =-IF(BZ$6=$E8,$E10*$E26,0) -> 0
D38: Commitment Fee | J38: =SUMIFS($S38:$BZ38,$S$4:$BZ$4,J$4) -> 0 | K38: =SUMIFS($S38:$BZ38,$S$4:$BZ$4,K$4) -> 0 | L38: =SUMIFS($S38:$BZ38,$S$4:$BZ$4,L$4) -> 0 | M38: =SUMIFS($S38:$BZ38,$S$4:$BZ$4,M$4) -> 0 | N38: =SUMIFS($S38:$BZ38,$S$4:$BZ$4,N$4) -> 0 | R38: =IF(AND(R$6>=$E8,R$6<$E9),-((($E10)-SUM(R36:$S36))*($E24))/12,0) -> 0 | S38: =IF(AND(S$6>=$E8,S$6<$E9),-((($E10)-SUM($S36:S36))*($E24))/12,0) -> 0 | T38: =IF(AND(T$6>=$E8,T$6<$E9),-((($E10)-SUM($S36:T36))*($E24))/12,0) -> 0 | U38: =IF(AND(U$6>=$E8,U$6<$E9),-((($E10)-SUM($S36:U36))*($E24))/12,0) -> 0 | V38: =IF(AND(V$6>=$E8,V$6<$E9),-((($E10)-SUM($S36:V36))*($E24))/12,0) -> 0 | W38: =IF(AND(W$6>=$E8,W$6<$E9),-((($E10)-SUM($S36:W36))*($E24))/12,0) -> 0 | X38: =IF(AND(X$6>=$E8,X$6<$E9),-((($E10)-SUM($S36:X36))*($E24))/12,0) -> 0 | Y38: =IF(AND(Y$6>=$E8,Y$6<$E9),-((($E10)-SUM($S36:Y36))*($E24))/12,0) -> 0 | Z38: =IF(AND(Z$6>=$E8,Z$6<$E9),-((($E10)-SUM($S36:Z36))*($E24))/12,0) -> 0 | ... BZ38: =IF(AND(BZ$6>=$E8,BZ$6<$E9),-((($E10)-SUM($S36:BZ36))*($E24))/12,0) -> 0
D39: Paid | J39: =SUMIFS($S39:$BZ39,$S$4:$BZ$4,J$4) -> 0 | K39: =SUMIFS($S39:$BZ39,$S$4:$BZ$4,K$4) -> 0 | L39: =SUMIFS($S39:$BZ39,$S$4:$BZ$4,L$4) -> 0 | M39: =SUMIFS($S39:$BZ39,$S$4:$BZ$4,M$4) -> 0 | N39: =SUMIFS($S39:$BZ39,$S$4:$BZ$4,N$4) -> 0 | R39: =IF($E$25="Current",R$38,0) -> 0 | S39: =IF($E$25="Current",S$38,0) -> 0 | T39: =IF($E$25="Current",T$38,0) -> 0 | U39: =IF($E$25="Current",U$38,0) -> 0 | V39: =IF($E$25="Current",V$38,0) -> 0 | W39: =IF($E$25="Current",W$38,0) -> 0 | X39: =IF($E$25="Current",X$38,0) -> 0 | Y39: =IF($E$25="Current",Y$38,0) -> 0 | ... BZ39: =IF($E$25="Current",BZ$38,0) -> 0
D40: PIK | J40: =SUMIFS($S40:$BZ40,$S$4:$BZ$4,J$4) -> 0 | K40: =SUMIFS($S40:$BZ40,$S$4:$BZ$4,K$4) -> 0 | L40: =SUMIFS($S40:$BZ40,$S$4:$BZ$4,L$4) -> 0 | M40: =SUMIFS($S40:$BZ40,$S$4:$BZ$4,M$4) -> 0 | N40: =SUMIFS($S40:$BZ40,$S$4:$BZ$4,N$4) -> 0 | R40: =IF($E$25="PIK",-R$38,0) -> 0 | S40: =IF($E$25="PIK",-S$38,0) -> 0 | T40: =IF($E$25="PIK",-T$38,0) -> 0 | U40: =IF($E$25="PIK",-U$38,0) -> 0 | V40: =IF($E$25="PIK",-V$38,0) -> 0 | W40: =IF($E$25="PIK",-W$38,0) -> 0 | X40: =IF($E$25="PIK",-X$38,0) -> 0 | Y40: =IF($E$25="PIK",-Y$38,0) -> 0 | ... BZ40: =IF($E$25="PIK",-BZ$38,0) -> 0
D41: Interest | J41: =SUMIFS($S41:$BZ41,$S$4:$BZ$4,J$4) -> -17305390 | K41: =SUMIFS($S41:$BZ41,$S$4:$BZ$4,K$4) -> -16044295 | L41: =SUMIFS($S41:$BZ41,$S$4:$BZ$4,L$4) -> -14706353 | M41: =SUMIFS($S41:$BZ41,$S$4:$BZ$4,M$4) -> -13289710 | N41: =SUMIFS($S41:$BZ41,$S$4:$BZ$4,N$4) -> -11791941 | R41: =-(R35*(IF($E$21="Floating",R$53+$E$19,$E$18))/12) -> 0 | S41: =-(S35*(IF($E$21="Floating",S$53+$E$19,$E$18))/12) -> -1476156.8 | T41: =-(T35*(IF($E$21="Floating",T$53+$E$19,$E$18))/12) -> -1476156.8 | U41: =-(U35*(IF($E$21="Floating",U$53+$E$19,$E$18))/12) -> -1476156.8 | V41: =-(V35*(IF($E$21="Floating",V$53+$E$19,$E$18))/12) -> -1476156.8 | W41: =-(W35*(IF($E$21="Floating",W$53+$E$19,$E$18))/12) -> -1476156.8 | X41: =-(X35*(IF($E$21="Floating",X$53+$E$19,$E$18))/12) -> -1425251.9 | Y41: =-(Y35*(IF($E$21="Floating",Y$53+$E$19,$E$18))/12) -> -1425251.9 | ... BZ41: =-(BZ35*(IF($E$21="Floating",BZ$53+$E$19,$E$18))/12) -> -895567.19
D42: Paid | J42: =SUMIFS($S42:$BZ42,$S$4:$BZ$4,J$4) -> -17305390 | K42: =SUMIFS($S42:$BZ42,$S$4:$BZ$4,K$4) -> -16044295 | L42: =SUMIFS($S42:$BZ42,$S$4:$BZ$4,L$4) -> -14706353 | M42: =SUMIFS($S42:$BZ42,$S$4:$BZ$4,M$4) -> -13289710 | N42: =SUMIFS($S42:$BZ42,$S$4:$BZ$4,N$4) -> -11791941 | R42: =IF($E$20="Current",R$41,0) -> 0 | S42: =IF($E$20="Current",S$41,0) -> -1476156.8 | T42: =IF($E$20="Current",T$41,0) -> -1476156.8 | U42: =IF($E$20="Current",U$41,0) -> -1476156.8 | V42: =IF($E$20="Current",V$41,0) -> -1476156.8 | W42: =IF($E$20="Current",W$41,0) -> -1476156.8 | X42: =IF($E$20="Current",X$41,0) -> -1425251.9 | Y42: =IF($E$20="Current",Y$41,0) -> -1425251.9 | ... BZ42: =IF($E$20="Current",BZ$41,0) -> -895567.19
D43: PIK | J43: =SUMIFS($S43:$BZ43,$S$4:$BZ$4,J$4) -> 0 | K43: =SUMIFS($S43:$BZ43,$S$4:$BZ$4,K$4) -> 0 | L43: =SUMIFS($S43:$BZ43,$S$4:$BZ$4,L$4) -> 0 | M43: =SUMIFS($S43:$BZ43,$S$4:$BZ$4,M$4) -> 0 | N43: =SUMIFS($S43:$BZ43,$S$4:$BZ$4,N$4) -> 0 | R43: =IF($E$20="PIK",-R$41,0) -> 0 | S43: =IF($E$20="PIK",-S$41,0) -> 0 | T43: =IF($E$20="PIK",-T$41,0) -> 0 | U43: =IF($E$20="PIK",-U$41,0) -> 0 | V43: =IF($E$20="PIK",-V$41,0) -> 0 | W43: =IF($E$20="PIK",-W$41,0) -> 0 | X43: =IF($E$20="PIK",-X$41,0) -> 0 | Y43: =IF($E$20="PIK",-Y$41,0) -> 0 | ... BZ43: =IF($E$20="PIK",-BZ$41,0) -> 0
D44: Amortisation | J44: =SUMIFS($S44:$BZ44,$S$4:$BZ$4,J$4) -> -14092373 | K44: =SUMIFS($S44:$BZ44,$S$4:$BZ$4,K$4) -> -14961444 | L44: =SUMIFS($S44:$BZ44,$S$4:$BZ$4,L$4) -> -15852712 | M44: =SUMIFS($S44:$BZ44,$S$4:$BZ$4,M$4) -> -16763016 | N44: =SUMIFS($S44:$BZ44,$S$4:$BZ$4,N$4) -> -17718277 | R44: =R45+R46 -> 0 | S44: =S45+S46 -> 0 | T44: =T45+T46 -> 0 | U44: =U45+U46 -> 0 | V44: =V45+V46 -> 0 | W44: =W45+W46 -> -6960554.8 | X44: =X45+X46 -> 0 | Y44: =Y45+Y46 -> 0 | ... BZ44: =BZ45+BZ46 -> 0
D45: Contracted Amortisation | J45: =SUMIFS($S45:$BZ45,$S$4:$BZ$4,J$4) -> 0 | K45: =SUMIFS($S45:$BZ45,$S$4:$BZ$4,K$4) -> 0 | L45: =SUMIFS($S45:$BZ45,$S$4:$BZ$4,L$4) -> 0 | M45: =SUMIFS($S45:$BZ45,$S$4:$BZ$4,M$4) -> 0 | N45: =SUMIFS($S45:$BZ45,$S$4:$BZ$4,N$4) -> 0 | R45: =(-R$35*$E$27)/12 -> 0 | S45: =(-S$35*$E$27)/12 -> 0 | T45: =(-T$35*$E$27)/12 -> 0 | U45: =(-U$35*$E$27)/12 -> 0 | V45: =(-V$35*$E$27)/12 -> 0 | W45: =(-W$35*$E$27)/12 -> 0 | X45: =(-X$35*$E$27)/12 -> 0 | Y45: =(-Y$35*$E$27)/12 -> 0 | ... BZ45: =(-BZ$35*$E$27)/12 -> 0
D46: Asset Sales Amortisation | J46: =SUMIFS($S46:$BZ46,$S$4:$BZ$4,J$4) -> -14092373 | K46: =SUMIFS($S46:$BZ46,$S$4:$BZ$4,K$4) -> -14961444 | L46: =SUMIFS($S46:$BZ46,$S$4:$BZ$4,L$4) -> -15852712 | M46: =SUMIFS($S46:$BZ46,$S$4:$BZ$4,M$4) -> -16763016 | N46: =SUMIFS($S46:$BZ46,$S$4:$BZ$4,N$4) -> -17718277 | R46: =(-IF((1+$E$29)*($E$30*(SUM(R$33:$S$33)))>$R$36,(MAX(0,($R$36-((1+$E$29)*$E$30*(SUM(R$33:$S$33)))))),((1+$E$29))*($E$30*R$33))) -> 0 | S46: =(-IF((1+$E$29)*($E$30*(SUM(S$33:$S$33)))>$R$36,(MAX(0,($R$36-((1+$E$29)*$E$30*(SUM(S$33:$S$33)))))),((1+$E$29))*($E$30*S$33))) -> 0 | T46: =(-IF((1+$E$29)*($E$30*(SUM($S$33:T$33)))>$R$36,(MAX(0,($R$36-((1+$E$29)*$E$30*(SUM($S$33:T$33)))))),((1+$E$29))*($E$30*T$33))) -> 0 | U46: =(-IF((1+$E$29)*($E$30*(SUM($S$33:U$33)))>$R$36,(MAX(0,($R$36-((1+$E$29)*$E$30*(SUM($S$33:U$33)))))),((1+$E$29))*($E$30*U$33))) -> 0 | V46: =(-IF((1+$E$29)*($E$30*(SUM($S$33:V$33)))>$R$36,(MAX(0,($R$36-((1+$E$29)*$E$30*(SUM($S$33:V$33)))))),((1+$E$29))*($E$30*V$33))) -> 0 | W46: =(-IF((1+$E$29)*($E$30*(SUM($S$33:W$33)))>$R$36,(MAX(0,($R$36-((1+$E$29)*$E$30*(SUM($S$33:W$33)))))),((1+$E$29))*($E$30*W$33))) -> -6960554.8 | X46: =(-IF((1+$E$29)*($E$30*(SUM($S$33:X$33)))>$R$36,(MAX(0,($R$36-((1+$E$29)*$E$30*(SUM($S$33:X$33)))))),((1+$E$29))*($E$30*X$33))) -> 0 | Y46: =(-IF((1+$E$29)*($E$30*(SUM($S$33:Y$33)))>$R$36,(MAX(0,($R$36-((1+$E$29)*$E$30*(SUM($S$33:Y$33)))))),((1+$E$29))*($E$30*Y$33))) -> 0 | Z46: =(-IF((1+$E$29)*($E$30*(SUM($S$33:Z$33)))>$R$36,(MAX(0,($R$36-((1+$E$29)*$E$30*(SUM($S$33:Z$33)))))),((1+$E$29))*($E$30*Z$33))) -> 0 | AA46: =(-IF((1+$E$29)*($E$30*(SUM($S$33:AA$33)))>$R$36,(MAX(0,($R$36-((1+$E$29)*$E$30*(SUM($S$33:AA$33)))))),((1+$E$29))*($E$30*AA$33))) -> 0 | ... BZ46: =(-IF((1+$E$29)*($E$30*(SUM($S$33:BZ$33)))>$R$36,(MAX(0,($R$36-((1+$E$29)*$E$30*(SUM($S$33:BZ$33)))))),((1+$E$29))*($E$30*BZ$33))) -> 0
D47: Exit Fee | J47: =SUMIFS($S47:$BZ47,$S$4:$BZ$4,J$4) -> 0 | K47: =SUMIFS($S47:$BZ47,$S$4:$BZ$4,K$4) -> 0 | L47: =SUMIFS($S47:$BZ47,$S$4:$BZ$4,L$4) -> 0 | M47: =SUMIFS($S47:$BZ47,$S$4:$BZ$4,M$4) -> 0 | N47: =SUMIFS($S47:$BZ47,$S$4:$BZ$4,N$4) -> -1224567.7 | R47: =-IF(R$6=$E$9,R35*$E$28,0) -> 0 | S47: =-IF(S$6=$E$9,S35*$E$28,0) -> 0 | T47: =-IF(T$6=$E$9,T35*$E$28,0) -> 0 | U47: =-IF(U$6=$E$9,U35*$E$28,0) -> 0 | V47: =-IF(V$6=$E$9,V35*$E$28,0) -> 0 | W47: =-IF(W$6=$E$9,W35*$E$28,0) -> 0 | X47: =-IF(X$6=$E$9,X35*$E$28,0) -> 0 | Y47: =-IF(Y$6=$E$9,Y35*$E$28,0) -> 0 | ... BZ47: =-IF(BZ$6=$E$9,BZ35*$E$28,0) -> -1224567.7
D48: Balloon Repayment | J48: =SUMIFS($S48:$BZ48,$S$4:$BZ$4,J$4) -> 0 | K48: =SUMIFS($S48:$BZ48,$S$4:$BZ$4,K$4) -> 0 | L48: =SUMIFS($S48:$BZ48,$S$4:$BZ$4,L$4) -> 0 | M48: =SUMIFS($S48:$BZ48,$S$4:$BZ$4,M$4) -> 0 | N48: =SUMIFS($S48:$BZ48,$S$4:$BZ$4,N$4) -> -1.2245677e+08 | R48: =IF(R$6=$E$9,-(R35+R36+R40+R43+R44),0) -> 0 | S48: =IF(S$6=$E$9,-(S35+S36+S40+S43+S44),0) -> 0 | T48: =IF(T$6=$E$9,-(T35+T36+T40+T43+T44),0) -> 0 | U48: =IF(U$6=$E$9,-(U35+U36+U40+U43+U44),0) -> 0 | V48: =IF(V$6=$E$9,-(V35+V36+V40+V43+V44),0) -> 0 | W48: =IF(W$6=$E$9,-(W35+W36+W40+W43+W44),0) -> 0 | X48: =IF(X$6=$E$9,-(X35+X36+X40+X43+X44),0) -> 0 | Y48: =IF(Y$6=$E$9,-(Y35+Y36+Y40+Y43+Y44),0) -> 0 | ... BZ48: =IF(BZ$6=$E$9,-(BZ35+BZ36+BZ40+BZ43+BZ44),0) -> -1.2245677e+08
D49: Closing Balance | J49: {=INDEX($S49:$BZ49,0,MATCH(J$6,$S$6:$BZ$6,0))} -> 1.8775222e+08 | K49: {=INDEX($S49:$BZ49,0,MATCH(K$6,$S$6:$BZ$6,0))} -> 1.7279078e+08 | L49: {=INDEX($S49:$BZ49,0,MATCH(L$6,$S$6:$BZ$6,0))} -> 1.5693807e+08 | M49: {=INDEX($S49:$BZ49,0,MATCH(M$6,$S$6:$BZ$6,0))} -> 1.4017505e+08 | N49: {=INDEX($S49:$BZ49,0,MATCH(N$6,$S$6:$BZ$6,0))} -> 0 | R49: =R35+R36+R40+R43+R44+R48 -> 2.0184459e+08 | S49: =S35+S36+S40+S43+S44+S48 -> 2.0184459e+08 | T49: =T35+T36+T40+T43+T44+T48 -> 2.0184459e+08 | U49: =U35+U36+U40+U43+U44+U48 -> 2.0184459e+08 | V49: =V35+V36+V40+V43+V44+V48 -> 2.0184459e+08 | W49: =W35+W36+W40+W43+W44+W48 -> 1.9488404e+08 | X49: =X35+X36+X40+X43+X44+X48 -> 1.9488404e+08 | Y49: =Y35+Y36+Y40+Y43+Y44+Y48 -> 1.9488404e+08 | ... BZ49: =BZ35+BZ36+BZ40+BZ43+BZ44+BZ48 -> 0
D51: Equity Cashflow | J51: =SUMIFS($S51:$BZ51,$S$4:$BZ$4,J$4) -> -31397764 | K51: =SUMIFS($S51:$BZ51,$S$4:$BZ$4,K$4) -> -31005739 | L51: =SUMIFS($S51:$BZ51,$S$4:$BZ$4,L$4) -> -30559065 | M51: =SUMIFS($S51:$BZ51,$S$4:$BZ$4,M$4) -> -30052726 | N51: =SUMIFS($S51:$BZ51,$S$4:$BZ$4,N$4) -> -1.5319156e+08 | R51: =R36+R37+R39+R42+R44+R47+R48 -> 1.9982615e+08 | S51: =S36+S37+S39+S42+S44+S47+S48 -> -1476156.8 | T51: =T36+T37+T39+T42+T44+T47+T48 -> -1476156.8 | U51: =U36+U37+U39+U42+U44+U47+U48 -> -1476156.8 | V51: =V36+V37+V39+V42+V44+V47+V48 -> -1476156.8 | W51: =W36+W37+W39+W42+W44+W47+W48 -> -8436711.6 | X51: =X36+X37+X39+X42+X44+X47+X48 -> -1425251.9 | Y51: =Y36+Y37+Y39+Y42+Y44+Y47+Y48 -> -1425251.9 | ... BZ51: =BZ36+BZ37+BZ39+BZ42+BZ44+BZ47+BZ48 -> -1.2457691e+08
D53: SONIA 3M | J53: =AVERAGEIFS($S53:$BZ53,$S$4:$BZ$4,J$4) -> 0.054891252 | K53: =AVERAGEIFS($S53:$BZ53,$S$4:$BZ$4,K$4) -> 0.049270045 | L53: =AVERAGEIFS($S53:$BZ53,$S$4:$BZ$4,L$4) -> 0.044287893 | M53: =AVERAGEIFS($S53:$BZ53,$S$4:$BZ$4,M$4) -> 0.041617367 | N53: =AVERAGEIFS($S53:$BZ53,$S$4:$BZ$4,N$4) -> 0.039487561 | R53: 0.05428808 | S53: 0.05428808 | T53: 0.055188803 | U53: 0.055532152 | V53: 0.055589406 | W53: 0.055679735 | X53: 0.055692061 | Y53: 0.055595272 | Z53: 0.05548102 | AA53: 0.055115718 | AB53: 0.05466469 | AC53: 0.054082932 | AD53: 0.051785147 | AE53: 0.051785147 | AF53: 0.051785147 | AG53: 0.051785147 | AH53: 0.051785147 | AI53: 0.051785147 | AJ53: 0.047966777 | AK53: 0.047966777 | AL53: 0.047966777 | AM53: 0.047966777 | AN53: 0.047966777 | AO53: 0.047966777 | AP53: 0.044514143 | AQ53: 0.044514143 | AR53: 0.044514143 | AS53: 0.044514143 | AT53: 0.044514143 | AU53: 0.044514143 | AV53: 0.044514143 | AW53: 0.044514143 | AX53: 0.044514143 | AY53: 0.044514143 | AZ53: 0.044514143 | BA53: 0.044514143 | BB53: 0.041799147 | BC53: 0.041799147 | BD53: 0.041799147 | BE53: 0.041799147 | BF53: 0.041799147 | BG53: 0.041799147 | BH53: 0.041799147 | BI53: 0.041799147 | BJ53: 0.041799147 | BK53: 0.041799147 | BL53: 0.041799147 | BM53: 0.041799147 | BN53: 0.039617789 | BO53: 0.039617789 | BP53: 0.039617789 | BQ53: 0.039617789 | BR53: 0.039617789 | BS53: 0.039617789 | BT53: 0.039617789 | BU53: 0.039617789 | BV53: 0.039617789 | BW53: 0.039617789 | BX53: 0.039617789 | BY53: 0.039617789 | BZ53: 0.038055062

Sheet Portfolio
I2: FY23 | J2: FY24 | K2: FY25 | L2: LTM | W2: {=INDEX(Index_Tab!$G$4:$K$4,MATCH(1,(W$4>=Index_Tab!$G$5:$K$5)*(W$4<=Index_Tab!$G$17:$K$17),0))} -> FY27E | X2: {=INDEX(Index_Tab!$G$4:$K$4,MATCH(1,(X$4>=Index_Tab!$G$5:$K$5)*(X$4<=Index_Tab!$G$17:$K$17),0))} -> FY27E | Y2: {=INDEX(Index_Tab!$G$4:$K$4,MATCH(1,(Y$4>=Index_Tab!$G$5:$K$5)*(Y$4<=Index_Tab!$G$17:$K$17),0))} -> FY27E | Z2: {=INDEX(Index_Tab!$G$4:$K$4,MATCH(1,(Z$4>=Index_Tab!$G$5:$K$5)*(Z$4<=Index_Tab!$G$17:$K$17),0))} -> FY27E | AA2: {=INDEX(Index_Tab!$G$4:$K$4,MATCH(1,(AA$4>=Index_Tab!$G$5:$K$5)*(AA$4<=Index_Tab!$G$17:$K$17),0))} -> FY27E | AB2: {=INDEX(Index_Tab!$G$4:$K$4,MATCH(1,(AB$4>=Index_Tab!$G$5:$K$5)*(AB$4<=Index_Tab!$G$17:$K$17),0))} -> FY27E | AC2: {=INDEX(Index_Tab!$G$4:$K$4,MATCH(1,(AC$4>=Index_Tab!$G$5:$K$5)*(AC$4<=Index_Tab!$G$17:$K$17),0))} -> FY27E | AD2: {=INDEX(Index_Tab!$G$4:$K$4,MATCH(1,(AD$4>=Index_Tab!$G$5:$K$5)*(AD$4<=Index_Tab!$G$17:$K$17),0))} -> FY27E | ... CD2: {=INDEX(Index_Tab!$G$4:$K$4,MATCH(1,(CD$4>=Index_Tab!$G$5:$K$5)*(CD$4<=Index_Tab!$G$17:$K$17),0))} -> FY31E
I3: FY23A | J3: FY24A | K3: FY25A | L3: FY26 P4 LTM | N3: ='Detailed Assumptions'!$E$17 -> FY26E | O3: ='Detailed Assumptions'!$F$17 -> FY27E | P3: ='Detailed Assumptions'!$G$17 -> FY28E | Q3: ='Detailed Assumptions'!$H$17 -> FY29E | R3: ='Detailed Assumptions'!$I$17 -> FY30E | S3: ='Detailed Assumptions'!$J$17 -> FY31E | U3: =N3&"-"&S3 -> FY26E-FY31E | W3: ='Detailed Assumptions'!$E$12 -> 46296 | X3: =W4+1 -> 46327 | Y3: =X4+1 -> 46357 | Z3: =Y4+1 -> 46388 | AA3: =Z4+1 -> 46419 | AB3: =AA4+1 -> 46447 | AC3: =AB4+1 -> 46478 | AD3: =AC4+1 -> 46508 | AE3: =AD4+1 -> 46539 | ... CD3: =CC4+1 -> 48092
I4: 45199 | J4: =EDATE(I4,12) -> 45565 | K4: =EDATE(J4,12) -> 45930 | L4: 46040 | N4: ='Detailed Assumptions'!$E$12-1 -> 46295 | O4: =EOMONTH(N4,12) -> 46660 | P4: =EOMONTH(O4,12) -> 47026 | Q4: =EOMONTH(P4,12) -> 47391 | R4: =EOMONTH(Q4,12) -> 47756 | S4: =EOMONTH(R4,12) -> 48121 | U4: CAGR | W4: =EOMONTH(W3,0) -> 46326 | X4: =EOMONTH(X3,0) -> 46356 | Y4: =EOMONTH(Y3,0) -> 46387 | Z4: =EOMONTH(Z3,0) -> 46418 | AA4: =EOMONTH(AA3,0) -> 46446 | AB4: =EOMONTH(AB3,0) -> 46477 | AC4: =EOMONTH(AC3,0) -> 46507 | AD4: =EOMONTH(AD3,0) -> 46538 | ... CD4: =EOMONTH(CD3,0) -> 48121
C7: X | E7: Consolidated Output
E9: Total no. of pubs within sub-portfolio | I9: =$N$9 -> 308 | J9: =$N$9 -> 308 | K9: =$N$9 -> 308 | L9: =$N$9 -> 308 | N9: ='Value Segment'!I9+'Mid-Market Segment'!I9+'Upper Mid-Market Segment'!I9+'Premium Segment'!I9+'Closures Overlay'!I9+'Disposals Overlay'!I9 -> 308 | O9: =INDEX($W9:$CD9,MATCH(O$4,$W$4:$CD$4,0)) -> 292 | P9: =INDEX($W9:$CD9,MATCH(P$4,$W$4:$CD$4,0)) -> 276 | Q9: =INDEX($W9:$CD9,MATCH(Q$4,$W$4:$CD$4,0)) -> 260 | R9: =INDEX($W9:$CD9,MATCH(R$4,$W$4:$CD$4,0)) -> 244 | S9: =INDEX($W9:$CD9,MATCH(S$4,$W$4:$CD$4,0)) -> 228 | W9: ='Value Segment'!R9+'Mid-Market Segment'!R9+'Upper Mid-Market Segment'!R9+'Premium Segment'!R9+'Closures Overlay'!R9+'Disposals Overlay'!R9 -> 308 | X9: ='Value Segment'!S9+'Mid-Market Segment'!S9+'Upper Mid-Market Segment'!S9+'Premium Segment'!S9+'Closures Overlay'!S9+'Disposals Overlay'!S9 -> 308 | Y9: ='Value Segment'!T9+'Mid-Market Segment'!T9+'Upper Mid-Market Segment'!T9+'Premium Segment'!T9+'Closures Overlay'!T9+'Disposals Overlay'!T9 -> 308 | Z9: ='Value Segment'!U9+'Mid-Market Segment'!U9+'Upper Mid-Market Segment'!U9+'Premium Segment'!U9+'Closures Overlay'!U9+'Disposals Overlay'!U9 -> 308 | AA9: ='Value Segment'!V9+'Mid-Market Segment'!V9+'Upper Mid-Market Segment'!V9+'Premium Segment'!V9+'Closures Overlay'!V9+'Disposals Overlay'!V9 -> 308 | AB9: ='Value Segment'!W9+'Mid-Market Segment'!W9+'Upper Mid-Market Segment'!W9+'Premium Segment'!W9+'Closures Overlay'!W9+'Disposals Overlay'!W9 -> 300 | AC9: ='Value Segment'!X9+'Mid-Market Segment'!X9+'Upper Mid-Market Segment'!X9+'Premium Segment'!X9+'Closures Overlay'!X9+'Disposals Overlay'!X9 -> 300 | AD9: ='Value Segment'!Y9+'Mid-Market Segment'!Y9+'Upper Mid-Market Segment'!Y9+'Premium Segment'!Y9+'Closures Overlay'!Y9+'Disposals Overlay'!Y9 -> 300 | ... CD9: ='Value Segment'!BY9+'Mid-Market Segment'!BY9+'Upper Mid-Market Segment'!BY9+'Premium Segment'!BY9+'Closures Overlay'!BY9+'Disposals Overlay'!BY9 -> 228
E11: Total no. of pubs within sub-portfolio | I11: =I9 -> 308 | J11: =J9 -> 308 | K11: =K9 -> 308 | L11: =L9 -> 308 | N11: =N9 -> 308 | O11: =INDEX($W11:$CD11,MATCH(O$4,$W$4:$CD$4,0)) -> 292 | P11: =INDEX($W11:$CD11,MATCH(P$4,$W$4:$CD$4,0)) -> 276 | Q11: =INDEX($W11:$CD11,MATCH(Q$4,$W$4:$CD$4,0)) -> 260 | R11: =INDEX($W11:$CD11,MATCH(R$4,$W$4:$CD$4,0)) -> 244 | S11: =INDEX($W11:$CD11,MATCH(S$4,$W$4:$CD$4,0)) -> 228 | W11: ='Value Segment'!R11+'Mid-Market Segment'!R11+'Upper Mid-Market Segment'!R11+'Premium Segment'!R11+'Closures Overlay'!R11+'Disposals Overlay'!R11 -> 308 | X11: ='Value Segment'!S11+'Mid-Market Segment'!S11+'Upper Mid-Market Segment'!S11+'Premium Segment'!S11+'Closures Overlay'!S11+'Disposals Overlay'!S11 -> 308 | Y11: ='Value Segment'!T11+'Mid-Market Segment'!T11+'Upper Mid-Market Segment'!T11+'Premium Segment'!T11+'Closures Overlay'!T11+'Disposals Overlay'!T11 -> 308 | Z11: ='Value Segment'!U11+'Mid-Market Segment'!U11+'Upper Mid-Market Segment'!U11+'Premium Segment'!U11+'Closures Overlay'!U11+'Disposals Overlay'!U11 -> 308 | AA11: ='Value Segment'!V11+'Mid-Market Segment'!V11+'Upper Mid-Market Segment'!V11+'Premium Segment'!V11+'Closures Overlay'!V11+'Disposals Overlay'!V11 -> 308 | AB11: ='Value Segment'!W11+'Mid-Market Segment'!W11+'Upper Mid-Market Segment'!W11+'Premium Segment'!W11+'Closures Overlay'!W11+'Disposals Overlay'!W11 -> 300 | AC11: ='Value Segment'!X11+'Mid-Market Segment'!X11+'Upper Mid-Market Segment'!X11+'Premium Segment'!X11+'Closures Overlay'!X11+'Disposals Overlay'!X11 -> 300 | AD11: ='Value Segment'!Y11+'Mid-Market Segment'!Y11+'Upper Mid-Market Segment'!Y11+'Premium Segment'!Y11+'Closures Overlay'!Y11+'Disposals Overlay'!Y11 -> 300 | ... CD11: ='Value Segment'!BY11+'Mid-Market Segment'!BY11+'Upper Mid-Market Segment'!BY11+'Premium Segment'!BY11+'Closures Overlay'!BY11+'Disposals Overlay'!BY11 -> 228
E12: of which open | I12: 0 | J12: 0 | K12: 0 | L12: 0 | N12: =N11-N13 -> 298 | O12: =INDEX($W12:$CD12,MATCH(O$4,$W$4:$CD$4,0)) -> 282 | P12: =INDEX($W12:$CD12,MATCH(P$4,$W$4:$CD$4,0)) -> 266 | Q12: =INDEX($W12:$CD12,MATCH(Q$4,$W$4:$CD$4,0)) -> 250 | R12: =INDEX($W12:$CD12,MATCH(R$4,$W$4:$CD$4,0)) -> 234 | S12: =INDEX($W12:$CD12,MATCH(S$4,$W$4:$CD$4,0)) -> 218 | W12: =W11-W13 -> 298 | X12: =X11-X13 -> 298 | Y12: =Y11-Y13 -> 298 | Z12: =Z11-Z13 -> 298 | AA12: =AA11-AA13 -> 298 | AB12: =AB11-AB13 -> 290 | AC12: =AC11-AC13 -> 290 | AD12: =AD11-AD13 -> 290 | ... CD12: =CD11-CD13 -> 218
E13: of which closed | I13: 0 | J13: 0 | K13: 0 | L13: 0 | N13: ='Value Segment'!I13+'Mid-Market Segment'!I13+'Upper Mid-Market Segment'!I13+'Premium Segment'!I13+'Closures Overlay'!I13+'Disposals Overlay'!I13 -> 10 | O13: =INDEX($W13:$CD13,MATCH(O$4,$W$4:$CD$4,0)) -> 10 | P13: =INDEX($W13:$CD13,MATCH(P$4,$W$4:$CD$4,0)) -> 10 | Q13: =INDEX($W13:$CD13,MATCH(Q$4,$W$4:$CD$4,0)) -> 10 | R13: =INDEX($W13:$CD13,MATCH(R$4,$W$4:$CD$4,0)) -> 10 | S13: =INDEX($W13:$CD13,MATCH(S$4,$W$4:$CD$4,0)) -> 10 | W13: ='Value Segment'!R13+'Mid-Market Segment'!R13+'Upper Mid-Market Segment'!R13+'Premium Segment'!R13+'Closures Overlay'!R13+'Disposals Overlay'!R13 -> 10 | X13: ='Value Segment'!S13+'Mid-Market Segment'!S13+'Upper Mid-Market Segment'!S13+'Premium Segment'!S13+'Closures Overlay'!S13+'Disposals Overlay'!S13 -> 10 | Y13: ='Value Segment'!T13+'Mid-Market Segment'!T13+'Upper Mid-Market Segment'!T13+'Premium Segment'!T13+'Closures Overlay'!T13+'Disposals Overlay'!T13 -> 10 | Z13: ='Value Segment'!U13+'Mid-Market Segment'!U13+'Upper Mid-Market Segment'!U13+'Premium Segment'!U13+'Closures Overlay'!U13+'Disposals Overlay'!U13 -> 10 | AA13: ='Value Segment'!V13+'Mid-Market Segment'!V13+'Upper Mid-Market Segment'!V13+'Premium Segment'!V13+'Closures Overlay'!V13+'Disposals Overlay'!V13 -> 10 | AB13: ='Value Segment'!W13+'Mid-Market Segment'!W13+'Upper Mid-Market Segment'!W13+'Premium Segment'!W13+'Closures Overlay'!W13+'Disposals Overlay'!W13 -> 10 | AC13: ='Value Segment'!X13+'Mid-Market Segment'!X13+'Upper Mid-Market Segment'!X13+'Premium Segment'!X13+'Closures Overlay'!X13+'Disposals Overlay'!X13 -> 10 | AD13: ='Value Segment'!Y13+'Mid-Market Segment'!Y13+'Upper Mid-Market Segment'!Y13+'Premium Segment'!Y13+'Closures Overlay'!Y13+'Disposals Overlay'!Y13 -> 10 | ... CD13: ='Value Segment'!BY13+'Mid-Market Segment'!BY13+'Upper Mid-Market Segment'!BY13+'Premium Segment'!BY13+'Closures Overlay'!BY13+'Disposals Overlay'!BY13 -> 10
E15: Total no. of pubs within sub-portfolio | I15: =I11 -> 308 | J15: =J11 -> 308 | K15: =K11 -> 308 | L15: =L11 -> 308 | N15: ='Value Segment'!I15+'Mid-Market Segment'!I15+'Upper Mid-Market Segment'!I15+'Premium Segment'!I15+'Closures Overlay'!I15+'Disposals Overlay'!I15 -> 308 | O15: =INDEX($W15:$CD15,MATCH(O$4,$W$4:$CD$4,0)) -> 292 | P15: =INDEX($W15:$CD15,MATCH(P$4,$W$4:$CD$4,0)) -> 276 | Q15: =INDEX($W15:$CD15,MATCH(Q$4,$W$4:$CD$4,0)) -> 260 | R15: =INDEX($W15:$CD15,MATCH(R$4,$W$4:$CD$4,0)) -> 244 | S15: =INDEX($W15:$CD15,MATCH(S$4,$W$4:$CD$4,0)) -> 228 | W15: ='Value Segment'!R15+'Mid-Market Segment'!R15+'Upper Mid-Market Segment'!R15+'Premium Segment'!R15+'Closures Overlay'!R15+'Disposals Overlay'!R15 -> 308 | X15: ='Value Segment'!S15+'Mid-Market Segment'!S15+'Upper Mid-Market Segment'!S15+'Premium Segment'!S15+'Closures Overlay'!S15+'Disposals Overlay'!S15 -> 308 | Y15: ='Value Segment'!T15+'Mid-Market Segment'!T15+'Upper Mid-Market Segment'!T15+'Premium Segment'!T15+'Closures Overlay'!T15+'Disposals Overlay'!T15 -> 308 | Z15: ='Value Segment'!U15+'Mid-Market Segment'!U15+'Upper Mid-Market Segment'!U15+'Premium Segment'!U15+'Closures Overlay'!U15+'Disposals Overlay'!U15 -> 308 | AA15: ='Value Segment'!V15+'Mid-Market Segment'!V15+'Upper Mid-Market Segment'!V15+'Premium Segment'!V15+'Closures Overlay'!V15+'Disposals Overlay'!V15 -> 308 | AB15: ='Value Segment'!W15+'Mid-Market Segment'!W15+'Upper Mid-Market Segment'!W15+'Premium Segment'!W15+'Closures Overlay'!W15+'Disposals Overlay'!W15 -> 300 | AC15: ='Value Segment'!X15+'Mid-Market Segment'!X15+'Upper Mid-Market Segment'!X15+'Premium Segment'!X15+'Closures Overlay'!X15+'Disposals Overlay'!X15 -> 300 | AD15: ='Value Segment'!Y15+'Mid-Market Segment'!Y15+'Upper Mid-Market Segment'!Y15+'Premium Segment'!Y15+'Closures Overlay'!Y15+'Disposals Overlay'!Y15 -> 300 | ... CD15: ='Value Segment'!BY15+'Mid-Market Segment'!BY15+'Upper Mid-Market Segment'!BY15+'Premium Segment'!BY15+'Closures Overlay'!BY15+'Disposals Overlay'!BY15 -> 228
E16: of which retained | I16: 0 | J16: 0 | K16: 0 | L16: 0 | N16: ='Value Segment'!I16+'Mid-Market Segment'!I16+'Upper Mid-Market Segment'!I16+'Premium Segment'!I16+'Closures Overlay'!I16+'Disposals Overlay'!I16 -> 308 | O16: =INDEX($W16:$CD16,MATCH(O$4,$W$4:$CD$4,0)) -> 292 | P16: =INDEX($W16:$CD16,MATCH(P$4,$W$4:$CD$4,0)) -> 276 | Q16: =INDEX($W16:$CD16,MATCH(Q$4,$W$4:$CD$4,0)) -> 260 | R16: =INDEX($W16:$CD16,MATCH(R$4,$W$4:$CD$4,0)) -> 244 | S16: =INDEX($W16:$CD16,MATCH(S$4,$W$4:$CD$4,0)) -> 228 | W16: =$W$15-W17 -> 308 | X16: =$W$15-X17 -> 308 | Y16: =$W$15-Y17 -> 308 | Z16: =$W$15-Z17 -> 308 | AA16: =$W$15-AA17 -> 308 | AB16: =$W$15-AB17 -> 300 | AC16: =$W$15-AC17 -> 300 | AD16: =$W$15-AD17 -> 300 | ... CD16: =$W$15-CD17 -> 228
E17: of which disposed | I17: 0 | J17: 0 | K17: 0 | L17: 0 | N17: ='Value Segment'!I17+'Mid-Market Segment'!I17+'Upper Mid-Market Segment'!I17+'Premium Segment'!I17+'Closures Overlay'!I17+'Disposals Overlay'!I17 -> 0 | O17: =INDEX($W17:$CD17,MATCH(O$4,$W$4:$CD$4,0)) -> 16 | P17: =INDEX($W17:$CD17,MATCH(P$4,$W$4:$CD$4,0)) -> 32 | Q17: =INDEX($W17:$CD17,MATCH(Q$4,$W$4:$CD$4,0)) -> 48 | R17: =INDEX($W17:$CD17,MATCH(R$4,$W$4:$CD$4,0)) -> 64 | S17: =INDEX($W17:$CD17,MATCH(S$4,$W$4:$CD$4,0)) -> 80 | W17: =-'Disposals Overlay'!R17 -> 0 | X17: =-'Disposals Overlay'!S17 -> 0 | Y17: =-'Disposals Overlay'!T17 -> 0 | Z17: =-'Disposals Overlay'!U17 -> 0 | AA17: =-'Disposals Overlay'!V17 -> 0 | AB17: =-'Disposals Overlay'!W17 -> 8 | AC17: =-'Disposals Overlay'!X17 -> 8 | AD17: =-'Disposals Overlay'!Y17 -> 8 | ... CD17: =-'Disposals Overlay'!BY17 -> 80
E19: BCF Volumes (Barrels) | I19: 48080.24 | J19: 46956.913 | K19: 45148.004 | L19: 44564.816 | N19: ='Value Segment'!I19+'Mid-Market Segment'!I19+'Upper Mid-Market Segment'!I19+'Premium Segment'!I19+'Closures Overlay'!I19+'Disposals Overlay'!I19 -> 46171.62 | O19: ='Value Segment'!J19+'Mid-Market Segment'!J19+'Upper Mid-Market Segment'!J19+'Premium Segment'!J19+'Closures Overlay'!J19+'Disposals Overlay'!J19 -> 45875.273 | P19: ='Value Segment'!K19+'Mid-Market Segment'!K19+'Upper Mid-Market Segment'!K19+'Premium Segment'!K19+'Closures Overlay'!K19+'Disposals Overlay'!K19 -> 44232.509 | Q19: ='Value Segment'!L19+'Mid-Market Segment'!L19+'Upper Mid-Market Segment'!L19+'Premium Segment'!L19+'Closures Overlay'!L19+'Disposals Overlay'!L19 -> 42482.492 | R19: ='Value Segment'!M19+'Mid-Market Segment'!M19+'Upper Mid-Market Segment'!M19+'Premium Segment'!M19+'Closures Overlay'!M19+'Disposals Overlay'!M19 -> 40663.946 | S19: ='Value Segment'!N19+'Mid-Market Segment'!N19+'Upper Mid-Market Segment'!N19+'Premium Segment'!N19+'Closures Overlay'!N19+'Disposals Overlay'!N19 -> 38757.829 | U19: =IFERROR(((S19/N19)^(1/5))-1,0) -> -0.034400868 | W19: ='Value Segment'!R19+'Mid-Market Segment'!R19+'Upper Mid-Market Segment'!R19+'Premium Segment'!R19+'Closures Overlay'!R19+'Disposals Overlay'!R19 -> 3847.635 | X19: ='Value Segment'!S19+'Mid-Market Segment'!S19+'Upper Mid-Market Segment'!S19+'Premium Segment'!S19+'Closures Overlay'!S19+'Disposals Overlay'!S19 -> 3847.635 | Y19: ='Value Segment'!T19+'Mid-Market Segment'!T19+'Upper Mid-Market Segment'!T19+'Premium Segment'!T19+'Closures Overlay'!T19+'Disposals Overlay'!T19 -> 3847.635 | Z19: ='Value Segment'!U19+'Mid-Market Segment'!U19+'Upper Mid-Market Segment'!U19+'Premium Segment'!U19+'Closures Overlay'!U19+'Disposals Overlay'!U19 -> 3847.635 | AA19: ='Value Segment'!V19+'Mid-Market Segment'!V19+'Upper Mid-Market Segment'!V19+'Premium Segment'!V19+'Closures Overlay'!V19+'Disposals Overlay'!V19 -> 3847.635 | AB19: ='Value Segment'!W19+'Mid-Market Segment'!W19+'Upper Mid-Market Segment'!W19+'Premium Segment'!W19+'Closures Overlay'!W19+'Disposals Overlay'!W19 -> 3744.3428 | AC19: ='Value Segment'!X19+'Mid-Market Segment'!X19+'Upper Mid-Market Segment'!X19+'Premium Segment'!X19+'Closures Overlay'!X19+'Disposals Overlay'!X19 -> 3833.0827 | AD19: ='Value Segment'!Y19+'Mid-Market Segment'!Y19+'Upper Mid-Market Segment'!Y19+'Premium Segment'!Y19+'Closures Overlay'!Y19+'Disposals Overlay'!Y19 -> 3833.0827 | ... CD19: ='Value Segment'!BY19+'Mid-Market Segment'!BY19+'Upper Mid-Market Segment'!BY19+'Premium Segment'!BY19+'Closures Overlay'!BY19+'Disposals Overlay'!BY19 -> 3142.7829
E21: BCF
E22: BCF gross sales | I22: 32651168 | J22: 34219750 | K22: 34242594 | L22: 34235780 | N22: ='Value Segment'!I22+'Mid-Market Segment'!I22+'Upper Mid-Market Segment'!I22+'Premium Segment'!I22+'Closures Overlay'!I22+'Disposals Overlay'!I22 -> 35898882 | O22: ='Value Segment'!J22+'Mid-Market Segment'!J22+'Upper Mid-Market Segment'!J22+'Premium Segment'!J22+'Closures Overlay'!J22+'Disposals Overlay'!J22 -> 37005938 | P22: ='Value Segment'!K22+'Mid-Market Segment'!K22+'Upper Mid-Market Segment'!K22+'Premium Segment'!K22+'Closures Overlay'!K22+'Disposals Overlay'!K22 -> 36982657 | Q22: ='Value Segment'!L22+'Mid-Market Segment'!L22+'Upper Mid-Market Segment'!L22+'Premium Segment'!L22+'Closures Overlay'!L22+'Disposals Overlay'!L22 -> 36771740 | R22: ='Value Segment'!M22+'Mid-Market Segment'!M22+'Upper Mid-Market Segment'!M22+'Premium Segment'!M22+'Closures Overlay'!M22+'Disposals Overlay'!M22 -> 36390323 | S22: ='Value Segment'!N22+'Mid-Market Segment'!N22+'Upper Mid-Market Segment'!N22+'Premium Segment'!N22+'Closures Overlay'!N22+'Disposals Overlay'!N22 -> 35860443 | U22: =IFERROR(((S22/N22)^(1/5))-1,0) -> -0.00021424022 | W22: ='Value Segment'!R22+'Mid-Market Segment'!R22+'Upper Mid-Market Segment'!R22+'Premium Segment'!R22+'Closures Overlay'!R22+'Disposals Overlay'!R22 -> 3103739 | X22: ='Value Segment'!S22+'Mid-Market Segment'!S22+'Upper Mid-Market Segment'!S22+'Premium Segment'!S22+'Closures Overlay'!S22+'Disposals Overlay'!S22 -> 3103739 | Y22: ='Value Segment'!T22+'Mid-Market Segment'!T22+'Upper Mid-Market Segment'!T22+'Premium Segment'!T22+'Closures Overlay'!T22+'Disposals Overlay'!T22 -> 3103739 | Z22: ='Value Segment'!U22+'Mid-Market Segment'!U22+'Upper Mid-Market Segment'!U22+'Premium Segment'!U22+'Closures Overlay'!U22+'Disposals Overlay'!U22 -> 3103739 | AA22: ='Value Segment'!V22+'Mid-Market Segment'!V22+'Upper Mid-Market Segment'!V22+'Premium Segment'!V22+'Closures Overlay'!V22+'Disposals Overlay'!V22 -> 3103739 | AB22: ='Value Segment'!W22+'Mid-Market Segment'!W22+'Upper Mid-Market Segment'!W22+'Premium Segment'!W22+'Closures Overlay'!W22+'Disposals Overlay'!W22 -> 3020417.2 | AC22: ='Value Segment'!X22+'Mid-Market Segment'!X22+'Upper Mid-Market Segment'!X22+'Premium Segment'!X22+'Closures Overlay'!X22+'Disposals Overlay'!X22 -> 3092020.4 | AD22: ='Value Segment'!Y22+'Mid-Market Segment'!Y22+'Upper Mid-Market Segment'!Y22+'Premium Segment'!Y22+'Closures Overlay'!Y22+'Disposals Overlay'!Y22 -> 3092020.4 | ... CD22: ='Value Segment'!BY22+'Mid-Market Segment'!BY22+'Upper Mid-Market Segment'!BY22+'Premium Segment'!BY22+'Closures Overlay'!BY22+'Disposals Overlay'!BY22 -> 2907870.9
E23: (-) BCF cost of sales | I23: -11407066 | J23: -11457426 | K23: -11176690 | L23: -11057618 | N23: ='Value Segment'!I23+'Mid-Market Segment'!I23+'Upper Mid-Market Segment'!I23+'Premium Segment'!I23+'Closures Overlay'!I23+'Disposals Overlay'!I23 -> -11435045 | O23: ='Value Segment'!J23+'Mid-Market Segment'!J23+'Upper Mid-Market Segment'!J23+'Premium Segment'!J23+'Closures Overlay'!J23+'Disposals Overlay'!J23 -> -11474525 | P23: ='Value Segment'!K23+'Mid-Market Segment'!K23+'Upper Mid-Market Segment'!K23+'Premium Segment'!K23+'Closures Overlay'!K23+'Disposals Overlay'!K23 -> -11174787 | Q23: ='Value Segment'!L23+'Mid-Market Segment'!L23+'Upper Mid-Market Segment'!L23+'Premium Segment'!L23+'Closures Overlay'!L23+'Disposals Overlay'!L23 -> -10841547 | R23: ='Value Segment'!M23+'Mid-Market Segment'!M23+'Upper Mid-Market Segment'!M23+'Premium Segment'!M23+'Closures Overlay'!M23+'Disposals Overlay'!M23 -> -10483829 | S23: ='Value Segment'!N23+'Mid-Market Segment'!N23+'Upper Mid-Market Segment'!N23+'Premium Segment'!N23+'Closures Overlay'!N23+'Disposals Overlay'!N23 -> -10095891 | U23: =IFERROR(((S23/N23)^(1/5))-1,0) -> -0.024603137 | W23: ='Value Segment'!R23+'Mid-Market Segment'!R23+'Upper Mid-Market Segment'!R23+'Premium Segment'!R23+'Closures Overlay'!R23+'Disposals Overlay'!R23 -> -962359.76 | X23: ='Value Segment'!S23+'Mid-Market Segment'!S23+'Upper Mid-Market Segment'!S23+'Premium Segment'!S23+'Closures Overlay'!S23+'Disposals Overlay'!S23 -> -962359.76 | Y23: ='Value Segment'!T23+'Mid-Market Segment'!T23+'Upper Mid-Market Segment'!T23+'Premium Segment'!T23+'Closures Overlay'!T23+'Disposals Overlay'!T23 -> -962359.76 | Z23: ='Value Segment'!U23+'Mid-Market Segment'!U23+'Upper Mid-Market Segment'!U23+'Premium Segment'!U23+'Closures Overlay'!U23+'Disposals Overlay'!U23 -> -962359.76 | AA23: ='Value Segment'!V23+'Mid-Market Segment'!V23+'Upper Mid-Market Segment'!V23+'Premium Segment'!V23+'Closures Overlay'!V23+'Disposals Overlay'!V23 -> -962359.76 | AB23: ='Value Segment'!W23+'Mid-Market Segment'!W23+'Upper Mid-Market Segment'!W23+'Premium Segment'!W23+'Closures Overlay'!W23+'Disposals Overlay'!W23 -> -936524.6 | AC23: ='Value Segment'!X23+'Mid-Market Segment'!X23+'Upper Mid-Market Segment'!X23+'Premium Segment'!X23+'Closures Overlay'!X23+'Disposals Overlay'!X23 -> -958775.15 | AD23: ='Value Segment'!Y23+'Mid-Market Segment'!Y23+'Upper Mid-Market Segment'!Y23+'Premium Segment'!Y23+'Closures Overlay'!Y23+'Disposals Overlay'!Y23 -> -958775.15 | ... CD23: ='Value Segment'!BY23+'Mid-Market Segment'!BY23+'Upper Mid-Market Segment'!BY23+'Premium Segment'!BY23+'Closures Overlay'!BY23+'Disposals Overlay'!BY23 -> -818706.32
E24: (-) BCF dist & disp | I24: -1899887.8 | J24: -1965046.5 | K24: -1935673.5 | L24: -1961595.2 | N24: ='Value Segment'!I24+'Mid-Market Segment'!I24+'Upper Mid-Market Segment'!I24+'Premium Segment'!I24+'Closures Overlay'!I24+'Disposals Overlay'!I24 -> -2118822.5 | O24: ='Value Segment'!J24+'Mid-Market Segment'!J24+'Upper Mid-Market Segment'!J24+'Premium Segment'!J24+'Closures Overlay'!J24+'Disposals Overlay'!J24 -> -2147501.3 | P24: ='Value Segment'!K24+'Mid-Market Segment'!K24+'Upper Mid-Market Segment'!K24+'Premium Segment'!K24+'Closures Overlay'!K24+'Disposals Overlay'!K24 -> -2112302.4 | Q24: ='Value Segment'!L24+'Mid-Market Segment'!L24+'Upper Mid-Market Segment'!L24+'Premium Segment'!L24+'Closures Overlay'!L24+'Disposals Overlay'!L24 -> -2069577.1 | R24: ='Value Segment'!M24+'Mid-Market Segment'!M24+'Upper Mid-Market Segment'!M24+'Premium Segment'!M24+'Closures Overlay'!M24+'Disposals Overlay'!M24 -> -2020881.9 | S24: ='Value Segment'!N24+'Mid-Market Segment'!N24+'Upper Mid-Market Segment'!N24+'Premium Segment'!N24+'Closures Overlay'!N24+'Disposals Overlay'!N24 -> -1964958.2 | U24: =IFERROR(((S24/N24)^(1/5))-1,0) -> -0.014964796 | W24: ='Value Segment'!R24+'Mid-Market Segment'!R24+'Upper Mid-Market Segment'!R24+'Premium Segment'!R24+'Closures Overlay'!R24+'Disposals Overlay'!R24 -> -180099.91 | X24: ='Value Segment'!S24+'Mid-Market Segment'!S24+'Upper Mid-Market Segment'!S24+'Premium Segment'!S24+'Closures Overlay'!S24+'Disposals Overlay'!S24 -> -180099.91 | Y24: ='Value Segment'!T24+'Mid-Market Segment'!T24+'Upper Mid-Market Segment'!T24+'Premium Segment'!T24+'Closures Overlay'!T24+'Disposals Overlay'!T24 -> -180099.91 | Z24: ='Value Segment'!U24+'Mid-Market Segment'!U24+'Upper Mid-Market Segment'!U24+'Premium Segment'!U24+'Closures Overlay'!U24+'Disposals Overlay'!U24 -> -180099.91 | AA24: ='Value Segment'!V24+'Mid-Market Segment'!V24+'Upper Mid-Market Segment'!V24+'Premium Segment'!V24+'Closures Overlay'!V24+'Disposals Overlay'!V24 -> -180099.91 | AB24: ='Value Segment'!W24+'Mid-Market Segment'!W24+'Upper Mid-Market Segment'!W24+'Premium Segment'!W24+'Closures Overlay'!W24+'Disposals Overlay'!W24 -> -175265.01 | AC24: ='Value Segment'!X24+'Mid-Market Segment'!X24+'Upper Mid-Market Segment'!X24+'Premium Segment'!X24+'Closures Overlay'!X24+'Disposals Overlay'!X24 -> -179447.85 | AD24: ='Value Segment'!Y24+'Mid-Market Segment'!Y24+'Upper Mid-Market Segment'!Y24+'Premium Segment'!Y24+'Closures Overlay'!Y24+'Disposals Overlay'!Y24 -> -179447.85 | ... CD24: ='Value Segment'!BY24+'Mid-Market Segment'!BY24+'Upper Mid-Market Segment'!BY24+'Premium Segment'!BY24+'Closures Overlay'!BY24+'Disposals Overlay'!BY24 -> -159353.26
E25: BCF gross commission | I25: =SUM(I22:I24) -> 19344214 | J25: =SUM(J22:J24) -> 20797277 | K25: =SUM(K22:K24) -> 21130231 | L25: =SUM(L22:L24) -> 21216567 | N25: =SUM(N22:N24) -> 22345014 | O25: =SUM(O22:O24) -> 23383911 | P25: =SUM(P22:P24) -> 23695568 | Q25: =SUM(Q22:Q24) -> 23860616 | R25: =SUM(R22:R24) -> 23885612 | S25: =SUM(S22:S24) -> 23799594 | U25: =IFERROR(((S25/N25)^(1/5))-1,0) -> 0.012692941 | W25: =SUM(W22:W24) -> 1961279.3 | X25: =SUM(X22:X24) -> 1961279.3 | Y25: =SUM(Y22:Y24) -> 1961279.3 | Z25: =SUM(Z22:Z24) -> 1961279.3 | AA25: =SUM(AA22:AA24) -> 1961279.3 | AB25: =SUM(AB22:AB24) -> 1908627.5 | AC25: =SUM(AC22:AC24) -> 1953797.4 | AD25: =SUM(AD22:AD24) -> 1953797.4 | ... CD25: =SUM(CD22:CD24) -> 1929811.3
E26: (-) BCF discounts | I26: -6232414.9 | J26: -6596134.3 | K26: -6790055.1 | L26: -6818644.3 | N26: ='Value Segment'!I26+'Mid-Market Segment'!I26+'Upper Mid-Market Segment'!I26+'Premium Segment'!I26+'Closures Overlay'!I26+'Disposals Overlay'!I26 -> -7260616.2 | O26: ='Value Segment'!J26+'Mid-Market Segment'!J26+'Upper Mid-Market Segment'!J26+'Premium Segment'!J26+'Closures Overlay'!J26+'Disposals Overlay'!J26 -> -7535193.7 | P26: ='Value Segment'!K26+'Mid-Market Segment'!K26+'Upper Mid-Market Segment'!K26+'Premium Segment'!K26+'Closures Overlay'!K26+'Disposals Overlay'!K26 -> -7577291.5 | Q26: ='Value Segment'!L26+'Mid-Market Segment'!L26+'Upper Mid-Market Segment'!L26+'Premium Segment'!L26+'Closures Overlay'!L26+'Disposals Overlay'!L26 -> -7577491.5 | R26: ='Value Segment'!M26+'Mid-Market Segment'!M26+'Upper Mid-Market Segment'!M26+'Premium Segment'!M26+'Closures Overlay'!M26+'Disposals Overlay'!M26 -> -7538516.2 | S26: ='Value Segment'!N26+'Mid-Market Segment'!N26+'Upper Mid-Market Segment'!N26+'Premium Segment'!N26+'Closures Overlay'!N26+'Disposals Overlay'!N26 -> -7466274.9 | U26: =IFERROR(((S26/N26)^(1/5))-1,0) -> 0.0056019318 | W26: ='Value Segment'!R26+'Mid-Market Segment'!R26+'Upper Mid-Market Segment'!R26+'Premium Segment'!R26+'Closures Overlay'!R26+'Disposals Overlay'!R26 -> -632082.89 | X26: ='Value Segment'!S26+'Mid-Market Segment'!S26+'Upper Mid-Market Segment'!S26+'Premium Segment'!S26+'Closures Overlay'!S26+'Disposals Overlay'!S26 -> -632082.89 | Y26: ='Value Segment'!T26+'Mid-Market Segment'!T26+'Upper Mid-Market Segment'!T26+'Premium Segment'!T26+'Closures Overlay'!T26+'Disposals Overlay'!T26 -> -632082.89 | Z26: ='Value Segment'!U26+'Mid-Market Segment'!U26+'Upper Mid-Market Segment'!U26+'Premium Segment'!U26+'Closures Overlay'!U26+'Disposals Overlay'!U26 -> -632082.89 | AA26: ='Value Segment'!V26+'Mid-Market Segment'!V26+'Upper Mid-Market Segment'!V26+'Premium Segment'!V26+'Closures Overlay'!V26+'Disposals Overlay'!V26 -> -632082.89 | AB26: ='Value Segment'!W26+'Mid-Market Segment'!W26+'Upper Mid-Market Segment'!W26+'Premium Segment'!W26+'Closures Overlay'!W26+'Disposals Overlay'!W26 -> -615114.22 | AC26: ='Value Segment'!X26+'Mid-Market Segment'!X26+'Upper Mid-Market Segment'!X26+'Premium Segment'!X26+'Closures Overlay'!X26+'Disposals Overlay'!X26 -> -629505.11 | AD26: ='Value Segment'!Y26+'Mid-Market Segment'!Y26+'Upper Mid-Market Segment'!Y26+'Premium Segment'!Y26+'Closures Overlay'!Y26+'Disposals Overlay'!Y26 -> -629505.11 | ... CD26: ='Value Segment'!BY26+'Mid-Market Segment'!BY26+'Upper Mid-Market Segment'!BY26+'Premium Segment'!BY26+'Closures Overlay'!BY26+'Disposals Overlay'!BY26 -> -605252.08
E27: BCF net commission | I27: =SUM(I25:I26) -> 13111799 | J27: =SUM(J25:J26) -> 14201143 | K27: =SUM(K25:K26) -> 14340176 | L27: =SUM(L25:L26) -> 14397923 | N27: =SUM(N25:N26) -> 15084398 | O27: =SUM(O25:O26) -> 15848717 | P27: =SUM(P25:P26) -> 16118276 | Q27: =SUM(Q25:Q26) -> 16283124 | R27: =SUM(R25:R26) -> 16347096 | S27: =SUM(S25:S26) -> 16333319 | U27: =IFERROR(((S27/N27)^(1/5))-1,0) -> 0.016036461 | W27: =SUM(W25:W26) -> 1329196.4 | X27: =SUM(X25:X26) -> 1329196.4 | Y27: =SUM(Y25:Y26) -> 1329196.4 | Z27: =SUM(Z25:Z26) -> 1329196.4 | AA27: =SUM(AA25:AA26) -> 1329196.4 | AB27: =SUM(AB25:AB26) -> 1293513.3 | AC27: =SUM(AC25:AC26) -> 1324292.3 | AD27: =SUM(AD25:AD26) -> 1324292.3 | ... CD27: =SUM(CD25:CD26) -> 1324559.3
E28: BCF net commission margin (%) | I28: =IFERROR(I27/I22,0) -> 0.40157213 | J28: =IFERROR(J27/J22,0) -> 0.41499845 | K28: =IFERROR(K27/K22,0) -> 0.41878182 | L28: =IFERROR(L27/L22,0) -> 0.42055191 | N28: =IFERROR(N27/N22,0) -> 0.4201913 | O28: =IFERROR(O27/O22,0) -> 0.42827498 | P28: =IFERROR(P27/P22,0) -> 0.43583338 | Q28: =IFERROR(Q27/Q22,0) -> 0.44281626 | R28: =IFERROR(R27/R22,0) -> 0.44921546 | S28: =IFERROR(S27/S22,0) -> 0.45546896 | U28: =IFERROR(((S28/N28)^(1/5))-1,0) -> 0.016254184 | W28: =IFERROR(W27/W22,0) -> 0.42825651 | X28: =IFERROR(X27/X22,0) -> 0.42825651 | Y28: =IFERROR(Y27/Y22,0) -> 0.42825651 | Z28: =IFERROR(Z27/Z22,0) -> 0.42825651 | AA28: =IFERROR(AA27/AA22,0) -> 0.42825651 | AB28: =IFERROR(AB27/AB22,0) -> 0.42825651 | AC28: =IFERROR(AC27/AC22,0) -> 0.42829352 | AD28: =IFERROR(AD27/AD22,0) -> 0.42829352 | ... CD28: =IFERROR(CD27/CD22,0) -> 0.45550828
E30: WSM
E31: WSM gross sales | I31: 3596064 | J31: 3263942.9 | K31: 2898256.4 | L31: 2790126.7 | N31: ='Value Segment'!I31+'Mid-Market Segment'!I31+'Upper Mid-Market Segment'!I31+'Premium Segment'!I31+'Closures Overlay'!I31+'Disposals Overlay'!I31 -> 2979936.8 | O31: ='Value Segment'!J31+'Mid-Market Segment'!J31+'Upper Mid-Market Segment'!J31+'Premium Segment'!J31+'Closures Overlay'!J31+'Disposals Overlay'!J31 -> 2960751.7 | P31: ='Value Segment'!K31+'Mid-Market Segment'!K31+'Upper Mid-Market Segment'!K31+'Premium Segment'!K31+'Closures Overlay'!K31+'Disposals Overlay'!K31 -> 2854671.9 | Q31: ='Value Segment'!L31+'Mid-Market Segment'!L31+'Upper Mid-Market Segment'!L31+'Premium Segment'!L31+'Closures Overlay'!L31+'Disposals Overlay'!L31 -> 2741685.6 | R31: ='Value Segment'!M31+'Mid-Market Segment'!M31+'Upper Mid-Market Segment'!M31+'Premium Segment'!M31+'Closures Overlay'!M31+'Disposals Overlay'!M31 -> 2624261.9 | S31: ='Value Segment'!N31+'Mid-Market Segment'!N31+'Upper Mid-Market Segment'!N31+'Premium Segment'!N31+'Closures Overlay'!N31+'Disposals Overlay'!N31 -> 2501172.4 | U31: =IFERROR(((S31/N31)^(1/5))-1,0) -> -0.034422107 | W31: ='Value Segment'!R31+'Mid-Market Segment'!R31+'Upper Mid-Market Segment'!R31+'Premium Segment'!R31+'Closures Overlay'!R31+'Disposals Overlay'!R31 -> 248328.07 | X31: ='Value Segment'!S31+'Mid-Market Segment'!S31+'Upper Mid-Market Segment'!S31+'Premium Segment'!S31+'Closures Overlay'!S31+'Disposals Overlay'!S31 -> 248328.07 | Y31: ='Value Segment'!T31+'Mid-Market Segment'!T31+'Upper Mid-Market Segment'!T31+'Premium Segment'!T31+'Closures Overlay'!T31+'Disposals Overlay'!T31 -> 248328.07 | Z31: ='Value Segment'!U31+'Mid-Market Segment'!U31+'Upper Mid-Market Segment'!U31+'Premium Segment'!U31+'Closures Overlay'!U31+'Disposals Overlay'!U31 -> 248328.07 | AA31: ='Value Segment'!V31+'Mid-Market Segment'!V31+'Upper Mid-Market Segment'!V31+'Premium Segment'!V31+'Closures Overlay'!V31+'Disposals Overlay'!V31 -> 248328.07 | AB31: ='Value Segment'!W31+'Mid-Market Segment'!W31+'Upper Mid-Market Segment'!W31+'Premium Segment'!W31+'Closures Overlay'!W31+'Disposals Overlay'!W31 -> 241661.54 | AC31: ='Value Segment'!X31+'Mid-Market Segment'!X31+'Upper Mid-Market Segment'!X31+'Premium Segment'!X31+'Closures Overlay'!X31+'Disposals Overlay'!X31 -> 247379.01 | AD31: ='Value Segment'!Y31+'Mid-Market Segment'!Y31+'Upper Mid-Market Segment'!Y31+'Premium Segment'!Y31+'Closures Overlay'!Y31+'Disposals Overlay'!Y31 -> 247379.01 | ... CD31: ='Value Segment'!BY31+'Mid-Market Segment'!BY31+'Upper Mid-Market Segment'!BY31+'Premium Segment'!BY31+'Closures Overlay'!BY31+'Disposals Overlay'!BY31 -> 202803.2
E32: (-) WSM cost of sales | I32: -2121269.5 | J32: -1855087.6 | K32: -1538048.1 | L32: -1456084.6 | N32: ='Value Segment'!I32+'Mid-Market Segment'!I32+'Upper Mid-Market Segment'!I32+'Premium Segment'!I32+'Closures Overlay'!I32+'Disposals Overlay'!I32 -> -1506679.3 | O32: ='Value Segment'!J32+'Mid-Market Segment'!J32+'Upper Mid-Market Segment'!J32+'Premium Segment'!J32+'Closures Overlay'!J32+'Disposals Overlay'!J32 -> -1496990.1 | P32: ='Value Segment'!K32+'Mid-Market Segment'!K32+'Upper Mid-Market Segment'!K32+'Premium Segment'!K32+'Closures Overlay'!K32+'Disposals Overlay'!K32 -> -1443370.4 | Q32: ='Value Segment'!L32+'Mid-Market Segment'!L32+'Upper Mid-Market Segment'!L32+'Premium Segment'!L32+'Closures Overlay'!L32+'Disposals Overlay'!L32 -> -1386256.8 | R32: ='Value Segment'!M32+'Mid-Market Segment'!M32+'Upper Mid-Market Segment'!M32+'Premium Segment'!M32+'Closures Overlay'!M32+'Disposals Overlay'!M32 -> -1326900.3 | S32: ='Value Segment'!N32+'Mid-Market Segment'!N32+'Upper Mid-Market Segment'!N32+'Premium Segment'!N32+'Closures Overlay'!N32+'Disposals Overlay'!N32 -> -1264679.3 | U32: =IFERROR(((S32/N32)^(1/5))-1,0) -> -0.034411874 | W32: ='Value Segment'!R32+'Mid-Market Segment'!R32+'Upper Mid-Market Segment'!R32+'Premium Segment'!R32+'Closures Overlay'!R32+'Disposals Overlay'!R32 -> -125556.61 | X32: ='Value Segment'!S32+'Mid-Market Segment'!S32+'Upper Mid-Market Segment'!S32+'Premium Segment'!S32+'Closures Overlay'!S32+'Disposals Overlay'!S32 -> -125556.61 | Y32: ='Value Segment'!T32+'Mid-Market Segment'!T32+'Upper Mid-Market Segment'!T32+'Premium Segment'!T32+'Closures Overlay'!T32+'Disposals Overlay'!T32 -> -125556.61 | Z32: ='Value Segment'!U32+'Mid-Market Segment'!U32+'Upper Mid-Market Segment'!U32+'Premium Segment'!U32+'Closures Overlay'!U32+'Disposals Overlay'!U32 -> -125556.61 | AA32: ='Value Segment'!V32+'Mid-Market Segment'!V32+'Upper Mid-Market Segment'!V32+'Premium Segment'!V32+'Closures Overlay'!V32+'Disposals Overlay'!V32 -> -125556.61 | AB32: ='Value Segment'!W32+'Mid-Market Segment'!W32+'Upper Mid-Market Segment'!W32+'Premium Segment'!W32+'Closures Overlay'!W32+'Disposals Overlay'!W32 -> -122185.96 | AC32: ='Value Segment'!X32+'Mid-Market Segment'!X32+'Upper Mid-Market Segment'!X32+'Premium Segment'!X32+'Closures Overlay'!X32+'Disposals Overlay'!X32 -> -125078.59 | AD32: ='Value Segment'!Y32+'Mid-Market Segment'!Y32+'Upper Mid-Market Segment'!Y32+'Premium Segment'!Y32+'Closures Overlay'!Y32+'Disposals Overlay'!Y32 -> -125078.59 | ... CD32: ='Value Segment'!BY32+'Mid-Market Segment'!BY32+'Upper Mid-Market Segment'!BY32+'Premium Segment'!BY32+'Closures Overlay'!BY32+'Disposals Overlay'!BY32 -> -102545.92
E33: (-) WSM dist & disp | I33: -340817.06 | J33: -257862.19 | K33: -195403.29 | L33: -187672.47 | N33: ='Value Segment'!I33+'Mid-Market Segment'!I33+'Upper Mid-Market Segment'!I33+'Premium Segment'!I33+'Closures Overlay'!I33+'Disposals Overlay'!I33 -> -193747.62 | O33: ='Value Segment'!J33+'Mid-Market Segment'!J33+'Upper Mid-Market Segment'!J33+'Premium Segment'!J33+'Closures Overlay'!J33+'Disposals Overlay'!J33 -> -192516.7 | P33: ='Value Segment'!K33+'Mid-Market Segment'!K33+'Upper Mid-Market Segment'!K33+'Premium Segment'!K33+'Closures Overlay'!K33+'Disposals Overlay'!K33 -> -185645.4 | Q33: ='Value Segment'!L33+'Mid-Market Segment'!L33+'Upper Mid-Market Segment'!L33+'Premium Segment'!L33+'Closures Overlay'!L33+'Disposals Overlay'!L33 -> -178321.8 | R33: ='Value Segment'!M33+'Mid-Market Segment'!M33+'Upper Mid-Market Segment'!M33+'Premium Segment'!M33+'Closures Overlay'!M33+'Disposals Overlay'!M33 -> -170708.92 | S33: ='Value Segment'!N33+'Mid-Market Segment'!N33+'Upper Mid-Market Segment'!N33+'Premium Segment'!N33+'Closures Overlay'!N33+'Disposals Overlay'!N33 -> -162726.55 | U33: =IFERROR(((S33/N33)^(1/5))-1,0) -> -0.03429516 | W33: ='Value Segment'!R33+'Mid-Market Segment'!R33+'Upper Mid-Market Segment'!R33+'Premium Segment'!R33+'Closures Overlay'!R33+'Disposals Overlay'!R33 -> -16145.635 | X33: ='Value Segment'!S33+'Mid-Market Segment'!S33+'Upper Mid-Market Segment'!S33+'Premium Segment'!S33+'Closures Overlay'!S33+'Disposals Overlay'!S33 -> -16145.635 | Y33: ='Value Segment'!T33+'Mid-Market Segment'!T33+'Upper Mid-Market Segment'!T33+'Premium Segment'!T33+'Closures Overlay'!T33+'Disposals Overlay'!T33 -> -16145.635 | Z33: ='Value Segment'!U33+'Mid-Market Segment'!U33+'Upper Mid-Market Segment'!U33+'Premium Segment'!U33+'Closures Overlay'!U33+'Disposals Overlay'!U33 -> -16145.635 | AA33: ='Value Segment'!V33+'Mid-Market Segment'!V33+'Upper Mid-Market Segment'!V33+'Premium Segment'!V33+'Closures Overlay'!V33+'Disposals Overlay'!V33 -> -16145.635 | AB33: ='Value Segment'!W33+'Mid-Market Segment'!W33+'Upper Mid-Market Segment'!W33+'Premium Segment'!W33+'Closures Overlay'!W33+'Disposals Overlay'!W33 -> -15712.195 | AC33: ='Value Segment'!X33+'Mid-Market Segment'!X33+'Upper Mid-Market Segment'!X33+'Premium Segment'!X33+'Closures Overlay'!X33+'Disposals Overlay'!X33 -> -16086.683 | AD33: ='Value Segment'!Y33+'Mid-Market Segment'!Y33+'Upper Mid-Market Segment'!Y33+'Premium Segment'!Y33+'Closures Overlay'!Y33+'Disposals Overlay'!Y33 -> -16086.683 | ... CD33: ='Value Segment'!BY33+'Mid-Market Segment'!BY33+'Upper Mid-Market Segment'!BY33+'Premium Segment'!BY33+'Closures Overlay'!BY33+'Disposals Overlay'!BY33 -> -13196.191
E34: WSM gross commission | I34: =SUM(I31:I33) -> 1133977.5 | J34: =SUM(J31:J33) -> 1150993.1 | K34: =SUM(K31:K33) -> 1164805 | L34: =SUM(L31:L33) -> 1146369.7 | N34: =SUM(N31:N33) -> 1279509.9 | O34: =SUM(O31:O33) -> 1271244.9 | P34: =SUM(P31:P33) -> 1225656 | Q34: =SUM(Q31:Q33) -> 1177107 | R34: =SUM(R31:R33) -> 1126652.7 | S34: =SUM(S31:S33) -> 1073766.6 | U34: =IFERROR(((S34/N34)^(1/5))-1,0) -> -0.034453386 | W34: =SUM(W31:W33) -> 106625.82 | X34: =SUM(X31:X33) -> 106625.82 | Y34: =SUM(Y31:Y33) -> 106625.82 | Z34: =SUM(Z31:Z33) -> 106625.82 | AA34: =SUM(AA31:AA33) -> 106625.82 | AB34: =SUM(AB31:AB33) -> 103763.39 | AC34: =SUM(AC31:AC33) -> 106213.74 | AD34: =SUM(AD31:AD33) -> 106213.74 | ... CD34: =SUM(CD31:CD33) -> 87061.094
E35: (-) WSM discounts | I35: -276130.83 | J35: -166105.28 | K35: -147070.19 | L35: -140380.92 | N35: ='Value Segment'!I35+'Mid-Market Segment'!I35+'Upper Mid-Market Segment'!I35+'Premium Segment'!I35+'Closures Overlay'!I35+'Disposals Overlay'!I35 -> -143581.34 | O35: ='Value Segment'!J35+'Mid-Market Segment'!J35+'Upper Mid-Market Segment'!J35+'Premium Segment'!J35+'Closures Overlay'!J35+'Disposals Overlay'!J35 -> -142631.94 | P35: ='Value Segment'!K35+'Mid-Market Segment'!K35+'Upper Mid-Market Segment'!K35+'Premium Segment'!K35+'Closures Overlay'!K35+'Disposals Overlay'!K35 -> -137489.64 | Q35: ='Value Segment'!L35+'Mid-Market Segment'!L35+'Upper Mid-Market Segment'!L35+'Premium Segment'!L35+'Closures Overlay'!L35+'Disposals Overlay'!L35 -> -132018.3 | R35: ='Value Segment'!M35+'Mid-Market Segment'!M35+'Upper Mid-Market Segment'!M35+'Premium Segment'!M35+'Closures Overlay'!M35+'Disposals Overlay'!M35 -> -126329.47 | S35: ='Value Segment'!N35+'Mid-Market Segment'!N35+'Upper Mid-Market Segment'!N35+'Premium Segment'!N35+'Closures Overlay'!N35+'Disposals Overlay'!N35 -> -120365.32 | U35: =IFERROR(((S35/N35)^(1/5))-1,0) -> -0.034659171 | W35: ='Value Segment'!R35+'Mid-Market Segment'!R35+'Upper Mid-Market Segment'!R35+'Premium Segment'!R35+'Closures Overlay'!R35+'Disposals Overlay'!R35 -> -11965.112 | X35: ='Value Segment'!S35+'Mid-Market Segment'!S35+'Upper Mid-Market Segment'!S35+'Premium Segment'!S35+'Closures Overlay'!S35+'Disposals Overlay'!S35 -> -11965.112 | Y35: ='Value Segment'!T35+'Mid-Market Segment'!T35+'Upper Mid-Market Segment'!T35+'Premium Segment'!T35+'Closures Overlay'!T35+'Disposals Overlay'!T35 -> -11965.112 | Z35: ='Value Segment'!U35+'Mid-Market Segment'!U35+'Upper Mid-Market Segment'!U35+'Premium Segment'!U35+'Closures Overlay'!U35+'Disposals Overlay'!U35 -> -11965.112 | AA35: ='Value Segment'!V35+'Mid-Market Segment'!V35+'Upper Mid-Market Segment'!V35+'Premium Segment'!V35+'Closures Overlay'!V35+'Disposals Overlay'!V35 -> -11965.112 | AB35: ='Value Segment'!W35+'Mid-Market Segment'!W35+'Upper Mid-Market Segment'!W35+'Premium Segment'!W35+'Closures Overlay'!W35+'Disposals Overlay'!W35 -> -11643.901 | AC35: ='Value Segment'!X35+'Mid-Market Segment'!X35+'Upper Mid-Market Segment'!X35+'Premium Segment'!X35+'Closures Overlay'!X35+'Disposals Overlay'!X35 -> -11915.196 | AD35: ='Value Segment'!Y35+'Mid-Market Segment'!Y35+'Upper Mid-Market Segment'!Y35+'Premium Segment'!Y35+'Closures Overlay'!Y35+'Disposals Overlay'!Y35 -> -11915.196 | ... CD35: ='Value Segment'!BY35+'Mid-Market Segment'!BY35+'Upper Mid-Market Segment'!BY35+'Premium Segment'!BY35+'Closures Overlay'!BY35+'Disposals Overlay'!BY35 -> -9755.0971
E36: WSM net commission | I36: =SUM(I34:I35) -> 857846.64 | J36: =SUM(J34:J35) -> 984887.84 | K36: =SUM(K34:K35) -> 1017734.8 | L36: =SUM(L34:L35) -> 1005988.8 | N36: =SUM(N34:N35) -> 1135928.5 | O36: =SUM(O34:O35) -> 1128612.9 | P36: =SUM(P34:P35) -> 1088166.4 | Q36: =SUM(Q34:Q35) -> 1045088.7 | R36: =SUM(R34:R35) -> 1000323.3 | S36: =SUM(S34:S35) -> 953401.23 | U36: =IFERROR(((S36/N36)^(1/5))-1,0) -> -0.034427387 | W36: =SUM(W34:W35) -> 94660.712 | X36: =SUM(X34:X35) -> 94660.712 | Y36: =SUM(Y34:Y35) -> 94660.712 | Z36: =SUM(Z34:Z35) -> 94660.712 | AA36: =SUM(AA34:AA35) -> 94660.712 | AB36: =SUM(AB34:AB35) -> 92119.485 | AC36: =SUM(AC34:AC35) -> 94298.54 | AD36: =SUM(AD34:AD35) -> 94298.54 | ... CD36: =SUM(CD34:CD35) -> 77305.997
E37: WSM net commission margin (%) | I37: =IFERROR(I36/I31,0) -> 0.23855155 | J37: =IFERROR(J36/J31,0) -> 0.30174788 | K37: =IFERROR(K36/K31,0) -> 0.35115416 | L37: =IFERROR(L36/L31,0) -> 0.36055307 | N37: =IFERROR(N36/N31,0) -> 0.38119216 | O37: =IFERROR(O36/O31,0) -> 0.38119135 | P37: =IFERROR(P36/P31,0) -> 0.38118791 | Q37: =IFERROR(Q36/Q31,0) -> 0.38118473 | R37: =IFERROR(R36/R31,0) -> 0.38118271 | S37: =IFERROR(S36/S31,0) -> 0.38118174 | U37: =IFERROR(((S37/N37)^(1/5))-1,0) -> -5.4685164e-06 | W37: =IFERROR(W36/W31,0) -> 0.38119216 | X37: =IFERROR(X36/X31,0) -> 0.38119216 | Y37: =IFERROR(Y36/Y31,0) -> 0.38119216 | Z37: =IFERROR(Z36/Z31,0) -> 0.38119216 | AA37: =IFERROR(AA36/AA31,0) -> 0.38119216 | AB37: =IFERROR(AB36/AB31,0) -> 0.38119216 | AC37: =IFERROR(AC36/AC31,0) -> 0.38119054 | AD37: =IFERROR(AD36/AD31,0) -> 0.38119054 | ... CD37: =IFERROR(CD36/CD31,0) -> 0.38118725
E39: Drinks gross profit (BCF + WSM) | I39: =SUM(I27,I36) -> 13969646 | J39: =SUM(J27,J36) -> 15186031 | K39: =SUM(K27,K36) -> 15357911 | L39: =SUM(L27,L36) -> 15403912 | N39: =SUM(N27,N36) -> 16220326 | O39: =SUM(O27,O36) -> 16977330 | P39: =SUM(P27,P36) -> 17206443 | Q39: =SUM(Q27,Q36) -> 17328213 | R39: =SUM(R27,R36) -> 17347419 | S39: =SUM(S27,S36) -> 17286720 | U39: =IFERROR(((S39/N39)^(1/5))-1,0) -> 0.012816115 | W39: =SUM(W27,W36) -> 1423857.2 | X39: =SUM(X27,X36) -> 1423857.2 | Y39: =SUM(Y27,Y36) -> 1423857.2 | Z39: =SUM(Z27,Z36) -> 1423857.2 | AA39: =SUM(AA27,AA36) -> 1423857.2 | AB39: =SUM(AB27,AB36) -> 1385632.8 | AC39: =SUM(AC27,AC36) -> 1418590.9 | AD39: =SUM(AD27,AD36) -> 1418590.9 | ... CD39: =SUM(CD27,CD36) -> 1401865.3
E40: Drinks gross profit margin (%) | I40: =IFERROR(I39/(I22+I31),0) -> 0.38539897 | J40: =IFERROR(J39/(J22+J31),0) -> 0.40513701 | K40: =IFERROR(K39/(K22+K31),0) -> 0.41350455 | L40: =IFERROR(L39/(L22+L31),0) -> 0.41603063 | N40: =IFERROR(N39/(N22+N31),0) -> 0.41720214 | O40: =IFERROR(O39/(O22+O31),0) -> 0.424787 | P40: =IFERROR(P39/(P22+P31),0) -> 0.43191758 | Q40: =IFERROR(Q39/(Q22+Q31),0) -> 0.43853989 | R40: =IFERROR(R39/(R22+R31),0) -> 0.44463934 | S40: =IFERROR(S39/(S22+S31),0) -> 0.45062545 | U40: =IFERROR(((S40/N40)^(1/5))-1,0) -> 0.015532524 | W40: =IFERROR(W39/(W22+W31),0) -> 0.42476989 | X40: =IFERROR(X39/(X22+X31),0) -> 0.42476989 | Y40: =IFERROR(Y39/(Y22+Y31),0) -> 0.42476989 | Z40: =IFERROR(Z39/(Z22+Z31),0) -> 0.42476989 | AA40: =IFERROR(AA39/(AA22+AA31),0) -> 0.42476989 | AB40: =IFERROR(AB39/(AB22+AB31),0) -> 0.42476989 | AC40: =IFERROR(AC39/(AC22+AC31),0) -> 0.42480419 | AD40: =IFERROR(AD39/(AD22+AD31),0) -> 0.42480419 | ... CD40: =IFERROR(CD39/(CD22+CD31),0) -> 0.45066285
E42: Rental income
E43: Rental income | I43: 9810077 | J43: 10009705 | K43: 10001615 | L43: 9989507.3 | N43: ='Value Segment'!I43+'Mid-Market Segment'!I43+'Upper Mid-Market Segment'!I43+'Premium Segment'!I43+'Closures Overlay'!I43+'Disposals Overlay'!I43 -> 10004063 | O43: ='Value Segment'!J43+'Mid-Market Segment'!J43+'Upper Mid-Market Segment'!J43+'Premium Segment'!J43+'Closures Overlay'!J43+'Disposals Overlay'!J43 -> 10278597 | P43: ='Value Segment'!K43+'Mid-Market Segment'!K43+'Upper Mid-Market Segment'!K43+'Premium Segment'!K43+'Closures Overlay'!K43+'Disposals Overlay'!K43 -> 10269103 | Q43: ='Value Segment'!L43+'Mid-Market Segment'!L43+'Upper Mid-Market Segment'!L43+'Premium Segment'!L43+'Closures Overlay'!L43+'Disposals Overlay'!L43 -> 10211383 | R43: ='Value Segment'!M43+'Mid-Market Segment'!M43+'Upper Mid-Market Segment'!M43+'Premium Segment'!M43+'Closures Overlay'!M43+'Disposals Overlay'!M43 -> 10092967 | S43: ='Value Segment'!N43+'Mid-Market Segment'!N43+'Upper Mid-Market Segment'!N43+'Premium Segment'!N43+'Closures Overlay'!N43+'Disposals Overlay'!N43 -> 9924582.9 | U43: =IFERROR(((S43/N43)^(1/5))-1,0) -> -0.0015940342 | W43: ='Value Segment'!R43+'Mid-Market Segment'!R43+'Upper Mid-Market Segment'!R43+'Premium Segment'!R43+'Closures Overlay'!R43+'Disposals Overlay'!R43 -> 858493.41 | X43: ='Value Segment'!S43+'Mid-Market Segment'!S43+'Upper Mid-Market Segment'!S43+'Premium Segment'!S43+'Closures Overlay'!S43+'Disposals Overlay'!S43 -> 858493.41 | Y43: ='Value Segment'!T43+'Mid-Market Segment'!T43+'Upper Mid-Market Segment'!T43+'Premium Segment'!T43+'Closures Overlay'!T43+'Disposals Overlay'!T43 -> 858493.41 | Z43: ='Value Segment'!U43+'Mid-Market Segment'!U43+'Upper Mid-Market Segment'!U43+'Premium Segment'!U43+'Closures Overlay'!U43+'Disposals Overlay'!U43 -> 858493.41 | AA43: ='Value Segment'!V43+'Mid-Market Segment'!V43+'Upper Mid-Market Segment'!V43+'Premium Segment'!V43+'Closures Overlay'!V43+'Disposals Overlay'!V43 -> 858493.41 | AB43: ='Value Segment'!W43+'Mid-Market Segment'!W43+'Upper Mid-Market Segment'!W43+'Premium Segment'!W43+'Closures Overlay'!W43+'Disposals Overlay'!W43 -> 835446.61 | AC43: ='Value Segment'!X43+'Mid-Market Segment'!X43+'Upper Mid-Market Segment'!X43+'Premium Segment'!X43+'Closures Overlay'!X43+'Disposals Overlay'!X43 -> 862412.3 | AD43: ='Value Segment'!Y43+'Mid-Market Segment'!Y43+'Upper Mid-Market Segment'!Y43+'Premium Segment'!Y43+'Closures Overlay'!Y43+'Disposals Overlay'!Y43 -> 862412.3 | ... CD43: ='Value Segment'!BY43+'Mid-Market Segment'!BY43+'Upper Mid-Market Segment'!BY43+'Premium Segment'!BY43+'Closures Overlay'!BY43+'Disposals Overlay'!BY43 -> 811790
E44: Tie Release Fees | I44: 830152.58 | J44: 936509.88 | K44: 1077382.9 | L44: 1184090.4 | N44: ='Value Segment'!I44+'Mid-Market Segment'!I44+'Upper Mid-Market Segment'!I44+'Premium Segment'!I44+'Closures Overlay'!I44+'Disposals Overlay'!I44 -> 1310139.6 | O44: ='Value Segment'!J44+'Mid-Market Segment'!J44+'Upper Mid-Market Segment'!J44+'Premium Segment'!J44+'Closures Overlay'!J44+'Disposals Overlay'!J44 -> 1331889.7 | P44: ='Value Segment'!K44+'Mid-Market Segment'!K44+'Upper Mid-Market Segment'!K44+'Premium Segment'!K44+'Closures Overlay'!K44+'Disposals Overlay'!K44 -> 1300873.9 | Q44: ='Value Segment'!L44+'Mid-Market Segment'!L44+'Upper Mid-Market Segment'!L44+'Premium Segment'!L44+'Closures Overlay'!L44+'Disposals Overlay'!L44 -> 1264678.8 | R44: ='Value Segment'!M44+'Mid-Market Segment'!M44+'Upper Mid-Market Segment'!M44+'Premium Segment'!M44+'Closures Overlay'!M44+'Disposals Overlay'!M44 -> 1217641.3 | S44: ='Value Segment'!N44+'Mid-Market Segment'!N44+'Upper Mid-Market Segment'!N44+'Premium Segment'!N44+'Closures Overlay'!N44+'Disposals Overlay'!N44 -> 1162620.8 | U44: =IFERROR(((S44/N44)^(1/5))-1,0) -> -0.02360824 | W44: ='Value Segment'!R44+'Mid-Market Segment'!R44+'Upper Mid-Market Segment'!R44+'Premium Segment'!R44+'Closures Overlay'!R44+'Disposals Overlay'!R44 -> 113013.42 | X44: ='Value Segment'!S44+'Mid-Market Segment'!S44+'Upper Mid-Market Segment'!S44+'Premium Segment'!S44+'Closures Overlay'!S44+'Disposals Overlay'!S44 -> 113013.42 | Y44: ='Value Segment'!T44+'Mid-Market Segment'!T44+'Upper Mid-Market Segment'!T44+'Premium Segment'!T44+'Closures Overlay'!T44+'Disposals Overlay'!T44 -> 113013.42 | Z44: ='Value Segment'!U44+'Mid-Market Segment'!U44+'Upper Mid-Market Segment'!U44+'Premium Segment'!U44+'Closures Overlay'!U44+'Disposals Overlay'!U44 -> 113013.42 | AA44: ='Value Segment'!V44+'Mid-Market Segment'!V44+'Upper Mid-Market Segment'!V44+'Premium Segment'!V44+'Closures Overlay'!V44+'Disposals Overlay'!V44 -> 113013.42 | AB44: ='Value Segment'!W44+'Mid-Market Segment'!W44+'Upper Mid-Market Segment'!W44+'Premium Segment'!W44+'Closures Overlay'!W44+'Disposals Overlay'!W44 -> 109979.5 | AC44: ='Value Segment'!X44+'Mid-Market Segment'!X44+'Upper Mid-Market Segment'!X44+'Premium Segment'!X44+'Closures Overlay'!X44+'Disposals Overlay'!X44 -> 109979.5 | AD44: ='Value Segment'!Y44+'Mid-Market Segment'!Y44+'Upper Mid-Market Segment'!Y44+'Premium Segment'!Y44+'Closures Overlay'!Y44+'Disposals Overlay'!Y44 -> 109979.5 | ... CD44: ='Value Segment'!BY44+'Mid-Market Segment'!BY44+'Upper Mid-Market Segment'!BY44+'Premium Segment'!BY44+'Closures Overlay'!BY44+'Disposals Overlay'!BY44 -> 92365.647
E45: Total rental income | I45: =SUM(I43:I44) -> 10640230 | J45: =SUM(J43:J44) -> 10946214 | K45: =SUM(K43:K44) -> 11078998 | L45: =SUM(L43:L44) -> 11173598 | N45: =SUM(N43:N44) -> 11314203 | O45: =SUM(O43:O44) -> 11610486 | P45: =SUM(P43:P44) -> 11569977 | Q45: =SUM(Q43:Q44) -> 11476062 | R45: =SUM(R43:R44) -> 11310608 | S45: =SUM(S43:S44) -> 11087204 | U45: =IFERROR(((S45/N45)^(1/5))-1,0) -> -0.0040452348 | W45: =SUM(W43:W44) -> 971506.83 | X45: =SUM(X43:X44) -> 971506.83 | Y45: =SUM(Y43:Y44) -> 971506.83 | Z45: =SUM(Z43:Z44) -> 971506.83 | AA45: =SUM(AA43:AA44) -> 971506.83 | AB45: =SUM(AB43:AB44) -> 945426.11 | AC45: =SUM(AC43:AC44) -> 972391.8 | AD45: =SUM(AD43:AD44) -> 972391.8 | ... CD45: =SUM(CD43:CD44) -> 904155.64
E47: Ancillary income
E48: Other income | I48: 62024.12 | J48: 40176.54 | K48: 49017.16 | L48: 72800.27 | N48: ='Value Segment'!I48+'Mid-Market Segment'!I48+'Upper Mid-Market Segment'!I48+'Premium Segment'!I48+'Closures Overlay'!I48+'Disposals Overlay'!I48 -> 21546.919 | O48: ='Value Segment'!J48+'Mid-Market Segment'!J48+'Upper Mid-Market Segment'!J48+'Premium Segment'!J48+'Closures Overlay'!J48+'Disposals Overlay'!J48 -> 21161.292 | P48: ='Value Segment'!K48+'Mid-Market Segment'!K48+'Upper Mid-Market Segment'!K48+'Premium Segment'!K48+'Closures Overlay'!K48+'Disposals Overlay'!K48 -> 20004.41 | Q48: ='Value Segment'!L48+'Mid-Market Segment'!L48+'Upper Mid-Market Segment'!L48+'Premium Segment'!L48+'Closures Overlay'!L48+'Disposals Overlay'!L48 -> 18847.529 | R48: ='Value Segment'!M48+'Mid-Market Segment'!M48+'Upper Mid-Market Segment'!M48+'Premium Segment'!M48+'Closures Overlay'!M48+'Disposals Overlay'!M48 -> 17690.647 | S48: ='Value Segment'!N48+'Mid-Market Segment'!N48+'Upper Mid-Market Segment'!N48+'Premium Segment'!N48+'Closures Overlay'!N48+'Disposals Overlay'!N48 -> 16533.766 | U48: =IFERROR(((S48/N48)^(1/5))-1,0) -> -0.051587391 | W48: ='Value Segment'!R48+'Mid-Market Segment'!R48+'Upper Mid-Market Segment'!R48+'Premium Segment'!R48+'Closures Overlay'!R48+'Disposals Overlay'!R48 -> 1795.5766 | X48: ='Value Segment'!S48+'Mid-Market Segment'!S48+'Upper Mid-Market Segment'!S48+'Premium Segment'!S48+'Closures Overlay'!S48+'Disposals Overlay'!S48 -> 1795.5766 | Y48: ='Value Segment'!T48+'Mid-Market Segment'!T48+'Upper Mid-Market Segment'!T48+'Premium Segment'!T48+'Closures Overlay'!T48+'Disposals Overlay'!T48 -> 1795.5766 | Z48: ='Value Segment'!U48+'Mid-Market Segment'!U48+'Upper Mid-Market Segment'!U48+'Premium Segment'!U48+'Closures Overlay'!U48+'Disposals Overlay'!U48 -> 1795.5766 | AA48: ='Value Segment'!V48+'Mid-Market Segment'!V48+'Upper Mid-Market Segment'!V48+'Premium Segment'!V48+'Closures Overlay'!V48+'Disposals Overlay'!V48 -> 1795.5766 | AB48: ='Value Segment'!W48+'Mid-Market Segment'!W48+'Upper Mid-Market Segment'!W48+'Premium Segment'!W48+'Closures Overlay'!W48+'Disposals Overlay'!W48 -> 1747.3732 | AC48: ='Value Segment'!X48+'Mid-Market Segment'!X48+'Upper Mid-Market Segment'!X48+'Premium Segment'!X48+'Closures Overlay'!X48+'Disposals Overlay'!X48 -> 1747.3732 | AD48: ='Value Segment'!Y48+'Mid-Market Segment'!Y48+'Upper Mid-Market Segment'!Y48+'Premium Segment'!Y48+'Closures Overlay'!Y48+'Disposals Overlay'!Y48 -> 1747.3732 | ... CD48: ='Value Segment'!BY48+'Mid-Market Segment'!BY48+'Upper Mid-Market Segment'!BY48+'Premium Segment'!BY48+'Closures Overlay'!BY48+'Disposals Overlay'!BY48 -> 1313.5426
E49: Machines income | I49: 654114.38 | J49: 622555.27 | K49: 609523.56 | L49: 612611.25 | N49: ='Value Segment'!I49+'Mid-Market Segment'!I49+'Upper Mid-Market Segment'!I49+'Premium Segment'!I49+'Closures Overlay'!I49+'Disposals Overlay'!I49 -> 621515.62 | O49: ='Value Segment'!J49+'Mid-Market Segment'!J49+'Upper Mid-Market Segment'!J49+'Premium Segment'!J49+'Closures Overlay'!J49+'Disposals Overlay'!J49 -> 610392.3 | P49: ='Value Segment'!K49+'Mid-Market Segment'!K49+'Upper Mid-Market Segment'!K49+'Premium Segment'!K49+'Closures Overlay'!K49+'Disposals Overlay'!K49 -> 577022.34 | Q49: ='Value Segment'!L49+'Mid-Market Segment'!L49+'Upper Mid-Market Segment'!L49+'Premium Segment'!L49+'Closures Overlay'!L49+'Disposals Overlay'!L49 -> 543652.37 | R49: ='Value Segment'!M49+'Mid-Market Segment'!M49+'Upper Mid-Market Segment'!M49+'Premium Segment'!M49+'Closures Overlay'!M49+'Disposals Overlay'!M49 -> 510282.4 | S49: ='Value Segment'!N49+'Mid-Market Segment'!N49+'Upper Mid-Market Segment'!N49+'Premium Segment'!N49+'Closures Overlay'!N49+'Disposals Overlay'!N49 -> 476912.44 | U49: =IFERROR(((S49/N49)^(1/5))-1,0) -> -0.051587391 | W49: ='Value Segment'!R49+'Mid-Market Segment'!R49+'Upper Mid-Market Segment'!R49+'Premium Segment'!R49+'Closures Overlay'!R49+'Disposals Overlay'!R49 -> 51792.969 | X49: ='Value Segment'!S49+'Mid-Market Segment'!S49+'Upper Mid-Market Segment'!S49+'Premium Segment'!S49+'Closures Overlay'!S49+'Disposals Overlay'!S49 -> 51792.969 | Y49: ='Value Segment'!T49+'Mid-Market Segment'!T49+'Upper Mid-Market Segment'!T49+'Premium Segment'!T49+'Closures Overlay'!T49+'Disposals Overlay'!T49 -> 51792.969 | Z49: ='Value Segment'!U49+'Mid-Market Segment'!U49+'Upper Mid-Market Segment'!U49+'Premium Segment'!U49+'Closures Overlay'!U49+'Disposals Overlay'!U49 -> 51792.969 | AA49: ='Value Segment'!V49+'Mid-Market Segment'!V49+'Upper Mid-Market Segment'!V49+'Premium Segment'!V49+'Closures Overlay'!V49+'Disposals Overlay'!V49 -> 51792.969 | AB49: ='Value Segment'!W49+'Mid-Market Segment'!W49+'Upper Mid-Market Segment'!W49+'Premium Segment'!W49+'Closures Overlay'!W49+'Disposals Overlay'!W49 -> 50402.553 | AC49: ='Value Segment'!X49+'Mid-Market Segment'!X49+'Upper Mid-Market Segment'!X49+'Premium Segment'!X49+'Closures Overlay'!X49+'Disposals Overlay'!X49 -> 50402.553 | AD49: ='Value Segment'!Y49+'Mid-Market Segment'!Y49+'Upper Mid-Market Segment'!Y49+'Premium Segment'!Y49+'Closures Overlay'!Y49+'Disposals Overlay'!Y49 -> 50402.553 | ... CD49: ='Value Segment'!BY49+'Mid-Market Segment'!BY49+'Upper Mid-Market Segment'!BY49+'Premium Segment'!BY49+'Closures Overlay'!BY49+'Disposals Overlay'!BY49 -> 37888.816
E50: F&F income | I50: 175705.16 | J50: 258782.38 | K50: 348999.44 | L50: 389521.04 | N50: ='Value Segment'!I50+'Mid-Market Segment'!I50+'Upper Mid-Market Segment'!I50+'Premium Segment'!I50+'Closures Overlay'!I50+'Disposals Overlay'!I50 -> 399308.78 | O50: ='Value Segment'!J50+'Mid-Market Segment'!J50+'Upper Mid-Market Segment'!J50+'Premium Segment'!J50+'Closures Overlay'!J50+'Disposals Overlay'!J50 -> 392162.31 | P50: ='Value Segment'!K50+'Mid-Market Segment'!K50+'Upper Mid-Market Segment'!K50+'Premium Segment'!K50+'Closures Overlay'!K50+'Disposals Overlay'!K50 -> 370722.91 | Q50: ='Value Segment'!L50+'Mid-Market Segment'!L50+'Upper Mid-Market Segment'!L50+'Premium Segment'!L50+'Closures Overlay'!L50+'Disposals Overlay'!L50 -> 349283.52 | R50: ='Value Segment'!M50+'Mid-Market Segment'!M50+'Upper Mid-Market Segment'!M50+'Premium Segment'!M50+'Closures Overlay'!M50+'Disposals Overlay'!M50 -> 327844.12 | S50: ='Value Segment'!N50+'Mid-Market Segment'!N50+'Upper Mid-Market Segment'!N50+'Premium Segment'!N50+'Closures Overlay'!N50+'Disposals Overlay'!N50 -> 306404.72 | U50: =IFERROR(((S50/N50)^(1/5))-1,0) -> -0.051587391 | W50: ='Value Segment'!R50+'Mid-Market Segment'!R50+'Upper Mid-Market Segment'!R50+'Premium Segment'!R50+'Closures Overlay'!R50+'Disposals Overlay'!R50 -> 33275.731 | X50: ='Value Segment'!S50+'Mid-Market Segment'!S50+'Upper Mid-Market Segment'!S50+'Premium Segment'!S50+'Closures Overlay'!S50+'Disposals Overlay'!S50 -> 33275.731 | Y50: ='Value Segment'!T50+'Mid-Market Segment'!T50+'Upper Mid-Market Segment'!T50+'Premium Segment'!T50+'Closures Overlay'!T50+'Disposals Overlay'!T50 -> 33275.731 | Z50: ='Value Segment'!U50+'Mid-Market Segment'!U50+'Upper Mid-Market Segment'!U50+'Premium Segment'!U50+'Closures Overlay'!U50+'Disposals Overlay'!U50 -> 33275.731 | AA50: ='Value Segment'!V50+'Mid-Market Segment'!V50+'Upper Mid-Market Segment'!V50+'Premium Segment'!V50+'Closures Overlay'!V50+'Disposals Overlay'!V50 -> 33275.731 | AB50: ='Value Segment'!W50+'Mid-Market Segment'!W50+'Upper Mid-Market Segment'!W50+'Premium Segment'!W50+'Closures Overlay'!W50+'Disposals Overlay'!W50 -> 32382.423 | AC50: ='Value Segment'!X50+'Mid-Market Segment'!X50+'Upper Mid-Market Segment'!X50+'Premium Segment'!X50+'Closures Overlay'!X50+'Disposals Overlay'!X50 -> 32382.423 | AD50: ='Value Segment'!Y50+'Mid-Market Segment'!Y50+'Upper Mid-Market Segment'!Y50+'Premium Segment'!Y50+'Closures Overlay'!Y50+'Disposals Overlay'!Y50 -> 32382.423 | ... CD50: ='Value Segment'!BY50+'Mid-Market Segment'!BY50+'Upper Mid-Market Segment'!BY50+'Premium Segment'!BY50+'Closures Overlay'!BY50+'Disposals Overlay'!BY50 -> 24342.649
E51: Insurance income | I51: 787795.79 | J51: 872430.87 | K51: 915562.87 | L51: 931415.25 | N51: ='Value Segment'!I51+'Mid-Market Segment'!I51+'Upper Mid-Market Segment'!I51+'Premium Segment'!I51+'Closures Overlay'!I51+'Disposals Overlay'!I51 -> 922330.71 | O51: ='Value Segment'!J51+'Mid-Market Segment'!J51+'Upper Mid-Market Segment'!J51+'Premium Segment'!J51+'Closures Overlay'!J51+'Disposals Overlay'!J51 -> 905823.67 | P51: ='Value Segment'!K51+'Mid-Market Segment'!K51+'Upper Mid-Market Segment'!K51+'Premium Segment'!K51+'Closures Overlay'!K51+'Disposals Overlay'!K51 -> 856302.56 | Q51: ='Value Segment'!L51+'Mid-Market Segment'!L51+'Upper Mid-Market Segment'!L51+'Premium Segment'!L51+'Closures Overlay'!L51+'Disposals Overlay'!L51 -> 806781.45 | R51: ='Value Segment'!M51+'Mid-Market Segment'!M51+'Upper Mid-Market Segment'!M51+'Premium Segment'!M51+'Closures Overlay'!M51+'Disposals Overlay'!M51 -> 757260.34 | S51: ='Value Segment'!N51+'Mid-Market Segment'!N51+'Upper Mid-Market Segment'!N51+'Premium Segment'!N51+'Closures Overlay'!N51+'Disposals Overlay'!N51 -> 707739.22 | U51: =IFERROR(((S51/N51)^(1/5))-1,0) -> -0.051587391 | W51: ='Value Segment'!R51+'Mid-Market Segment'!R51+'Upper Mid-Market Segment'!R51+'Premium Segment'!R51+'Closures Overlay'!R51+'Disposals Overlay'!R51 -> 76860.892 | X51: ='Value Segment'!S51+'Mid-Market Segment'!S51+'Upper Mid-Market Segment'!S51+'Premium Segment'!S51+'Closures Overlay'!S51+'Disposals Overlay'!S51 -> 76860.892 | Y51: ='Value Segment'!T51+'Mid-Market Segment'!T51+'Upper Mid-Market Segment'!T51+'Premium Segment'!T51+'Closures Overlay'!T51+'Disposals Overlay'!T51 -> 76860.892 | Z51: ='Value Segment'!U51+'Mid-Market Segment'!U51+'Upper Mid-Market Segment'!U51+'Premium Segment'!U51+'Closures Overlay'!U51+'Disposals Overlay'!U51 -> 76860.892 | AA51: ='Value Segment'!V51+'Mid-Market Segment'!V51+'Upper Mid-Market Segment'!V51+'Premium Segment'!V51+'Closures Overlay'!V51+'Disposals Overlay'!V51 -> 76860.892 | AB51: ='Value Segment'!W51+'Mid-Market Segment'!W51+'Upper Mid-Market Segment'!W51+'Premium Segment'!W51+'Closures Overlay'!W51+'Disposals Overlay'!W51 -> 74797.513 | AC51: ='Value Segment'!X51+'Mid-Market Segment'!X51+'Upper Mid-Market Segment'!X51+'Premium Segment'!X51+'Closures Overlay'!X51+'Disposals Overlay'!X51 -> 74797.513 | AD51: ='Value Segment'!Y51+'Mid-Market Segment'!Y51+'Upper Mid-Market Segment'!Y51+'Premium Segment'!Y51+'Closures Overlay'!Y51+'Disposals Overlay'!Y51 -> 74797.513 | ... CD51: ='Value Segment'!BY51+'Mid-Market Segment'!BY51+'Upper Mid-Market Segment'!BY51+'Premium Segment'!BY51+'Closures Overlay'!BY51+'Disposals Overlay'!BY51 -> 56227.096
E52: Total other income | I52: =SUM(I48:I51) -> 1679639.4 | J52: =SUM(J48:J51) -> 1793945.1 | K52: =SUM(K48:K51) -> 1923103 | L52: =SUM(L48:L51) -> 2006347.8 | N52: =SUM(N48:N51) -> 1964702 | O52: =SUM(O48:O51) -> 1929539.6 | P52: =SUM(P48:P51) -> 1824052.2 | Q52: =SUM(Q48:Q51) -> 1718564.9 | R52: =SUM(R48:R51) -> 1613077.5 | S52: =SUM(S48:S51) -> 1507590.1 | U52: =IFERROR(((S52/N52)^(1/5))-1,0) -> -0.051587391 | W52: =SUM(W48:W51) -> 163725.17 | X52: =SUM(X48:X51) -> 163725.17 | Y52: =SUM(Y48:Y51) -> 163725.17 | Z52: =SUM(Z48:Z51) -> 163725.17 | AA52: =SUM(AA48:AA51) -> 163725.17 | AB52: =SUM(AB48:AB51) -> 159329.86 | AC52: =SUM(AC48:AC51) -> 159329.86 | AD52: =SUM(AD48:AD51) -> 159329.86 | ... CD52: =SUM(CD48:CD51) -> 119772.1
E54: Net income (drinks GP + rent + other income) | I54: =SUM(I39,I45,I52) -> 26289515 | J54: =SUM(J39,J45,J52) -> 27926190 | K54: =SUM(K39,K45,K52) -> 28360011 | L54: =SUM(L39,L45,L52) -> 28583857 | N54: =SUM(N39,N45,N52) -> 29499231 | O54: =SUM(O39,O45,O52) -> 30517356 | P54: =SUM(P39,P45,P52) -> 30600472 | Q54: =SUM(Q39,Q45,Q52) -> 30522840 | R54: =SUM(R39,R45,R52) -> 30271105 | S54: =SUM(S39,S45,S52) -> 29881514 | U54: =IFERROR(((S54/N54)^(1/5))-1,0) -> 0.0025784846 | W54: =SUM(W39,W45,W52) -> 2559089.2 | X54: =SUM(X39,X45,X52) -> 2559089.2 | Y54: =SUM(Y39,Y45,Y52) -> 2559089.2 | Z54: =SUM(Z39,Z45,Z52) -> 2559089.2 | AA54: =SUM(AA39,AA45,AA52) -> 2559089.2 | AB54: =SUM(AB39,AB45,AB52) -> 2490388.8 | AC54: =SUM(AC39,AC45,AC52) -> 2550312.5 | AD54: =SUM(AD39,AD45,AD52) -> 2550312.5 | ... CD54: =SUM(CD39,CD45,CD52) -> 2425793
E56: Pub costs
E57: R&M | I57: -626159.86 | J57: -873385.44 | K57: -582458.56 | L57: -564690.03 | N57: ='Value Segment'!I57+'Mid-Market Segment'!I57+'Upper Mid-Market Segment'!I57+'Premium Segment'!I57+'Closures Overlay'!I57+'Disposals Overlay'!I57 -> -576809.1 | O57: ='Value Segment'!J57+'Mid-Market Segment'!J57+'Upper Mid-Market Segment'!J57+'Premium Segment'!J57+'Closures Overlay'!J57+'Disposals Overlay'!J57 -> -577815.61 | P57: ='Value Segment'!K57+'Mid-Market Segment'!K57+'Upper Mid-Market Segment'!K57+'Premium Segment'!K57+'Closures Overlay'!K57+'Disposals Overlay'!K57 -> -557151.14 | Q57: ='Value Segment'!L57+'Mid-Market Segment'!L57+'Upper Mid-Market Segment'!L57+'Premium Segment'!L57+'Closures Overlay'!L57+'Disposals Overlay'!L57 -> -535428.95 | R57: ='Value Segment'!M57+'Mid-Market Segment'!M57+'Upper Mid-Market Segment'!M57+'Premium Segment'!M57+'Closures Overlay'!M57+'Disposals Overlay'!M57 -> -512615.02 | S57: ='Value Segment'!N57+'Mid-Market Segment'!N57+'Upper Mid-Market Segment'!N57+'Premium Segment'!N57+'Closures Overlay'!N57+'Disposals Overlay'!N57 -> -488674.37 | U57: =IFERROR(((S57/N57)^(1/5))-1,0) -> -0.032619138 | W57: ='Value Segment'!R57+'Mid-Market Segment'!R57+'Upper Mid-Market Segment'!R57+'Premium Segment'!R57+'Closures Overlay'!R57+'Disposals Overlay'!R57 -> -49028.773 | X57: ='Value Segment'!S57+'Mid-Market Segment'!S57+'Upper Mid-Market Segment'!S57+'Premium Segment'!S57+'Closures Overlay'!S57+'Disposals Overlay'!S57 -> -49028.773 | Y57: ='Value Segment'!T57+'Mid-Market Segment'!T57+'Upper Mid-Market Segment'!T57+'Premium Segment'!T57+'Closures Overlay'!T57+'Disposals Overlay'!T57 -> -49028.773 | Z57: ='Value Segment'!U57+'Mid-Market Segment'!U57+'Upper Mid-Market Segment'!U57+'Premium Segment'!U57+'Closures Overlay'!U57+'Disposals Overlay'!U57 -> -49028.773 | AA57: ='Value Segment'!V57+'Mid-Market Segment'!V57+'Upper Mid-Market Segment'!V57+'Premium Segment'!V57+'Closures Overlay'!V57+'Disposals Overlay'!V57 -> -49028.773 | AB57: ='Value Segment'!W57+'Mid-Market Segment'!W57+'Upper Mid-Market Segment'!W57+'Premium Segment'!W57+'Closures Overlay'!W57+'Disposals Overlay'!W57 -> -47712.565 | AC57: ='Value Segment'!X57+'Mid-Market Segment'!X57+'Upper Mid-Market Segment'!X57+'Premium Segment'!X57+'Closures Overlay'!X57+'Disposals Overlay'!X57 -> -47712.565 | AD57: ='Value Segment'!Y57+'Mid-Market Segment'!Y57+'Upper Mid-Market Segment'!Y57+'Premium Segment'!Y57+'Closures Overlay'!Y57+'Disposals Overlay'!Y57 -> -47712.565 | ... CD57: ='Value Segment'!BY57+'Mid-Market Segment'!BY57+'Upper Mid-Market Segment'!BY57+'Premium Segment'!BY57+'Closures Overlay'!BY57+'Disposals Overlay'!BY57 -> -38823.255
E58: Marketing Support | I58: -98240.37 | J58: -95258.11 | K58: -106686.83 | L58: -90338.02 | N58: ='Value Segment'!I58+'Mid-Market Segment'!I58+'Upper Mid-Market Segment'!I58+'Premium Segment'!I58+'Closures Overlay'!I58+'Disposals Overlay'!I58 -> -87480.06 | O58: ='Value Segment'!J58+'Mid-Market Segment'!J58+'Upper Mid-Market Segment'!J58+'Premium Segment'!J58+'Closures Overlay'!J58+'Disposals Overlay'!J58 -> -87632.709 | P58: ='Value Segment'!K58+'Mid-Market Segment'!K58+'Upper Mid-Market Segment'!K58+'Premium Segment'!K58+'Closures Overlay'!K58+'Disposals Overlay'!K58 -> -84498.692 | Q58: ='Value Segment'!L58+'Mid-Market Segment'!L58+'Upper Mid-Market Segment'!L58+'Premium Segment'!L58+'Closures Overlay'!L58+'Disposals Overlay'!L58 -> -81204.261 | R58: ='Value Segment'!M58+'Mid-Market Segment'!M58+'Upper Mid-Market Segment'!M58+'Premium Segment'!M58+'Closures Overlay'!M58+'Disposals Overlay'!M58 -> -77744.254 | S58: ='Value Segment'!N58+'Mid-Market Segment'!N58+'Upper Mid-Market Segment'!N58+'Premium Segment'!N58+'Closures Overlay'!N58+'Disposals Overlay'!N58 -> -74113.364 | U58: =IFERROR(((S58/N58)^(1/5))-1,0) -> -0.032619138 | W58: ='Value Segment'!R58+'Mid-Market Segment'!R58+'Upper Mid-Market Segment'!R58+'Premium Segment'!R58+'Closures Overlay'!R58+'Disposals Overlay'!R58 -> -7435.8051 | X58: ='Value Segment'!S58+'Mid-Market Segment'!S58+'Upper Mid-Market Segment'!S58+'Premium Segment'!S58+'Closures Overlay'!S58+'Disposals Overlay'!S58 -> -7435.8051 | Y58: ='Value Segment'!T58+'Mid-Market Segment'!T58+'Upper Mid-Market Segment'!T58+'Premium Segment'!T58+'Closures Overlay'!T58+'Disposals Overlay'!T58 -> -7435.8051 | Z58: ='Value Segment'!U58+'Mid-Market Segment'!U58+'Upper Mid-Market Segment'!U58+'Premium Segment'!U58+'Closures Overlay'!U58+'Disposals Overlay'!U58 -> -7435.8051 | AA58: ='Value Segment'!V58+'Mid-Market Segment'!V58+'Upper Mid-Market Segment'!V58+'Premium Segment'!V58+'Closures Overlay'!V58+'Disposals Overlay'!V58 -> -7435.8051 | AB58: ='Value Segment'!W58+'Mid-Market Segment'!W58+'Upper Mid-Market Segment'!W58+'Premium Segment'!W58+'Closures Overlay'!W58+'Disposals Overlay'!W58 -> -7236.1861 | AC58: ='Value Segment'!X58+'Mid-Market Segment'!X58+'Upper Mid-Market Segment'!X58+'Premium Segment'!X58+'Closures Overlay'!X58+'Disposals Overlay'!X58 -> -7236.1861 | AD58: ='Value Segment'!Y58+'Mid-Market Segment'!Y58+'Upper Mid-Market Segment'!Y58+'Premium Segment'!Y58+'Closures Overlay'!Y58+'Disposals Overlay'!Y58 -> -7236.1861 | ... CD58: ='Value Segment'!BY58+'Mid-Market Segment'!BY58+'Upper Mid-Market Segment'!BY58+'Premium Segment'!BY58+'Closures Overlay'!BY58+'Disposals Overlay'!BY58 -> -5888.0151
E59: Total pub costs | I59: =SUM(I57:I58) -> -724400.23 | J59: =SUM(J57:J58) -> -968643.55 | K59: =SUM(K57:K58) -> -689145.39 | L59: =SUM(L57:L58) -> -655028.05 | N59: =SUM(N57:N58) -> -664289.16 | O59: =SUM(O57:O58) -> -665448.32 | P59: =SUM(P57:P58) -> -641649.83 | Q59: =SUM(Q57:Q58) -> -616633.22 | R59: =SUM(R57:R58) -> -590359.28 | S59: =SUM(S57:S58) -> -562787.73 | U59: =IFERROR(((S59/N59)^(1/5))-1,0) -> -0.032619138 | W59: =SUM(W57:W58) -> -56464.579 | X59: =SUM(X57:X58) -> -56464.579 | Y59: =SUM(Y57:Y58) -> -56464.579 | Z59: =SUM(Z57:Z58) -> -56464.579 | AA59: =SUM(AA57:AA58) -> -56464.579 | AB59: =SUM(AB57:AB58) -> -54948.751 | AC59: =SUM(AC57:AC58) -> -54948.751 | AD59: =SUM(AD57:AD58) -> -54948.751 | ... CD59: =SUM(CD57:CD58) -> -44711.27
E61: Outlet EBITDA | I61: =SUM(I54,I59) -> 25565115 | J61: =SUM(J54,J59) -> 26957547 | K61: =SUM(K54,K59) -> 27670866 | L61: =SUM(L54,L59) -> 27928829 | N61: =SUM(N54,N59) -> 28834942 | O61: =SUM(O54,O59) -> 29851908 | P61: =SUM(P54,P59) -> 29958822 | Q61: =SUM(Q54,Q59) -> 29906207 | R61: =SUM(R54,R59) -> 29680745 | S61: =SUM(S54,S59) -> 29318726 | U61: =IFERROR(((S61/N61)^(1/5))-1,0) -> 0.003333247 | W61: =SUM(W54,W59) -> 2502624.6 | X61: =SUM(X54,X59) -> 2502624.6 | Y61: =SUM(Y54,Y59) -> 2502624.6 | Z61: =SUM(Z54,Z59) -> 2502624.6 | AA61: =SUM(AA54,AA59) -> 2502624.6 | AB61: =SUM(AB54,AB59) -> 2435440 | AC61: =SUM(AC54,AC59) -> 2495363.8 | AD61: =SUM(AD54,AD59) -> 2495363.8 | ... CD61: =SUM(CD54,CD59) -> 2381081.7
E62: Outlet EBITDA Margin | I62: =IFERROR(I61/SUM(I22,I31,I45,I52),0) -> 0.52638749 | J62: =IFERROR(J61/SUM(J22,J31,J45,J52),0) -> 0.5367479 | K62: =IFERROR(K61/SUM(K22,K31,K45,K52),0) -> 0.55183959 | L62: =IFERROR(L61/SUM(L22,L31,L45,L52),0) -> 0.55628632 | N62: =IFERROR(N61/SUM(N22,N31,N45,N52),0) -> 0.55284127 | O62: =IFERROR(O61/SUM(O22,O31,O45,O52),0) -> 0.55790956 | P62: =IFERROR(P61/SUM(P22,P31,P45,P52),0) -> 0.56280401 | Q62: =IFERROR(Q61/SUM(Q22,Q31,Q45,Q52),0) -> 0.56739351 | R62: =IFERROR(R61/SUM(R22,R31,R45,R52),0) -> 0.57146195 | S62: =IFERROR(S61/SUM(S22,S31,S45,S52),0) -> 0.57536876 | U62: =IFERROR(((S62/N62)^(1/5))-1,0) -> 0.008020037 | W62: =IFERROR(W61/SUM(W22,W31,W45,W52),0) -> 0.5577129 | X62: =IFERROR(X61/SUM(X22,X31,X45,X52),0) -> 0.5577129 | Y62: =IFERROR(Y61/SUM(Y22,Y31,Y45,Y52),0) -> 0.5577129 | Z62: =IFERROR(Z61/SUM(Z22,Z31,Z45,Z52),0) -> 0.5577129 | AA62: =IFERROR(AA61/SUM(AA22,AA31,AA45,AA52),0) -> 0.5577129 | AB62: =IFERROR(AB61/SUM(AB22,AB31,AB45,AB52),0) -> 0.5577129 | AC62: =IFERROR(AC61/SUM(AC22,AC31,AC45,AC52),0) -> 0.55810695 | AD62: =IFERROR(AD61/SUM(AD22,AD31,AD45,AD52),0) -> 0.55810695 | ... CD62: =IFERROR(CD61/SUM(CD22,CD31,CD45,CD52),0) -> 0.57589142
E64: Overheads | I64: -2494800 | J64: -2494800 | K64: -2494800 | L64: -2494800 | N64: ='Value Segment'!I64+'Mid-Market Segment'!I64+'Upper Mid-Market Segment'!I64+'Premium Segment'!I64+'Closures Overlay'!I64+'Disposals Overlay'!I64 -> -2679600 | O64: ='Value Segment'!J64+'Mid-Market Segment'!J64+'Upper Mid-Market Segment'!J64+'Premium Segment'!J64+'Closures Overlay'!J64+'Disposals Overlay'!J64 -> -2698178 | P64: ='Value Segment'!K64+'Mid-Market Segment'!K64+'Upper Mid-Market Segment'!K64+'Premium Segment'!K64+'Closures Overlay'!K64+'Disposals Overlay'!K64 -> -2614763 | Q64: ='Value Segment'!L64+'Mid-Market Segment'!L64+'Upper Mid-Market Segment'!L64+'Premium Segment'!L64+'Closures Overlay'!L64+'Disposals Overlay'!L64 -> -2521776.6 | R64: ='Value Segment'!M64+'Mid-Market Segment'!M64+'Upper Mid-Market Segment'!M64+'Premium Segment'!M64+'Closures Overlay'!M64+'Disposals Overlay'!M64 -> -2419207.9 | S64: ='Value Segment'!N64+'Mid-Market Segment'!N64+'Upper Mid-Market Segment'!N64+'Premium Segment'!N64+'Closures Overlay'!N64+'Disposals Overlay'!N64 -> -2311200.4 | U64: =IFERROR(((S64/N64)^(1/5))-1,0) -> -0.02914689 | W64: ='Value Segment'!R64+'Mid-Market Segment'!R64+'Upper Mid-Market Segment'!R64+'Premium Segment'!R64+'Closures Overlay'!R64+'Disposals Overlay'!R64 -> -228810.25 | X64: ='Value Segment'!S64+'Mid-Market Segment'!S64+'Upper Mid-Market Segment'!S64+'Premium Segment'!S64+'Closures Overlay'!S64+'Disposals Overlay'!S64 -> -228810.25 | Y64: ='Value Segment'!T64+'Mid-Market Segment'!T64+'Upper Mid-Market Segment'!T64+'Premium Segment'!T64+'Closures Overlay'!T64+'Disposals Overlay'!T64 -> -228810.25 | Z64: ='Value Segment'!U64+'Mid-Market Segment'!U64+'Upper Mid-Market Segment'!U64+'Premium Segment'!U64+'Closures Overlay'!U64+'Disposals Overlay'!U64 -> -228810.25 | AA64: ='Value Segment'!V64+'Mid-Market Segment'!V64+'Upper Mid-Market Segment'!V64+'Premium Segment'!V64+'Closures Overlay'!V64+'Disposals Overlay'!V64 -> -228810.25 | AB64: ='Value Segment'!W64+'Mid-Market Segment'!W64+'Upper Mid-Market Segment'!W64+'Premium Segment'!W64+'Closures Overlay'!W64+'Disposals Overlay'!W64 -> -222867.13 | AC64: ='Value Segment'!X64+'Mid-Market Segment'!X64+'Upper Mid-Market Segment'!X64+'Premium Segment'!X64+'Closures Overlay'!X64+'Disposals Overlay'!X64 -> -222867.13 | AD64: ='Value Segment'!Y64+'Mid-Market Segment'!Y64+'Upper Mid-Market Segment'!Y64+'Premium Segment'!Y64+'Closures Overlay'!Y64+'Disposals Overlay'!Y64 -> -222867.13 | ... CD64: ='Value Segment'!BY64+'Mid-Market Segment'!BY64+'Upper Mid-Market Segment'!BY64+'Premium Segment'!BY64+'Closures Overlay'!BY64+'Disposals Overlay'!BY64 -> -183992.21
E65: Corporate EBITDA | I65: =I64+I61 -> 23070315 | J65: =J64+J61 -> 24462747 | K65: =K64+K61 -> 25176066 | L65: =L64+L61 -> 25434029 | N65: =N64+N61 -> 26155342 | O65: =O64+O61 -> 27153730 | P65: =P64+P61 -> 27344059 | Q65: =Q64+Q61 -> 27384430 | R65: =R64+R61 -> 27261537 | S65: =S64+S61 -> 27007526 | U65: =IFERROR(((S65/N65)^(1/5))-1,0) -> 0.0064330263 | W65: =W64+W61 -> 2273814.3 | X65: =X64+X61 -> 2273814.3 | Y65: =Y64+Y61 -> 2273814.3 | Z65: =Z64+Z61 -> 2273814.3 | AA65: =AA64+AA61 -> 2273814.3 | AB65: =AB64+AB61 -> 2212572.9 | AC65: =AC64+AC61 -> 2272496.7 | AD65: =AD64+AD61 -> 2272496.7 | ... CD65: =CD64+CD61 -> 2197089.5
E66: Corporate EBITDA margin (%) | I66: =IFERROR(I65/SUM(I22,I31,I45,I52),0) -> 0.47501939 | J66: =IFERROR(J65/SUM(J22,J31,J45,J52),0) -> 0.48707429 | K66: =IFERROR(K65/SUM(K22,K31,K45,K52),0) -> 0.50208584 | L66: =IFERROR(L65/SUM(L22,L31,L45,L52),0) -> 0.5065949 | M66: =IFERROR(M65/SUM(M22,M31,M45,M52),0) -> 0 | N66: =IFERROR(N65/SUM(N22,N31,N45,N52),0) -> 0.50146633 | O66: =IFERROR(O65/SUM(O22,O31,O45,O52),0) -> 0.50748265 | P66: =IFERROR(P65/SUM(P22,P31,P45,P52),0) -> 0.51368328 | ... S66: =IFERROR(S65/SUM(S22,S31,S45,S52),0) -> 0.53001234 | U66: =IFERROR(((S66/N66)^(1/5))-1,0) -> 0.011134296 | W66: =IFERROR(W65/SUM(W22,W31,W45,W52),0) -> 0.50672226 | X66: =IFERROR(X65/SUM(X22,X31,X45,X52),0) -> 0.50672226 | Y66: =IFERROR(Y65/SUM(Y22,Y31,Y45,Y52),0) -> 0.50672226 | Z66: =IFERROR(Z65/SUM(Z22,Z31,Z45,Z52),0) -> 0.50672226 | AA66: =IFERROR(AA65/SUM(AA22,AA31,AA45,AA52),0) -> 0.50672226 | AB66: =IFERROR(AB65/SUM(AB22,AB31,AB45,AB52),0) -> 0.50667659 | AC66: =IFERROR(AC65/SUM(AC22,AC31,AC45,AC52),0) -> 0.50826104 | AD66: =IFERROR(AD65/SUM(AD22,AD31,AD45,AD52),0) -> 0.50826104 | ... CD66: =IFERROR(CD65/SUM(CD22,CD31,CD45,CD52),0) -> 0.53139083
E68: Maintenance capex | I68: -2581520.8 | J68: -3593664.8 | K68: -2663578.1 | L68: -3067823.2 | N68: ='Value Segment'!I68+'Mid-Market Segment'!I68+'Upper Mid-Market Segment'!I68+'Premium Segment'!I68+'Closures Overlay'!I68+'Disposals Overlay'!I68 -> -3065576.1 | O68: ='Value Segment'!J68+'Mid-Market Segment'!J68+'Upper Mid-Market Segment'!J68+'Premium Segment'!J68+'Closures Overlay'!J68+'Disposals Overlay'!J68 -> -2388160 | P68: ='Value Segment'!K68+'Mid-Market Segment'!K68+'Upper Mid-Market Segment'!K68+'Premium Segment'!K68+'Closures Overlay'!K68+'Disposals Overlay'!K68 -> -2302752 | Q68: ='Value Segment'!L68+'Mid-Market Segment'!L68+'Upper Mid-Market Segment'!L68+'Premium Segment'!L68+'Closures Overlay'!L68+'Disposals Overlay'!L68 -> -2212972.4 | R68: ='Value Segment'!M68+'Mid-Market Segment'!M68+'Upper Mid-Market Segment'!M68+'Premium Segment'!M68+'Closures Overlay'!M68+'Disposals Overlay'!M68 -> -2118680.5 | S68: ='Value Segment'!N68+'Mid-Market Segment'!N68+'Upper Mid-Market Segment'!N68+'Premium Segment'!N68+'Closures Overlay'!N68+'Disposals Overlay'!N68 -> -2019731.8 | U68: =IFERROR(((S68/N68)^(1/5))-1,0) -> -0.080066742 | W68: ='Value Segment'!R68+'Mid-Market Segment'!R68+'Upper Mid-Market Segment'!R68+'Premium Segment'!R68+'Closures Overlay'!R68+'Disposals Overlay'!R68 -> -202640 | X68: ='Value Segment'!S68+'Mid-Market Segment'!S68+'Upper Mid-Market Segment'!S68+'Premium Segment'!S68+'Closures Overlay'!S68+'Disposals Overlay'!S68 -> -202640 | Y68: ='Value Segment'!T68+'Mid-Market Segment'!T68+'Upper Mid-Market Segment'!T68+'Premium Segment'!T68+'Closures Overlay'!T68+'Disposals Overlay'!T68 -> -202640 | Z68: ='Value Segment'!U68+'Mid-Market Segment'!U68+'Upper Mid-Market Segment'!U68+'Premium Segment'!U68+'Closures Overlay'!U68+'Disposals Overlay'!U68 -> -202640 | AA68: ='Value Segment'!V68+'Mid-Market Segment'!V68+'Upper Mid-Market Segment'!V68+'Premium Segment'!V68+'Closures Overlay'!V68+'Disposals Overlay'!V68 -> -202640 | AB68: ='Value Segment'!W68+'Mid-Market Segment'!W68+'Upper Mid-Market Segment'!W68+'Premium Segment'!W68+'Closures Overlay'!W68+'Disposals Overlay'!W68 -> -197200 | AC68: ='Value Segment'!X68+'Mid-Market Segment'!X68+'Upper Mid-Market Segment'!X68+'Premium Segment'!X68+'Closures Overlay'!X68+'Disposals Overlay'!X68 -> -197200 | AD68: ='Value Segment'!Y68+'Mid-Market Segment'!Y68+'Upper Mid-Market Segment'!Y68+'Premium Segment'!Y68+'Closures Overlay'!Y68+'Disposals Overlay'!Y68 -> -197200 | ... CD68: ='Value Segment'!BY68+'Mid-Market Segment'!BY68+'Upper Mid-Market Segment'!BY68+'Premium Segment'!BY68+'Closures Overlay'!BY68+'Disposals Overlay'!BY68 -> -160459.74
E69: Bad debts | I69: -295394 | J69: -546267.84 | K69: -547348.92 | L69: -683027.13 | N69: ='Value Segment'!I69+'Mid-Market Segment'!I69+'Upper Mid-Market Segment'!I69+'Premium Segment'!I69+'Closures Overlay'!I69+'Disposals Overlay'!I69 -> -432524.13 | O69: ='Value Segment'!J69+'Mid-Market Segment'!J69+'Upper Mid-Market Segment'!J69+'Premium Segment'!J69+'Closures Overlay'!J69+'Disposals Overlay'!J69 -> -447778.62 | P69: ='Value Segment'!K69+'Mid-Market Segment'!K69+'Upper Mid-Market Segment'!K69+'Premium Segment'!K69+'Closures Overlay'!K69+'Disposals Overlay'!K69 -> -449382.33 | Q69: ='Value Segment'!L69+'Mid-Market Segment'!L69+'Upper Mid-Market Segment'!L69+'Premium Segment'!L69+'Closures Overlay'!L69+'Disposals Overlay'!L69 -> -448593.1 | R69: ='Value Segment'!M69+'Mid-Market Segment'!M69+'Upper Mid-Market Segment'!M69+'Premium Segment'!M69+'Closures Overlay'!M69+'Disposals Overlay'!M69 -> -445211.18 | S69: ='Value Segment'!N69+'Mid-Market Segment'!N69+'Upper Mid-Market Segment'!N69+'Premium Segment'!N69+'Closures Overlay'!N69+'Disposals Overlay'!N69 -> -439780.9 | U69: =IFERROR(((S69/N69)^(1/5))-1,0) -> 0.003333247 | W69: ='Value Segment'!R69+'Mid-Market Segment'!R69+'Upper Mid-Market Segment'!R69+'Premium Segment'!R69+'Closures Overlay'!R69+'Disposals Overlay'!R69 -> -37539.369 | X69: ='Value Segment'!S69+'Mid-Market Segment'!S69+'Upper Mid-Market Segment'!S69+'Premium Segment'!S69+'Closures Overlay'!S69+'Disposals Overlay'!S69 -> -37539.369 | Y69: ='Value Segment'!T69+'Mid-Market Segment'!T69+'Upper Mid-Market Segment'!T69+'Premium Segment'!T69+'Closures Overlay'!T69+'Disposals Overlay'!T69 -> -37539.369 | Z69: ='Value Segment'!U69+'Mid-Market Segment'!U69+'Upper Mid-Market Segment'!U69+'Premium Segment'!U69+'Closures Overlay'!U69+'Disposals Overlay'!U69 -> -37539.369 | AA69: ='Value Segment'!V69+'Mid-Market Segment'!V69+'Upper Mid-Market Segment'!V69+'Premium Segment'!V69+'Closures Overlay'!V69+'Disposals Overlay'!V69 -> -37539.369 | AB69: ='Value Segment'!W69+'Mid-Market Segment'!W69+'Upper Mid-Market Segment'!W69+'Premium Segment'!W69+'Closures Overlay'!W69+'Disposals Overlay'!W69 -> -36531.6 | AC69: ='Value Segment'!X69+'Mid-Market Segment'!X69+'Upper Mid-Market Segment'!X69+'Premium Segment'!X69+'Closures Overlay'!X69+'Disposals Overlay'!X69 -> -37430.457 | AD69: ='Value Segment'!Y69+'Mid-Market Segment'!Y69+'Upper Mid-Market Segment'!Y69+'Premium Segment'!Y69+'Closures Overlay'!Y69+'Disposals Overlay'!Y69 -> -37430.457 | ... CD69: ='Value Segment'!BY69+'Mid-Market Segment'!BY69+'Upper Mid-Market Segment'!BY69+'Premium Segment'!BY69+'Closures Overlay'!BY69+'Disposals Overlay'!BY69 -> -35716.226
E70: Security costs re closed sites | I70: -38347.88 | J70: -126428.83 | K70: -109539.1 | L70: -116732.89 | N70: ='Value Segment'!I70+'Mid-Market Segment'!I70+'Upper Mid-Market Segment'!I70+'Premium Segment'!I70+'Closures Overlay'!I70+'Disposals Overlay'!I70 -> -300000 | O70: ='Value Segment'!J70+'Mid-Market Segment'!J70+'Upper Mid-Market Segment'!J70+'Premium Segment'!J70+'Closures Overlay'!J70+'Disposals Overlay'!J70 -> -307402.93 | P70: ='Value Segment'!K70+'Mid-Market Segment'!K70+'Upper Mid-Market Segment'!K70+'Premium Segment'!K70+'Closures Overlay'!K70+'Disposals Overlay'!K70 -> -314526.43 | Q70: ='Value Segment'!L70+'Mid-Market Segment'!L70+'Upper Mid-Market Segment'!L70+'Premium Segment'!L70+'Closures Overlay'!L70+'Disposals Overlay'!L70 -> -321272.72 | R70: ='Value Segment'!M70+'Mid-Market Segment'!M70+'Upper Mid-Market Segment'!M70+'Premium Segment'!M70+'Closures Overlay'!M70+'Disposals Overlay'!M70 -> -327569.22 | S70: ='Value Segment'!N70+'Mid-Market Segment'!N70+'Upper Mid-Market Segment'!N70+'Premium Segment'!N70+'Closures Overlay'!N70+'Disposals Overlay'!N70 -> -333924.15 | U70: =IFERROR(((S70/N70)^(1/5))-1,0) -> 0.021657473 | W70: ='Value Segment'!R70+'Mid-Market Segment'!R70+'Upper Mid-Market Segment'!R70+'Premium Segment'!R70+'Closures Overlay'!R70+'Disposals Overlay'!R70 -> -25616.911 | X70: ='Value Segment'!S70+'Mid-Market Segment'!S70+'Upper Mid-Market Segment'!S70+'Premium Segment'!S70+'Closures Overlay'!S70+'Disposals Overlay'!S70 -> -25616.911 | Y70: ='Value Segment'!T70+'Mid-Market Segment'!T70+'Upper Mid-Market Segment'!T70+'Premium Segment'!T70+'Closures Overlay'!T70+'Disposals Overlay'!T70 -> -25616.911 | Z70: ='Value Segment'!U70+'Mid-Market Segment'!U70+'Upper Mid-Market Segment'!U70+'Premium Segment'!U70+'Closures Overlay'!U70+'Disposals Overlay'!U70 -> -25616.911 | AA70: ='Value Segment'!V70+'Mid-Market Segment'!V70+'Upper Mid-Market Segment'!V70+'Premium Segment'!V70+'Closures Overlay'!V70+'Disposals Overlay'!V70 -> -25616.911 | AB70: ='Value Segment'!W70+'Mid-Market Segment'!W70+'Upper Mid-Market Segment'!W70+'Premium Segment'!W70+'Closures Overlay'!W70+'Disposals Overlay'!W70 -> -25616.911 | AC70: ='Value Segment'!X70+'Mid-Market Segment'!X70+'Upper Mid-Market Segment'!X70+'Premium Segment'!X70+'Closures Overlay'!X70+'Disposals Overlay'!X70 -> -25616.911 | AD70: ='Value Segment'!Y70+'Mid-Market Segment'!Y70+'Upper Mid-Market Segment'!Y70+'Premium Segment'!Y70+'Closures Overlay'!Y70+'Disposals Overlay'!Y70 -> -25616.911 | ... CD70: ='Value Segment'!BY70+'Mid-Market Segment'!BY70+'Upper Mid-Market Segment'!BY70+'Premium Segment'!BY70+'Closures Overlay'!BY70+'Disposals Overlay'!BY70 -> -27827.013
E71: Normalised operating CF | I71: =I65+SUM(I68:I70) -> 20155052 | J71: =J65+SUM(J68:J70) -> 20196385 | K71: =K65+SUM(K68:K70) -> 21855600 | L71: =L65+SUM(L68:L70) -> 21566446 | N71: =N65+SUM(N68:N70) -> 22357242 | O71: =O65+SUM(O68:O70) -> 24010388 | P71: =P65+SUM(P68:P70) -> 24277398 | Q71: =Q65+SUM(Q68:Q70) -> 24401592 | R71: =R65+SUM(R68:R70) -> 24370076 | S71: =S65+SUM(S68:S70) -> 24214089 | U71: =IFERROR(((S71/N71)^(1/5))-1,0) -> 0.016084866 | W71: =W65+SUM(W68:W70) -> 2008018.1 | X71: =X65+SUM(X68:X70) -> 2008018.1 | Y71: =Y65+SUM(Y68:Y70) -> 2008018.1 | Z71: =Z65+SUM(Z68:Z70) -> 2008018.1 | AA71: =AA65+SUM(AA68:AA70) -> 2008018.1 | AB71: =AB65+SUM(AB68:AB70) -> 1953224.4 | AC71: =AC65+SUM(AC68:AC70) -> 2012249.3 | AD71: =AD65+SUM(AD68:AD70) -> 2012249.3 | ... CD71: =CD65+SUM(CD68:CD70) -> 1973086.6
E72: Normalised operating CF conversion (%) | I72: =IFERROR(I71/I61,0) -> 0.78838105 | J72: =IFERROR(J71/J61,0) -> 0.74919226 | K72: =IFERROR(K71/K61,0) -> 0.78984155 | L72: =IFERROR(L71/L61,0) -> 0.77219298 | N72: =IFERROR(N71/N61,0) -> 0.77535241 | O72: =IFERROR(O71/O61,0) -> 0.80431671 | P72: =IFERROR(P71/P61,0) -> 0.81035891 | Q72: =IFERROR(Q71/Q61,0) -> 0.81593738 | R72: =IFERROR(R71/R61,0) -> 0.8210736 | S72: =IFERROR(S71/S61,0) -> 0.82589158 | U72: =IFERROR(((S72/N72)^(1/5))-1,0) -> 0.012709255 | W72: =IFERROR(W71/W61,0) -> 0.80236487 | X72: =IFERROR(X71/X61,0) -> 0.80236487 | Y72: =IFERROR(Y71/Y61,0) -> 0.80236487 | Z72: =IFERROR(Z71/Z61,0) -> 0.80236487 | AA72: =IFERROR(AA71/AA61,0) -> 0.80236487 | AB72: =IFERROR(AB71/AB61,0) -> 0.80200061 | AC72: =IFERROR(AC71/AC61,0) -> 0.80639516 | AD72: =IFERROR(AD71/AD61,0) -> 0.80639516 | ... CD72: =IFERROR(CD71/CD61,0) -> 0.82865133
E74: Growth capex | I74: -850365.85 | J74: -138031.89 | K74: -421795.4 | L74: -587858.03 | N74: ='Value Segment'!I74+'Mid-Market Segment'!I74+'Upper Mid-Market Segment'!I74+'Premium Segment'!I74+'Closures Overlay'!I74+'Disposals Overlay'!I74 -> -1391870.9 | O74: ='Value Segment'!J74+'Mid-Market Segment'!J74+'Upper Mid-Market Segment'!J74+'Premium Segment'!J74+'Closures Overlay'!J74+'Disposals Overlay'!J74 -> -1597966.6 | P74: ='Value Segment'!K74+'Mid-Market Segment'!K74+'Upper Mid-Market Segment'!K74+'Premium Segment'!K74+'Closures Overlay'!K74+'Disposals Overlay'!K74 -> -1546113.4 | Q74: ='Value Segment'!L74+'Mid-Market Segment'!L74+'Upper Mid-Market Segment'!L74+'Premium Segment'!L74+'Closures Overlay'!L74+'Disposals Overlay'!L74 -> -1488519.2 | R74: ='Value Segment'!M74+'Mid-Market Segment'!M74+'Upper Mid-Market Segment'!M74+'Premium Segment'!M74+'Closures Overlay'!M74+'Disposals Overlay'!M74 -> -1425078.2 | S74: ='Value Segment'!N74+'Mid-Market Segment'!N74+'Upper Mid-Market Segment'!N74+'Premium Segment'!N74+'Closures Overlay'!N74+'Disposals Overlay'!N74 -> -1356831.2 | U74: =IFERROR(((S74/N74)^(1/5))-1,0) -> -0.0050863927 | W74: ='Value Segment'!R74+'Mid-Market Segment'!R74+'Upper Mid-Market Segment'!R74+'Premium Segment'!R74+'Closures Overlay'!R74+'Disposals Overlay'!R74 -> 0 | X74: ='Value Segment'!S74+'Mid-Market Segment'!S74+'Upper Mid-Market Segment'!S74+'Premium Segment'!S74+'Closures Overlay'!S74+'Disposals Overlay'!S74 -> 0 | Y74: ='Value Segment'!T74+'Mid-Market Segment'!T74+'Upper Mid-Market Segment'!T74+'Premium Segment'!T74+'Closures Overlay'!T74+'Disposals Overlay'!T74 -> 0 | Z74: ='Value Segment'!U74+'Mid-Market Segment'!U74+'Upper Mid-Market Segment'!U74+'Premium Segment'!U74+'Closures Overlay'!U74+'Disposals Overlay'!U74 -> 0 | AA74: ='Value Segment'!V74+'Mid-Market Segment'!V74+'Upper Mid-Market Segment'!V74+'Premium Segment'!V74+'Closures Overlay'!V74+'Disposals Overlay'!V74 -> 0 | AB74: ='Value Segment'!W74+'Mid-Market Segment'!W74+'Upper Mid-Market Segment'!W74+'Premium Segment'!W74+'Closures Overlay'!W74+'Disposals Overlay'!W74 -> -1597966.6 | AC74: ='Value Segment'!X74+'Mid-Market Segment'!X74+'Upper Mid-Market Segment'!X74+'Premium Segment'!X74+'Closures Overlay'!X74+'Disposals Overlay'!X74 -> 0 | AD74: ='Value Segment'!Y74+'Mid-Market Segment'!Y74+'Upper Mid-Market Segment'!Y74+'Premium Segment'!Y74+'Closures Overlay'!Y74+'Disposals Overlay'!Y74 -> 0 | ... CD74: ='Value Segment'!BY74+'Mid-Market Segment'!BY74+'Upper Mid-Market Segment'!BY74+'Premium Segment'!BY74+'Closures Overlay'!BY74+'Disposals Overlay'!BY74 -> 0
E75: Asset disposal proceeds | I75: 0 | J75: 0 | K75: 0 | L75: 0 | N75: ='Value Segment'!I75+'Mid-Market Segment'!I75+'Upper Mid-Market Segment'!I75+'Premium Segment'!I75+'Closures Overlay'!I75+'Disposals Overlay'!I75 -> 0 | O75: ='Value Segment'!J75+'Mid-Market Segment'!J75+'Upper Mid-Market Segment'!J75+'Premium Segment'!J75+'Closures Overlay'!J75+'Disposals Overlay'!J75 -> 21007265 | P75: ='Value Segment'!K75+'Mid-Market Segment'!K75+'Upper Mid-Market Segment'!K75+'Premium Segment'!K75+'Closures Overlay'!K75+'Disposals Overlay'!K75 -> 22302773 | Q75: ='Value Segment'!L75+'Mid-Market Segment'!L75+'Upper Mid-Market Segment'!L75+'Premium Segment'!L75+'Closures Overlay'!L75+'Disposals Overlay'!L75 -> 23631372 | R75: ='Value Segment'!M75+'Mid-Market Segment'!M75+'Upper Mid-Market Segment'!M75+'Premium Segment'!M75+'Closures Overlay'!M75+'Disposals Overlay'!M75 -> 24988348 | S75: ='Value Segment'!N75+'Mid-Market Segment'!N75+'Upper Mid-Market Segment'!N75+'Premium Segment'!N75+'Closures Overlay'!N75+'Disposals Overlay'!N75 -> 26412339 | U75: =IFERROR(((S75/N75)^(1/5))-1,0) -> 0 | W75: ='Value Segment'!R75+'Mid-Market Segment'!R75+'Upper Mid-Market Segment'!R75+'Premium Segment'!R75+'Closures Overlay'!R75+'Disposals Overlay'!R75 -> 0 | X75: ='Value Segment'!S75+'Mid-Market Segment'!S75+'Upper Mid-Market Segment'!S75+'Premium Segment'!S75+'Closures Overlay'!S75+'Disposals Overlay'!S75 -> 0 | Y75: ='Value Segment'!T75+'Mid-Market Segment'!T75+'Upper Mid-Market Segment'!T75+'Premium Segment'!T75+'Closures Overlay'!T75+'Disposals Overlay'!T75 -> 0 | Z75: ='Value Segment'!U75+'Mid-Market Segment'!U75+'Upper Mid-Market Segment'!U75+'Premium Segment'!U75+'Closures Overlay'!U75+'Disposals Overlay'!U75 -> 0 | AA75: ='Value Segment'!V75+'Mid-Market Segment'!V75+'Upper Mid-Market Segment'!V75+'Premium Segment'!V75+'Closures Overlay'!V75+'Disposals Overlay'!V75 -> 10375982 | AB75: ='Value Segment'!W75+'Mid-Market Segment'!W75+'Upper Mid-Market Segment'!W75+'Premium Segment'!W75+'Closures Overlay'!W75+'Disposals Overlay'!W75 -> 0 | AC75: ='Value Segment'!X75+'Mid-Market Segment'!X75+'Upper Mid-Market Segment'!X75+'Premium Segment'!X75+'Closures Overlay'!X75+'Disposals Overlay'!X75 -> 0 | AD75: ='Value Segment'!Y75+'Mid-Market Segment'!Y75+'Upper Mid-Market Segment'!Y75+'Premium Segment'!Y75+'Closures Overlay'!Y75+'Disposals Overlay'!Y75 -> 0 | ... CD75: ='Value Segment'!BY75+'Mid-Market Segment'!BY75+'Upper Mid-Market Segment'!BY75+'Premium Segment'!BY75+'Closures Overlay'!BY75+'Disposals Overlay'!BY75 -> 0
E76: Surplus land disposal proceeds | I76: 0 | J76: 0 | K76: 0 | L76: 0 | N76: =SUMIF($W$2:$CD$2,N$3,$W76:$CD76) -> 0 | O76: =SUMIF($W$2:$CD$2,O$3,$W76:$CD76) -> 833333.33 | P76: =SUMIF($W$2:$CD$2,P$3,$W76:$CD76) -> 2500000 | Q76: =SUMIF($W$2:$CD$2,Q$3,$W76:$CD76) -> 4166666.7 | R76: =SUMIF($W$2:$CD$2,R$3,$W76:$CD76) -> 5000000 | S76: =SUMIF($W$2:$CD$2,S$3,$W76:$CD76) -> 5000000 | U76: =IFERROR(((S76/N76)^(1/5))-1,0) -> 0 | W76: ='Surplus Land Overlay'!R17 -> 0 | X76: ='Surplus Land Overlay'!S17 -> 0 | Y76: ='Surplus Land Overlay'!T17 -> 0 | Z76: ='Surplus Land Overlay'!U17 -> 0 | AA76: ='Surplus Land Overlay'!V17 -> 0 | AB76: ='Surplus Land Overlay'!W17 -> 0 | AC76: ='Surplus Land Overlay'!X17 -> 0 | AD76: ='Surplus Land Overlay'!Y17 -> 0 | ... CD76: ='Surplus Land Overlay'!BY17 -> 0
E77: Portfolio net cash flow | I77: =I71+SUM(I74:I76) -> 19304686 | J77: =J71+SUM(J74:J76) -> 20058354 | K77: =K71+SUM(K74:K76) -> 21433804 | L77: =L71+SUM(L74:L76) -> 20978588 | N77: =N71+SUM(N74:N76) -> 20965371 | O77: =O71+SUM(O74:O76) -> 44253020 | P77: =P71+SUM(P74:P76) -> 47534058 | Q77: =Q71+SUM(Q74:Q76) -> 50711112 | R77: =R71+SUM(R74:R76) -> 52933346 | S77: =S71+SUM(S74:S76) -> 54269597 | U77: =IFERROR(((S77/N77)^(1/5))-1,0) -> 0.20951375 | W77: =W71+SUM(W74:W76) -> 2008018.1 | X77: =X71+SUM(X74:X76) -> 2008018.1 | Y77: =Y71+SUM(Y74:Y76) -> 2008018.1 | Z77: =Z71+SUM(Z74:Z76) -> 2008018.1 | AA77: =AA71+SUM(AA74:AA76) -> 12384000 | AB77: =AB71+SUM(AB74:AB76) -> 355257.75 | AC77: =AC71+SUM(AC74:AC76) -> 2012249.3 | AD77: =AD71+SUM(AD74:AD76) -> 2012249.3 | ... CD77: =CD71+SUM(CD74:CD76) -> 1973086.6
C79: X | E79: Per Pub Basis
E81: BCF Volumes (Barrels) | I81: =I19/I$9 -> 156.10468 | J81: =J19/J$9 -> 152.45751 | K81: =K19/K$9 -> 146.58443 | L81: =L19/L$9 -> 144.69096 | N81: =IFERROR(N19/N$9,0) -> 149.90786 | O81: =SUMIF($W$2:$CD$2,O$3,$W81:$CD81) -> 151.59233 | P81: =SUMIF($W$2:$CD$2,P$3,$W81:$CD81) -> 154.32799 | Q81: =SUMIF($W$2:$CD$2,Q$3,$W81:$CD81) -> 156.99066 | R81: =SUMIF($W$2:$CD$2,R$3,$W81:$CD81) -> 159.71867 | S81: =SUMIF($W$2:$CD$2,S$3,$W81:$CD81) -> 162.44528 | U81: =IFERROR(((S81/N81)^(1/5))-1,0) -> 0.016193795 | W81: =IFERROR(W19/W$9,0) -> 12.492321 | X81: =IFERROR(X19/X$9,0) -> 12.492321 | Y81: =IFERROR(Y19/Y$9,0) -> 12.492321 | Z81: =IFERROR(Z19/Z$9,0) -> 12.492321 | AA81: =IFERROR(AA19/AA$9,0) -> 12.492321 | AB81: =IFERROR(AB19/AB$9,0) -> 12.481143 | AC81: =IFERROR(AC19/AC$9,0) -> 12.776942 | AD81: =IFERROR(AD19/AD$9,0) -> 12.776942 | ... CD81: =IFERROR(CD19/CD$9,0) -> 13.784135
E83: BCF
E84: BCF gross sales | I84: =I22/I$9 -> 106010.29 | J84: =J22/J$9 -> 111103.08 | K84: =K22/K$9 -> 111177.25 | L84: =L22/L$9 -> 111155.13 | N84: =IFERROR(N22/N$9,0) -> 116554.81 | O84: =SUMIF($W$2:$CD$2,O$3,$W84:$CD84) -> 122284.1 | P84: =SUMIF($W$2:$CD$2,P$3,$W84:$CD84) -> 129033.14 | Q84: =SUMIF($W$2:$CD$2,Q$3,$W84:$CD84) -> 135887.04 | R84: =SUMIF($W$2:$CD$2,R$3,$W84:$CD84) -> 142932.88 | S84: =SUMIF($W$2:$CD$2,S$3,$W84:$CD84) -> 150301.52 | U84: =IFERROR(((S84/N84)^(1/5))-1,0) -> 0.052171743 | W84: =IFERROR(W22/W$9,0) -> 10077.075 | X84: =IFERROR(X22/X$9,0) -> 10077.075 | Y84: =IFERROR(Y22/Y$9,0) -> 10077.075 | Z84: =IFERROR(Z22/Z$9,0) -> 10077.075 | AA84: =IFERROR(AA22/AA$9,0) -> 10077.075 | AB84: =IFERROR(AB22/AB$9,0) -> 10068.057 | AC84: =IFERROR(AC22/AC$9,0) -> 10306.735 | AD84: =IFERROR(AD22/AD$9,0) -> 10306.735 | ... CD84: =IFERROR(CD22/CD$9,0) -> 12753.82
E85: (-) BCF cost of sales | I85: =I23/I$9 -> -37035.929 | J85: =J23/J$9 -> -37199.434 | K85: =K23/K$9 -> -36287.954 | L85: =L23/L$9 -> -35901.358 | N85: =IFERROR(N23/N$9,0) -> -37126.771 | O85: =SUMIF($W$2:$CD$2,O$3,$W85:$CD85) -> -37916.956 | P85: =SUMIF($W$2:$CD$2,P$3,$W85:$CD85) -> -38989.046 | Q85: =SUMIF($W$2:$CD$2,Q$3,$W85:$CD85) -> -40064.099 | R85: =SUMIF($W$2:$CD$2,R$3,$W85:$CD85) -> -41178.118 | S85: =SUMIF($W$2:$CD$2,S$3,$W85:$CD85) -> -42314.848 | U85: =IFERROR(((S85/N85)^(1/5))-1,0) -> 0.026505127 | W85: =IFERROR(W23/W$9,0) -> -3124.5447 | X85: =IFERROR(X23/X$9,0) -> -3124.5447 | Y85: =IFERROR(Y23/Y$9,0) -> -3124.5447 | Z85: =IFERROR(Z23/Z$9,0) -> -3124.5447 | AA85: =IFERROR(AA23/AA$9,0) -> -3124.5447 | AB85: =IFERROR(AB23/AB$9,0) -> -3121.7487 | AC85: =IFERROR(AC23/AC$9,0) -> -3195.9172 | AD85: =IFERROR(AD23/AD$9,0) -> -3195.9172 | ... CD85: =IFERROR(CD23/CD$9,0) -> -3590.8172
E86: (-) BCF dist & disp | I86: =I24/I$9 -> -6168.4669 | J86: =J24/J$9 -> -6380.0211 | K86: =K24/K$9 -> -6284.6541 | L86: =L24/L$9 -> -6368.8157 | N86: =IFERROR(N24/N$9,0) -> -6879.2937 | O86: =SUMIF($W$2:$CD$2,O$3,$W86:$CD86) -> -7096.3083 | P86: =SUMIF($W$2:$CD$2,P$3,$W86:$CD86) -> -7369.869 | Q86: =SUMIF($W$2:$CD$2,Q$3,$W86:$CD86) -> -7647.9689 | R86: =SUMIF($W$2:$CD$2,R$3,$W86:$CD86) -> -7937.5754 | S86: =SUMIF($W$2:$CD$2,S$3,$W86:$CD86) -> -8235.7254 | U86: =IFERROR(((S86/N86)^(1/5))-1,0) -> 0.036648685 | W86: =IFERROR(W24/W$9,0) -> -584.73996 | X86: =IFERROR(X24/X$9,0) -> -584.73996 | Y86: =IFERROR(Y24/Y$9,0) -> -584.73996 | Z86: =IFERROR(Z24/Z$9,0) -> -584.73996 | AA86: =IFERROR(AA24/AA$9,0) -> -584.73996 | AB86: =IFERROR(AB24/AB$9,0) -> -584.21671 | AC86: =IFERROR(AC24/AC$9,0) -> -598.15948 | AD86: =IFERROR(AD24/AD$9,0) -> -598.15948 | ... CD86: =IFERROR(CD24/CD$9,0) -> -698.9178
E87: BCF gross commission | I87: =I25/I$9 -> 62805.89 | J87: =J25/J$9 -> 67523.628 | K87: =K25/K$9 -> 68604.646 | L87: =L25/L$9 -> 68884.958 | N87: =IFERROR(N25/N$9,0) -> 72548.747 | O87: =SUMIF($W$2:$CD$2,O$3,$W87:$CD87) -> 77270.838 | P87: =SUMIF($W$2:$CD$2,P$3,$W87:$CD87) -> 82674.223 | Q87: =SUMIF($W$2:$CD$2,Q$3,$W87:$CD87) -> 88174.975 | R87: =SUMIF($W$2:$CD$2,R$3,$W87:$CD87) -> 93817.184 | S87: =SUMIF($W$2:$CD$2,S$3,$W87:$CD87) -> 99750.948 | U87: =IFERROR(((S87/N87)^(1/5))-1,0) -> 0.065755108 | W87: =IFERROR(W25/W$9,0) -> 6367.7901 | X87: =IFERROR(X25/X$9,0) -> 6367.7901 | Y87: =IFERROR(Y25/Y$9,0) -> 6367.7901 | Z87: =IFERROR(Z25/Z$9,0) -> 6367.7901 | AA87: =IFERROR(AA25/AA$9,0) -> 6367.7901 | AB87: =IFERROR(AB25/AB$9,0) -> 6362.0918 | AC87: =IFERROR(AC25/AC$9,0) -> 6512.6581 | AD87: =IFERROR(AD25/AD$9,0) -> 6512.6581 | ... CD87: =IFERROR(CD25/CD$9,0) -> 8464.0849
E88: (-) BCF discounts | I88: =I26/I$9 -> -20235.113 | J88: =J26/J$9 -> -21416.02 | K88: =K26/K$9 -> -22045.634 | L88: =L26/L$9 -> -22138.455 | N88: =IFERROR(N26/N$9,0) -> -23573.429 | O88: =SUMIF($W$2:$CD$2,O$3,$W88:$CD88) -> -24899.587 | P88: =SUMIF($W$2:$CD$2,P$3,$W88:$CD88) -> -26437.231 | Q88: =SUMIF($W$2:$CD$2,Q$3,$W88:$CD88) -> -28001.923 | R88: =SUMIF($W$2:$CD$2,R$3,$W88:$CD88) -> -29609.447 | S88: =SUMIF($W$2:$CD$2,S$3,$W88:$CD88) -> -31293.17 | U88: =IFERROR(((S88/N88)^(1/5))-1,0) -> 0.058291625 | W88: =IFERROR(W26/W$9,0) -> -2052.2172 | X88: =IFERROR(X26/X$9,0) -> -2052.2172 | Y88: =IFERROR(Y26/Y$9,0) -> -2052.2172 | Z88: =IFERROR(Z26/Z$9,0) -> -2052.2172 | AA88: =IFERROR(AA26/AA$9,0) -> -2052.2172 | AB88: =IFERROR(AB26/AB$9,0) -> -2050.3807 | AC88: =IFERROR(AC26/AC$9,0) -> -2098.3504 | AD88: =IFERROR(AD26/AD$9,0) -> -2098.3504 | ... CD88: =IFERROR(CD26/CD$9,0) -> -2654.6144
E89: BCF net commission | I89: =I27/I$9 -> 42570.777 | J89: =J27/J$9 -> 46107.608 | K89: =K27/K$9 -> 46559.012 | L89: =L27/L$9 -> 46746.503 | N89: =IFERROR(N27/N$9,0) -> 48975.318 | O89: =SUMIF($W$2:$CD$2,O$3,$W89:$CD89) -> 52371.252 | P89: =SUMIF($W$2:$CD$2,P$3,$W89:$CD89) -> 56236.992 | Q89: =SUMIF($W$2:$CD$2,Q$3,$W89:$CD89) -> 60173.052 | R89: =SUMIF($W$2:$CD$2,R$3,$W89:$CD89) -> 64207.737 | S89: =SUMIF($W$2:$CD$2,S$3,$W89:$CD89) -> 68457.778 | U89: =IFERROR(((S89/N89)^(1/5))-1,0) -> 0.069274246 | W89: =IFERROR(W27/W$9,0) -> 4315.5729 | X89: =IFERROR(X27/X$9,0) -> 4315.5729 | Y89: =IFERROR(Y27/Y$9,0) -> 4315.5729 | Z89: =IFERROR(Z27/Z$9,0) -> 4315.5729 | AA89: =IFERROR(AA27/AA$9,0) -> 4315.5729 | AB89: =IFERROR(AB27/AB$9,0) -> 4311.7111 | AC89: =IFERROR(AC27/AC$9,0) -> 4414.3078 | AD89: =IFERROR(AD27/AD$9,0) -> 4414.3078 | ... CD89: =IFERROR(CD27/CD$9,0) -> 5809.4705
E91: WSM
E92: WSM gross sales | I92: =I31/I$9 -> 11675.533 | J92: =J31/J$9 -> 10597.217 | K92: =K31/K$9 -> 9409.9234 | L92: =L31/L$9 -> 9058.8531 | N92: =IFERROR(N31/N$9,0) -> 9675.1195 | O92: =SUMIF($W$2:$CD$2,O$3,$W92:$CD92) -> 9783.6395 | P92: =SUMIF($W$2:$CD$2,P$3,$W92:$CD92) -> 9959.9951 | Q92: =SUMIF($W$2:$CD$2,Q$3,$W92:$CD92) -> 10131.675 | R92: =SUMIF($W$2:$CD$2,R$3,$W92:$CD92) -> 10307.492 | S92: =SUMIF($W$2:$CD$2,S$3,$W92:$CD92) -> 10483.128 | U92: =IFERROR(((S92/N92)^(1/5))-1,0) -> 0.016171257 | W92: =IFERROR(W31/W$9,0) -> 806.25996 | X92: =IFERROR(X31/X$9,0) -> 806.25996 | Y92: =IFERROR(Y31/Y$9,0) -> 806.25996 | Z92: =IFERROR(Z31/Z$9,0) -> 806.25996 | AA92: =IFERROR(AA31/AA$9,0) -> 806.25996 | AB92: =IFERROR(AB31/AB$9,0) -> 805.53847 | AC92: =IFERROR(AC31/AC$9,0) -> 824.59671 | AD92: =IFERROR(AD31/AD$9,0) -> 824.59671 | ... CD92: =IFERROR(CD31/CD$9,0) -> 889.48774
E93: (-) WSM cost of sales | I93: =I32/I$9 -> -6887.2387 | J93: =J32/J$9 -> -6023.0116 | K93: =K32/K$9 -> -4993.6628 | L93: =L32/L$9 -> -4727.5474 | N93: =IFERROR(N32/N$9,0) -> -4891.8159 | O93: =SUMIF($W$2:$CD$2,O$3,$W93:$CD93) -> -4946.7212 | P93: =SUMIF($W$2:$CD$2,P$3,$W93:$CD93) -> -5035.9428 | Q93: =SUMIF($W$2:$CD$2,Q$3,$W93:$CD93) -> -5122.7994 | R93: =SUMIF($W$2:$CD$2,R$3,$W93:$CD93) -> -5211.7576 | S93: =SUMIF($W$2:$CD$2,S$3,$W93:$CD93) -> -5300.6334 | U93: =IFERROR(((S93/N93)^(1/5))-1,0) -> 0.016182079 | W93: =IFERROR(W32/W$9,0) -> -407.65133 | X93: =IFERROR(X32/X$9,0) -> -407.65133 | Y93: =IFERROR(Y32/Y$9,0) -> -407.65133 | Z93: =IFERROR(Z32/Z$9,0) -> -407.65133 | AA93: =IFERROR(AA32/AA$9,0) -> -407.65133 | AB93: =IFERROR(AB32/AB$9,0) -> -407.28654 | AC93: =IFERROR(AC32/AC$9,0) -> -416.92864 | AD93: =IFERROR(AD32/AD$9,0) -> -416.92864 | ... CD93: =IFERROR(CD32/CD$9,0) -> -449.76281
E94: (-) WSM dist & disp | I94: =I33/I$9 -> -1106.5489 | J94: =J33/J$9 -> -837.2149 | K94: =K33/K$9 -> -634.42627 | L94: =L33/L$9 -> -609.3262 | N94: =IFERROR(N33/N$9,0) -> -629.0507 | O94: =SUMIF($W$2:$CD$2,O$3,$W94:$CD94) -> -636.16145 | P94: =SUMIF($W$2:$CD$2,P$3,$W94:$CD94) -> -647.72063 | Q94: =SUMIF($W$2:$CD$2,Q$3,$W94:$CD94) -> -658.97471 | R94: =SUMIF($W$2:$CD$2,R$3,$W94:$CD94) -> -670.50637 | S94: =SUMIF($W$2:$CD$2,S$3,$W94:$CD94) -> -682.03498 | U94: =IFERROR(((S94/N94)^(1/5))-1,0) -> 0.01630532 | W94: =IFERROR(W33/W$9,0) -> -52.420892 | X94: =IFERROR(X33/X$9,0) -> -52.420892 | Y94: =IFERROR(Y33/Y$9,0) -> -52.420892 | Z94: =IFERROR(Z33/Z$9,0) -> -52.420892 | AA94: =IFERROR(AA33/AA$9,0) -> -52.420892 | AB94: =IFERROR(AB33/AB$9,0) -> -52.373983 | AC94: =IFERROR(AC33/AC$9,0) -> -53.622278 | AD94: =IFERROR(AD33/AD$9,0) -> -53.622278 | ... CD94: =IFERROR(CD33/CD$9,0) -> -57.87803
E95: WSM gross commission | I95: =I34/I$9 -> 3681.745 | J95: =J34/J$9 -> 3736.9906 | K95: =K34/K$9 -> 3781.8344 | L95: =L34/L$9 -> 3721.9795 | N95: =IFERROR(N34/N$9,0) -> 4154.2529 | O95: =SUMIF($W$2:$CD$2,O$3,$W95:$CD95) -> 4200.7569 | P95: =SUMIF($W$2:$CD$2,P$3,$W95:$CD95) -> 4276.3316 | Q95: =SUMIF($W$2:$CD$2,Q$3,$W95:$CD95) -> 4349.9004 | R95: =SUMIF($W$2:$CD$2,R$3,$W95:$CD95) -> 4425.2281 | S95: =SUMIF($W$2:$CD$2,S$3,$W95:$CD95) -> 4500.4593 | U95: =IFERROR(((S95/N95)^(1/5))-1,0) -> 0.016138206 | W95: =IFERROR(W34/W$9,0) -> 346.18774 | X95: =IFERROR(X34/X$9,0) -> 346.18774 | Y95: =IFERROR(Y34/Y$9,0) -> 346.18774 | Z95: =IFERROR(Z34/Z$9,0) -> 346.18774 | AA95: =IFERROR(AA34/AA$9,0) -> 346.18774 | AB95: =IFERROR(AB34/AB$9,0) -> 345.87795 | AC95: =IFERROR(AC34/AC$9,0) -> 354.04579 | AD95: =IFERROR(AD34/AD$9,0) -> 354.04579 | ... CD95: =IFERROR(CD34/CD$9,0) -> 381.8469
E96: (-) WSM discounts | I96: =I35/I$9 -> -896.52867 | J96: =J35/J$9 -> -539.30286 | K96: =K35/K$9 -> -477.50062 | L96: =L35/L$9 -> -455.78221 | N96: =IFERROR(N35/N$9,0) -> -466.17319 | O96: =SUMIF($W$2:$CD$2,O$3,$W96:$CD96) -> -471.31822 | P96: =SUMIF($W$2:$CD$2,P$3,$W96:$CD96) -> -479.70181 | Q96: =SUMIF($W$2:$CD$2,Q$3,$W96:$CD96) -> -487.86041 | R96: =SUMIF($W$2:$CD$2,R$3,$W96:$CD96) -> -496.18972 | S96: =SUMIF($W$2:$CD$2,S$3,$W96:$CD96) -> -504.48151 | U96: =IFERROR(((S96/N96)^(1/5))-1,0) -> 0.015920191 | W96: =IFERROR(W35/W$9,0) -> -38.847766 | X96: =IFERROR(X35/X$9,0) -> -38.847766 | Y96: =IFERROR(Y35/Y$9,0) -> -38.847766 | Z96: =IFERROR(Z35/Z$9,0) -> -38.847766 | AA96: =IFERROR(AA35/AA$9,0) -> -38.847766 | AB96: =IFERROR(AB35/AB$9,0) -> -38.813003 | AC96: =IFERROR(AC35/AC$9,0) -> -39.717319 | AD96: =IFERROR(AD35/AD$9,0) -> -39.717319 | ... CD96: =IFERROR(CD35/CD$9,0) -> -42.785514
E97: WSM net commission | I97: =I36/I$9 -> 2785.2164 | J97: =J36/J$9 -> 3197.6878 | K97: =K36/K$9 -> 3304.3338 | L97: =L36/L$9 -> 3266.1973 | N97: =IFERROR(N36/N$9,0) -> 3688.0797 | O97: =SUMIF($W$2:$CD$2,O$3,$W97:$CD97) -> 3729.4387 | P97: =SUMIF($W$2:$CD$2,P$3,$W97:$CD97) -> 3796.6298 | Q97: =SUMIF($W$2:$CD$2,Q$3,$W97:$CD97) -> 3862.04 | R97: =SUMIF($W$2:$CD$2,R$3,$W97:$CD97) -> 3929.0384 | S97: =SUMIF($W$2:$CD$2,S$3,$W97:$CD97) -> 3995.9777 | U97: =IFERROR(((S97/N97)^(1/5))-1,0) -> 0.01616575 | W97: =IFERROR(W36/W$9,0) -> 307.33997 | X97: =IFERROR(X36/X$9,0) -> 307.33997 | Y97: =IFERROR(Y36/Y$9,0) -> 307.33997 | Z97: =IFERROR(Z36/Z$9,0) -> 307.33997 | AA97: =IFERROR(AA36/AA$9,0) -> 307.33997 | AB97: =IFERROR(AB36/AB$9,0) -> 307.06495 | AC97: =IFERROR(AC36/AC$9,0) -> 314.32847 | AD97: =IFERROR(AD36/AD$9,0) -> 314.32847 | ... CD97: =IFERROR(CD36/CD$9,0) -> 339.06139
E99: Drinks gross profit (BCF + WSM) | I99: =I39/I$9 -> 45355.993 | J99: =J39/J$9 -> 49305.296 | K99: =K39/K$9 -> 49863.346 | L99: =L39/L$9 -> 50012.7 | N99: =IFERROR(N39/N$9,0) -> 52663.397 | O99: =SUMIF($W$2:$CD$2,O$3,$W99:$CD99) -> 56100.69 | P99: =SUMIF($W$2:$CD$2,P$3,$W99:$CD99) -> 60033.622 | Q99: =SUMIF($W$2:$CD$2,Q$3,$W99:$CD99) -> 64035.092 | R99: =SUMIF($W$2:$CD$2,R$3,$W99:$CD99) -> 68136.775 | S99: =SUMIF($W$2:$CD$2,S$3,$W99:$CD99) -> 72453.755 | U99: =IFERROR(((S99/N99)^(1/5))-1,0) -> 0.065885135 | W99: =IFERROR(W39/W$9,0) -> 4622.9128 | X99: =IFERROR(X39/X$9,0) -> 4622.9128 | Y99: =IFERROR(Y39/Y$9,0) -> 4622.9128 | Z99: =IFERROR(Z39/Z$9,0) -> 4622.9128 | AA99: =IFERROR(AA39/AA$9,0) -> 4622.9128 | AB99: =IFERROR(AB39/AB$9,0) -> 4618.776 | AC99: =IFERROR(AC39/AC$9,0) -> 4728.6362 | AD99: =IFERROR(AD39/AD$9,0) -> 4728.6362 | ... CD99: =IFERROR(CD39/CD$9,0) -> 6148.5319
E101: Rental income
E102: Rental income | I102: =I43/I$9 -> 31850.899 | J102: =J43/J$9 -> 32499.041 | K102: =K43/K$9 -> 32472.775 | L102: =L43/L$9 -> 32433.465 | N102: =IFERROR(N43/N$9,0) -> 32480.725 | O102: =SUMIF($W$2:$CD$2,O$3,$W102:$CD102) -> 33966.934 | P102: =SUMIF($W$2:$CD$2,P$3,$W102:$CD102) -> 35831.718 | Q102: =SUMIF($W$2:$CD$2,Q$3,$W102:$CD102) -> 37738.925 | R102: =SUMIF($W$2:$CD$2,R$3,$W102:$CD102) -> 39647.571 | S102: =SUMIF($W$2:$CD$2,S$3,$W102:$CD102) -> 41602.904 | U102: =IFERROR(((S102/N102)^(1/5))-1,0) -> 0.050750457 | W102: =IFERROR(W43/W$9,0) -> 2787.3163 | X102: =IFERROR(X43/X$9,0) -> 2787.3163 | Y102: =IFERROR(Y43/Y$9,0) -> 2787.3163 | Z102: =IFERROR(Z43/Z$9,0) -> 2787.3163 | AA102: =IFERROR(AA43/AA$9,0) -> 2787.3163 | AB102: =IFERROR(AB43/AB$9,0) -> 2784.822 | AC102: =IFERROR(AC43/AC$9,0) -> 2874.7077 | AD102: =IFERROR(AD43/AD$9,0) -> 2874.7077 | ... CD102: =IFERROR(CD43/CD$9,0) -> 3560.4824
E103: Tie Release Fees | I103: =I44/I$9 -> 2695.3006 | J103: =J44/J$9 -> 3040.6165 | K103: =K44/K$9 -> 3497.9963 | L103: =L44/L$9 -> 3844.4493 | N103: =IFERROR(N44/N$9,0) -> 4253.6999 | O103: =SUMIF($W$2:$CD$2,O$3,$W103:$CD103) -> 4400.4754 | P103: =SUMIF($W$2:$CD$2,P$3,$W103:$CD103) -> 4537.882 | Q103: =SUMIF($W$2:$CD$2,Q$3,$W103:$CD103) -> 4672.3973 | R103: =SUMIF($W$2:$CD$2,R$3,$W103:$CD103) -> 4781.2383 | S103: =SUMIF($W$2:$CD$2,S$3,$W103:$CD103) -> 4871.2223 | U103: =IFERROR(((S103/N103)^(1/5))-1,0) -> 0.027481996 | W103: =IFERROR(W44/W$9,0) -> 366.92668 | X103: =IFERROR(X44/X$9,0) -> 366.92668 | Y103: =IFERROR(Y44/Y$9,0) -> 366.92668 | Z103: =IFERROR(Z44/Z$9,0) -> 366.92668 | AA103: =IFERROR(AA44/AA$9,0) -> 366.92668 | AB103: =IFERROR(AB44/AB$9,0) -> 366.59833 | AC103: =IFERROR(AC44/AC$9,0) -> 366.59833 | AD103: =IFERROR(AD44/AD$9,0) -> 366.59833 | ... CD103: =IFERROR(CD44/CD$9,0) -> 405.11249
E104: Total rental income | I104: =I45/I$9 -> 34546.2 | J104: =J45/J$9 -> 35539.657 | K104: =K45/K$9 -> 35970.771 | L104: =L45/L$9 -> 36277.914 | N104: =IFERROR(N45/N$9,0) -> 36734.424 | O104: =SUMIF($W$2:$CD$2,O$3,$W104:$CD104) -> 38367.409 | P104: =SUMIF($W$2:$CD$2,P$3,$W104:$CD104) -> 40369.6 | Q104: =SUMIF($W$2:$CD$2,Q$3,$W104:$CD104) -> 42411.322 | R104: =SUMIF($W$2:$CD$2,R$3,$W104:$CD104) -> 44428.809 | S104: =SUMIF($W$2:$CD$2,S$3,$W104:$CD104) -> 46474.126 | U104: =IFERROR(((S104/N104)^(1/5))-1,0) -> 0.04816004 | W104: =IFERROR(W45/W$9,0) -> 3154.243 | X104: =IFERROR(X45/X$9,0) -> 3154.243 | Y104: =IFERROR(Y45/Y$9,0) -> 3154.243 | Z104: =IFERROR(Z45/Z$9,0) -> 3154.243 | AA104: =IFERROR(AA45/AA$9,0) -> 3154.243 | AB104: =IFERROR(AB45/AB$9,0) -> 3151.4204 | AC104: =IFERROR(AC45/AC$9,0) -> 3241.306 | AD104: =IFERROR(AD45/AD$9,0) -> 3241.306 | ... CD104: =IFERROR(CD45/CD$9,0) -> 3965.5949
E106: Ancillary income
E107: Other income | I107: =I48/I$9 -> 201.37701 | J107: =J48/J$9 -> 130.44331 | K107: =K48/K$9 -> 159.14662 | L107: =L48/L$9 -> 236.36451 | N107: =IFERROR(N48/N$9,0) -> 69.957529 | O107: =SUMIF($W$2:$CD$2,O$3,$W107:$CD107) -> 69.915509 | P107: =SUMIF($W$2:$CD$2,P$3,$W107:$CD107) -> 69.782057 | Q107: =SUMIF($W$2:$CD$2,Q$3,$W107:$CD107) -> 69.632812 | R107: =SUMIF($W$2:$CD$2,R$3,$W107:$CD107) -> 69.464793 | S107: =SUMIF($W$2:$CD$2,S$3,$W107:$CD107) -> 69.274219 | U107: =IFERROR(((S107/N107)^(1/5))-1,0) -> -0.0019611791 | W107: =IFERROR(W48/W$9,0) -> 5.8297941 | X107: =IFERROR(X48/X$9,0) -> 5.8297941 | Y107: =IFERROR(Y48/Y$9,0) -> 5.8297941 | Z107: =IFERROR(Z48/Z$9,0) -> 5.8297941 | AA107: =IFERROR(AA48/AA$9,0) -> 5.8297941 | AB107: =IFERROR(AB48/AB$9,0) -> 5.8245773 | AC107: =IFERROR(AC48/AC$9,0) -> 5.8245773 | AD107: =IFERROR(AD48/AD$9,0) -> 5.8245773 | ... CD107: =IFERROR(CD48/CD$9,0) -> 5.7611518
E108: Machines income | I108: =I49/I$9 -> 2123.748 | J108: =J49/J$9 -> 2021.2833 | K108: =K49/K$9 -> 1978.9726 | L108: =L49/L$9 -> 1988.9976 | N108: =IFERROR(N49/N$9,0) -> 2017.9079 | O108: =SUMIF($W$2:$CD$2,O$3,$W108:$CD108) -> 2016.6958 | P108: =SUMIF($W$2:$CD$2,P$3,$W108:$CD108) -> 2012.8464 | Q108: =SUMIF($W$2:$CD$2,Q$3,$W108:$CD108) -> 2008.5415 | R108: =SUMIF($W$2:$CD$2,R$3,$W108:$CD108) -> 2003.695 | S108: =SUMIF($W$2:$CD$2,S$3,$W108:$CD108) -> 1998.1979 | U108: =IFERROR(((S108/N108)^(1/5))-1,0) -> -0.0019611791 | W108: =IFERROR(W49/W$9,0) -> 168.15899 | X108: =IFERROR(X49/X$9,0) -> 168.15899 | Y108: =IFERROR(Y49/Y$9,0) -> 168.15899 | Z108: =IFERROR(Z49/Z$9,0) -> 168.15899 | AA108: =IFERROR(AA49/AA$9,0) -> 168.15899 | AB108: =IFERROR(AB49/AB$9,0) -> 168.00851 | AC108: =IFERROR(AC49/AC$9,0) -> 168.00851 | AD108: =IFERROR(AD49/AD$9,0) -> 168.00851 | ... CD108: =IFERROR(CD49/CD$9,0) -> 166.17902
E109: F&F income | I109: =I50/I$9 -> 570.4713 | J109: =J50/J$9 -> 840.20253 | K109: =K50/K$9 -> 1133.1151 | L109: =L50/L$9 -> 1264.6787 | N109: =IFERROR(N50/N$9,0) -> 1296.4571 | O109: =SUMIF($W$2:$CD$2,O$3,$W109:$CD109) -> 1295.6783 | P109: =SUMIF($W$2:$CD$2,P$3,$W109:$CD109) -> 1293.2052 | Q109: =SUMIF($W$2:$CD$2,Q$3,$W109:$CD109) -> 1290.4394 | R109: =SUMIF($W$2:$CD$2,R$3,$W109:$CD109) -> 1287.3257 | S109: =SUMIF($W$2:$CD$2,S$3,$W109:$CD109) -> 1283.7939 | U109: =IFERROR(((S109/N109)^(1/5))-1,0) -> -0.0019611791 | W109: =IFERROR(W50/W$9,0) -> 108.03809 | X109: =IFERROR(X50/X$9,0) -> 108.03809 | Y109: =IFERROR(Y50/Y$9,0) -> 108.03809 | Z109: =IFERROR(Z50/Z$9,0) -> 108.03809 | AA109: =IFERROR(AA50/AA$9,0) -> 108.03809 | AB109: =IFERROR(AB50/AB$9,0) -> 107.94141 | AC109: =IFERROR(AC50/AC$9,0) -> 107.94141 | AD109: =IFERROR(AD50/AD$9,0) -> 107.94141 | ... CD109: =IFERROR(CD50/CD$9,0) -> 106.766
E110: Insurance income | I110: =I51/I$9 -> 2557.7785 | J110: =J51/J$9 -> 2832.5678 | K110: =K51/K$9 -> 2972.6067 | L110: =L51/L$9 -> 3024.0755 | N110: =IFERROR(N51/N$9,0) -> 2994.5802 | O110: =SUMIF($W$2:$CD$2,O$3,$W110:$CD110) -> 2992.7815 | P110: =SUMIF($W$2:$CD$2,P$3,$W110:$CD110) -> 2987.069 | Q110: =SUMIF($W$2:$CD$2,Q$3,$W110:$CD110) -> 2980.6805 | R110: =SUMIF($W$2:$CD$2,R$3,$W110:$CD110) -> 2973.4883 | S110: =SUMIF($W$2:$CD$2,S$3,$W110:$CD110) -> 2965.3306 | U110: =IFERROR(((S110/N110)^(1/5))-1,0) -> -0.0019611791 | W110: =IFERROR(W51/W$9,0) -> 249.54835 | X110: =IFERROR(X51/X$9,0) -> 249.54835 | Y110: =IFERROR(Y51/Y$9,0) -> 249.54835 | Z110: =IFERROR(Z51/Z$9,0) -> 249.54835 | AA110: =IFERROR(AA51/AA$9,0) -> 249.54835 | AB110: =IFERROR(AB51/AB$9,0) -> 249.32504 | AC110: =IFERROR(AC51/AC$9,0) -> 249.32504 | AD110: =IFERROR(AD51/AD$9,0) -> 249.32504 | ... CD110: =IFERROR(CD51/CD$9,0) -> 246.61007
E111: Total other income | I111: =I52/I$9 -> 5453.3748 | J111: =J52/J$9 -> 5824.4969 | K111: =K52/K$9 -> 6243.841 | L111: =L52/L$9 -> 6514.1163 | N111: =IFERROR(N52/N$9,0) -> 6378.9027 | O111: =SUMIF($W$2:$CD$2,O$3,$W111:$CD111) -> 6375.0712 | P111: =SUMIF($W$2:$CD$2,P$3,$W111:$CD111) -> 6362.9027 | Q111: =SUMIF($W$2:$CD$2,Q$3,$W111:$CD111) -> 6349.2942 | R111: =SUMIF($W$2:$CD$2,R$3,$W111:$CD111) -> 6333.9738 | S111: =SUMIF($W$2:$CD$2,S$3,$W111:$CD111) -> 6316.5967 | U111: =IFERROR(((S111/N111)^(1/5))-1,0) -> -0.0019611791 | W111: =IFERROR(W52/W$9,0) -> 531.57522 | X111: =IFERROR(X52/X$9,0) -> 531.57522 | Y111: =IFERROR(Y52/Y$9,0) -> 531.57522 | Z111: =IFERROR(Z52/Z$9,0) -> 531.57522 | AA111: =IFERROR(AA52/AA$9,0) -> 531.57522 | AB111: =IFERROR(AB52/AB$9,0) -> 531.09954 | AC111: =IFERROR(AC52/AC$9,0) -> 531.09954 | AD111: =IFERROR(AD52/AD$9,0) -> 531.09954 | ... CD111: =IFERROR(CD52/CD$9,0) -> 525.31624
E113: Net income (drinks GP + rent + other income) | I113: =I54/I$9 -> 85355.568 | J113: =J54/J$9 -> 90669.45 | K113: =K54/K$9 -> 92077.958 | L113: =L54/L$9 -> 92804.731 | N113: =IFERROR(N54/N$9,0) -> 95776.725 | O113: =SUMIF($W$2:$CD$2,O$3,$W113:$CD113) -> 100843.17 | P113: =SUMIF($W$2:$CD$2,P$3,$W113:$CD113) -> 106766.12 | Q113: =SUMIF($W$2:$CD$2,Q$3,$W113:$CD113) -> 112795.71 | R113: =SUMIF($W$2:$CD$2,R$3,$W113:$CD113) -> 118899.56 | S113: =SUMIF($W$2:$CD$2,S$3,$W113:$CD113) -> 125244.48 | U113: =IFERROR(((S113/N113)^(1/5))-1,0) -> 0.055114816 | W113: =IFERROR(W54/W$9,0) -> 8308.731 | X113: =IFERROR(X54/X$9,0) -> 8308.731 | Y113: =IFERROR(Y54/Y$9,0) -> 8308.731 | Z113: =IFERROR(Z54/Z$9,0) -> 8308.731 | AA113: =IFERROR(AA54/AA$9,0) -> 8308.731 | AB113: =IFERROR(AB54/AB$9,0) -> 8301.2959 | AC113: =IFERROR(AC54/AC$9,0) -> 8501.0418 | AD113: =IFERROR(AD54/AD$9,0) -> 8501.0418 | ... CD113: =IFERROR(CD54/CD$9,0) -> 10639.443
E115: Pub costs
E116: R&M | I116: =I57/I$9 -> -2032.9866 | J116: =J57/J$9 -> -2835.667 | K116: =K57/K$9 -> -1891.0992 | L116: =L57/L$9 -> -1833.4092 | N116: =IFERROR(N57/N$9,0) -> -1872.7568 | O116: =SUMIF($W$2:$CD$2,O$3,$W116:$CD116) -> -1909.0646 | P116: =SUMIF($W$2:$CD$2,P$3,$W116:$CD116) -> -1943.529 | Q116: =SUMIF($W$2:$CD$2,Q$3,$W116:$CD116) -> -1978.1598 | R116: =SUMIF($W$2:$CD$2,R$3,$W116:$CD116) -> -2012.8544 | S116: =SUMIF($W$2:$CD$2,S$3,$W116:$CD116) -> -2047.4788 | U116: =IFERROR(((S116/N116)^(1/5))-1,0) -> 0.017999597 | W116: =IFERROR(W57/W$9,0) -> -159.18433 | X116: =IFERROR(X57/X$9,0) -> -159.18433 | Y116: =IFERROR(Y57/Y$9,0) -> -159.18433 | Z116: =IFERROR(Z57/Z$9,0) -> -159.18433 | AA116: =IFERROR(AA57/AA$9,0) -> -159.18433 | AB116: =IFERROR(AB57/AB$9,0) -> -159.04188 | AC116: =IFERROR(AC57/AC$9,0) -> -159.04188 | AD116: =IFERROR(AD57/AD$9,0) -> -159.04188 | ... CD116: =IFERROR(CD57/CD$9,0) -> -170.27743
E117: Marketing Support | I117: =I58/I$9 -> -318.96224 | J117: =J58/J$9 -> -309.27958 | K117: =K58/K$9 -> -346.38581 | L117: =L58/L$9 -> -293.30526 | N117: =IFERROR(N58/N$9,0) -> -284.02617 | O117: =SUMIF($W$2:$CD$2,O$3,$W117:$CD117) -> -289.53268 | P117: =SUMIF($W$2:$CD$2,P$3,$W117:$CD117) -> -294.75963 | Q117: =SUMIF($W$2:$CD$2,Q$3,$W117:$CD117) -> -300.0118 | R117: =SUMIF($W$2:$CD$2,R$3,$W117:$CD117) -> -305.27365 | S117: =SUMIF($W$2:$CD$2,S$3,$W117:$CD117) -> -310.52487 | U117: =IFERROR(((S117/N117)^(1/5))-1,0) -> 0.017999597 | W117: =IFERROR(W58/W$9,0) -> -24.142224 | X117: =IFERROR(X58/X$9,0) -> -24.142224 | Y117: =IFERROR(Y58/Y$9,0) -> -24.142224 | Z117: =IFERROR(Z58/Z$9,0) -> -24.142224 | AA117: =IFERROR(AA58/AA$9,0) -> -24.142224 | AB117: =IFERROR(AB58/AB$9,0) -> -24.12062 | AC117: =IFERROR(AC58/AC$9,0) -> -24.12062 | AD117: =IFERROR(AD58/AD$9,0) -> -24.12062 | ... CD117: =IFERROR(CD58/CD$9,0) -> -25.824627
E118: Total pub costs | I118: =I59/I$9 -> -2351.9488 | J118: =J59/J$9 -> -3144.9466 | K118: =K59/K$9 -> -2237.485 | L118: =L59/L$9 -> -2126.7144 | N118: =IFERROR(N59/N$9,0) -> -2156.783 | O118: =SUMIF($W$2:$CD$2,O$3,$W118:$CD118) -> -2198.5972 | P118: =SUMIF($W$2:$CD$2,P$3,$W118:$CD118) -> -2238.2887 | Q118: =SUMIF($W$2:$CD$2,Q$3,$W118:$CD118) -> -2278.1716 | R118: =SUMIF($W$2:$CD$2,R$3,$W118:$CD118) -> -2318.128 | S118: =SUMIF($W$2:$CD$2,S$3,$W118:$CD118) -> -2358.0037 | U118: =IFERROR(((S118/N118)^(1/5))-1,0) -> 0.017999597 | W118: =IFERROR(W59/W$9,0) -> -183.32655 | X118: =IFERROR(X59/X$9,0) -> -183.32655 | Y118: =IFERROR(Y59/Y$9,0) -> -183.32655 | Z118: =IFERROR(Z59/Z$9,0) -> -183.32655 | AA118: =IFERROR(AA59/AA$9,0) -> -183.32655 | AB118: =IFERROR(AB59/AB$9,0) -> -183.1625 | AC118: =IFERROR(AC59/AC$9,0) -> -183.1625 | AD118: =IFERROR(AD59/AD$9,0) -> -183.1625 | ... CD118: =IFERROR(CD59/CD$9,0) -> -196.10206
E120: Outlet EBITDA | I120: =I61/I$9 -> 83003.619 | J120: =J61/J$9 -> 87524.503 | K120: =K61/K$9 -> 89840.473 | L120: =L61/L$9 -> 90678.016 | N120: =IFERROR(N61/N$9,0) -> 93619.942 | O120: =IFERROR(O61/O$9,0) -> 102232.56 | P120: =IFERROR(P61/P$9,0) -> 108546.46 | Q120: =IFERROR(Q61/Q$9,0) -> 115023.87 | R120: =IFERROR(R61/R$9,0) -> 121642.4 | S120: =IFERROR(S61/S$9,0) -> 128590.91 | U120: =IFERROR(((S120/N120)^(1/5))-1,0) -> 0.065536614 | W120: =IFERROR(W61/W$9,0) -> 8125.4045 | X120: =IFERROR(X61/X$9,0) -> 8125.4045 | Y120: =IFERROR(Y61/Y$9,0) -> 8125.4045 | Z120: =IFERROR(Z61/Z$9,0) -> 8125.4045 | AA120: =IFERROR(AA61/AA$9,0) -> 8125.4045 | AB120: =IFERROR(AB61/AB$9,0) -> 8118.1334 | AC120: =IFERROR(AC61/AC$9,0) -> 8317.8793 | AD120: =IFERROR(AD61/AD$9,0) -> 8317.8793 | ... CD120: =IFERROR(CD61/CD$9,0) -> 10443.341
E122: Overheads | I122: =I64/I$9 -> -8100 | J122: =J64/J$9 -> -8100 | K122: =K64/K$9 -> -8100 | L122: =L64/L$9 -> -8100 | N122: =IFERROR(N64/N$9,0) -> -8700 | O122: =IFERROR(O64/O$9,0) -> -9240.3356 | P122: =IFERROR(P64/P$9,0) -> -9473.7791 | Q122: =IFERROR(Q64/Q$9,0) -> -9699.1409 | R122: =IFERROR(R64/R$9,0) -> -9914.7864 | S122: =IFERROR(S64/S$9,0) -> -10136.844 | U122: =IFERROR(((S122/N122)^(1/5))-1,0) -> 0.031042815 | W122: =IFERROR(W64/W$9,0) -> -742.89042 | X122: =IFERROR(X64/X$9,0) -> -742.89042 | Y122: =IFERROR(Y64/Y$9,0) -> -742.89042 | Z122: =IFERROR(Z64/Z$9,0) -> -742.89042 | AA122: =IFERROR(AA64/AA$9,0) -> -742.89042 | AB122: =IFERROR(AB64/AB$9,0) -> -742.89042 | AC122: =IFERROR(AC64/AC$9,0) -> -742.89042 | AD122: =IFERROR(AD64/AD$9,0) -> -742.89042 | ... CD122: =IFERROR(CD64/CD$9,0) -> -806.98337
E123: Corporate EBITDA | I123: =I65/I$9 -> 74903.619 | J123: =J65/J$9 -> 79424.503 | K123: =K65/K$9 -> 81740.473 | L123: =L65/L$9 -> 82578.016 | N123: =IFERROR(N65/N$9,0) -> 84919.942 | O123: =IFERROR(O65/O$9,0) -> 92992.226 | P123: =IFERROR(P65/P$9,0) -> 99072.677 | Q123: =IFERROR(Q65/Q$9,0) -> 105324.73 | R123: =IFERROR(R65/R$9,0) -> 111727.61 | S123: =IFERROR(S65/S$9,0) -> 118454.06 | U123: =IFERROR(((S123/N123)^(1/5))-1,0) -> 0.068828569 | W123: =IFERROR(W65/W$9,0) -> 7382.5141 | X123: =IFERROR(X65/X$9,0) -> 7382.5141 | Y123: =IFERROR(Y65/Y$9,0) -> 7382.5141 | Z123: =IFERROR(Z65/Z$9,0) -> 7382.5141 | AA123: =IFERROR(AA65/AA$9,0) -> 7382.5141 | AB123: =IFERROR(AB65/AB$9,0) -> 7375.243 | AC123: =IFERROR(AC65/AC$9,0) -> 7574.9888 | AD123: =IFERROR(AD65/AD$9,0) -> 7574.9888 | ... CD123: =IFERROR(CD65/CD$9,0) -> 9636.3576
E125: Maintenance capex | I125: =I68/I$9 -> -8381.561 | J125: =J68/J$9 -> -11667.743 | K125: =K68/K$9 -> -8647.9809 | L125: =L68/L$9 -> -9960.465 | N125: =IFERROR(N68/N$9,0) -> -9953.1693 | O125: =SUMIF($W$2:$CD$2,O$3,$W125:$CD125) -> -7890.3227 | P125: =SUMIF($W$2:$CD$2,P$3,$W125:$CD125) -> -8032.7672 | Q125: =SUMIF($W$2:$CD$2,Q$3,$W125:$CD125) -> -8175.8991 | R125: =SUMIF($W$2:$CD$2,R$3,$W125:$CD125) -> -8319.2946 | S125: =SUMIF($W$2:$CD$2,S$3,$W125:$CD125) -> -8462.4003 | U125: =IFERROR(((S125/N125)^(1/5))-1,0) -> -0.031930728 | W125: =IFERROR(W68/W$9,0) -> -657.92208 | X125: =IFERROR(X68/X$9,0) -> -657.92208 | Y125: =IFERROR(Y68/Y$9,0) -> -657.92208 | Z125: =IFERROR(Z68/Z$9,0) -> -657.92208 | AA125: =IFERROR(AA68/AA$9,0) -> -657.92208 | AB125: =IFERROR(AB68/AB$9,0) -> -657.33333 | AC125: =IFERROR(AC68/AC$9,0) -> -657.33333 | AD125: =IFERROR(AD68/AD$9,0) -> -657.33333 | ... CD125: =IFERROR(CD68/CD$9,0) -> -703.7708
E126: Bad debts | I126: =I69/I$9 -> -959.07143 | J126: =J69/J$9 -> -1773.5969 | K126: =K69/K$9 -> -1777.1069 | L126: =L69/L$9 -> -2217.6206 | N126: =IFERROR(N69/N$9,0) -> -1404.2991 | O126: =SUMIF($W$2:$CD$2,O$3,$W126:$CD126) -> -1479.6686 | P126: =SUMIF($W$2:$CD$2,P$3,$W126:$CD126) -> -1567.9175 | Q126: =SUMIF($W$2:$CD$2,Q$3,$W126:$CD126) -> -1657.7631 | R126: =SUMIF($W$2:$CD$2,R$3,$W126:$CD126) -> -1748.7215 | S126: =SUMIF($W$2:$CD$2,S$3,$W126:$CD126) -> -1843.2971 | U126: =IFERROR(((S126/N126)^(1/5))-1,0) -> 0.055910586 | W126: =IFERROR(W69/W$9,0) -> -121.88107 | X126: =IFERROR(X69/X$9,0) -> -121.88107 | Y126: =IFERROR(Y69/Y$9,0) -> -121.88107 | Z126: =IFERROR(Z69/Z$9,0) -> -121.88107 | AA126: =IFERROR(AA69/AA$9,0) -> -121.88107 | AB126: =IFERROR(AB69/AB$9,0) -> -121.772 | AC126: =IFERROR(AC69/AC$9,0) -> -124.76819 | AD126: =IFERROR(AD69/AD$9,0) -> -124.76819 | ... CD126: =IFERROR(CD69/CD$9,0) -> -156.65011
E127: Security costs re closed sites | I127: =I70/I$9 -> -124.5061 | J127: =J70/J$9 -> -410.48321 | K127: =K70/K$9 -> -355.64643 | L127: =L70/L$9 -> -379.00289 | N127: =IFERROR(N70/N$9,0) -> -974.02597 | O127: =SUMIF($W$2:$CD$2,O$3,$W127:$CD127) -> -1015.9263 | P127: =SUMIF($W$2:$CD$2,P$3,$W127:$CD127) -> -1097.52 | Q127: =SUMIF($W$2:$CD$2,Q$3,$W127:$CD127) -> -1187.3746 | R127: =SUMIF($W$2:$CD$2,R$3,$W127:$CD127) -> -1286.7643 | S127: =SUMIF($W$2:$CD$2,S$3,$W127:$CD127) -> -1399.7404 | U127: =IFERROR(((S127/N127)^(1/5))-1,0) -> 0.075215192 | W127: =IFERROR(W70/W$9,0) -> -83.171789 | X127: =IFERROR(X70/X$9,0) -> -83.171789 | Y127: =IFERROR(Y70/Y$9,0) -> -83.171789 | Z127: =IFERROR(Z70/Z$9,0) -> -83.171789 | AA127: =IFERROR(AA70/AA$9,0) -> -83.171789 | AB127: =IFERROR(AB70/AB$9,0) -> -85.389703 | AC127: =IFERROR(AC70/AC$9,0) -> -85.389703 | AD127: =IFERROR(AD70/AD$9,0) -> -85.389703 | ... CD127: =IFERROR(CD70/CD$9,0) -> -122.0483
E128: Normalised operating CF | I128: =I71/I$9 -> 65438.48 | J128: =J71/J$9 -> 65572.68 | K128: =K71/K$9 -> 70959.739 | L128: =L71/L$9 -> 70020.928 | N128: =IFERROR(N71/N$9,0) -> 72588.447 | O128: =SUMIF($W$2:$CD$2,O$3,$W128:$CD128) -> 79343.97 | P128: =SUMIF($W$2:$CD$2,P$3,$W128:$CD128) -> 84708.365 | Q128: =SUMIF($W$2:$CD$2,Q$3,$W128:$CD128) -> 90179.591 | R128: =SUMIF($W$2:$CD$2,R$3,$W128:$CD128) -> 95727.142 | S128: =SUMIF($W$2:$CD$2,S$3,$W128:$CD128) -> 101497.24 | U128: =IFERROR(((S128/N128)^(1/5))-1,0) -> 0.069343766 | W128: =IFERROR(W71/W$9,0) -> 6519.5391 | X128: =IFERROR(X71/X$9,0) -> 6519.5391 | Y128: =IFERROR(Y71/Y$9,0) -> 6519.5391 | Z128: =IFERROR(Z71/Z$9,0) -> 6519.5391 | AA128: =IFERROR(AA71/AA$9,0) -> 6519.5391 | AB128: =IFERROR(AB71/AB$9,0) -> 6510.748 | AC128: =IFERROR(AC71/AC$9,0) -> 6707.4976 | AD128: =IFERROR(AD71/AD$9,0) -> 6707.4976 | ... CD128: =IFERROR(CD71/CD$9,0) -> 8653.8884
E130: Growth capex | I130: =I74/$I$9 -> -2760.9281 | J130: =J74/$I$9 -> -448.15549 | K130: =K74/$I$9 -> -1369.4656 | L130: =L74/$I$9 -> -1908.63 | N130: =IFERROR(N74/N$9,0) -> -4519.0614 | O130: =SUMIF($W$2:$CD$2,O$3,$W130:$CD130) -> -5326.5555 | P130: =SUMIF($W$2:$CD$2,P$3,$W130:$CD130) -> -5444.0614 | Q130: =SUMIF($W$2:$CD$2,Q$3,$W130:$CD130) -> -5554.1762 | R130: =SUMIF($W$2:$CD$2,R$3,$W130:$CD130) -> -5655.0723 | S130: =SUMIF($W$2:$CD$2,S$3,$W130:$CD130) -> -5749.2847 | U130: =IFERROR(((S130/N130)^(1/5))-1,0) -> 0.049332474 | W130: =IFERROR(W74/W$9,0) -> 0 | X130: =IFERROR(X74/X$9,0) -> 0 | Y130: =IFERROR(Y74/Y$9,0) -> 0 | Z130: =IFERROR(Z74/Z$9,0) -> 0 | AA130: =IFERROR(AA74/AA$9,0) -> 0 | AB130: =IFERROR(AB74/AB$9,0) -> -5326.5555 | AC130: =IFERROR(AC74/AC$9,0) -> 0 | AD130: =IFERROR(AD74/AD$9,0) -> 0 | ... CD130: =IFERROR(CD74/CD$9,0) -> 0
E131: Asset disposal proceeds | I131: =I75/$I$9 -> 0 | J131: =J75/$I$9 -> 0 | K131: =K75/$I$9 -> 0 | L131: =L75/$I$9 -> 0 | N131: =IFERROR(N75/N$9,0) -> 0 | O131: =SUMIF($W$2:$CD$2,O$3,$W131:$CD131) -> 69125.862 | P131: =SUMIF($W$2:$CD$2,P$3,$W131:$CD131) -> 77470.961 | Q131: =SUMIF($W$2:$CD$2,Q$3,$W131:$CD131) -> 86920.806 | R131: =SUMIF($W$2:$CD$2,R$3,$W131:$CD131) -> 97664.432 | S131: =SUMIF($W$2:$CD$2,S$3,$W131:$CD131) -> 110122.09 | U131: =IFERROR(((S131/N131)^(1/5))-1,0) -> 0 | W131: =IFERROR(W75/W$9,0) -> 0 | X131: =IFERROR(X75/X$9,0) -> 0 | Y131: =IFERROR(Y75/Y$9,0) -> 0 | Z131: =IFERROR(Z75/Z$9,0) -> 0 | AA131: =IFERROR(AA75/AA$9,0) -> 33688.254 | AB131: =IFERROR(AB75/AB$9,0) -> 0 | AC131: =IFERROR(AC75/AC$9,0) -> 0 | AD131: =IFERROR(AD75/AD$9,0) -> 0 | ... CD131: =IFERROR(CD75/CD$9,0) -> 0
...

Sheet Portfolio>>>

Sheet Value Segment
